{"average":[{"i":"necrozma_dusk_mane","n":"Necrozma (Dusk Mane)","f":"METAL_CLAW","c":"SUNSTEEL_STRIKE","cp":4099,"lv":40,"d":55.35,"d0":54.55,"d1":57.42,"dp":100,"m":0,"m0":0,"m1":0,"td":600,"td0":600,"td1":600,"e":0.06,"e0":0.06,"e1":0.06,"tw":10.8,"er":100.43,"bu":0.3,"bd":7.1},{"i":"zacian_crowned_sword","n":"Zacian (Crowned Sword)","f":"METAL_CLAW","c":"BEHEMOTH_BLADE","cp":4979,"lv":40,"d":55.35,"d0":54.55,"d1":57.42,"dp":100,"m":0,"m0":0,"m1":0,"td":600,"td0":600,"td1":600,"e":0.06,"e0":0.06,"e1":0.06,"tw":10.8,"er":100.44,"bu":0.4,"bd":6.7},{"i":"necrozma_dusk_mane","n":"Necrozma (Dusk Mane)","f":"SHADOW_CLAW","c":"SUNSTEEL_STRIKE","cp":4099,"lv":40,"d":45.45,"d0":45.45,"d1":45.45,"dp":100,"m":0,"m0":0,"m1":0,"td":600,"td0":600,"td1":600,"e":0.07,"e0":0.07,"e1":0.07,"tw":13.2,"er":86.64,"bu":0,"bd":7.1},{"i":"zacian_crowned_sword","n":"Zacian (Crowned Sword)","f":"AIR_SLASH","c":"BEHEMOTH_BLADE","cp":4979,"lv":40,"d":47.62,"d0":47.62,"d1":47.62,"dp":100,"m":0,"m0":0,"m1":0,"td":600,"td0":600,"td1":600,"e":0.07,"e0":0.07,"e1":0.07,"tw":12.6,"er":89.72,"bu":0,"bd":6.7},{"i":"lucario_mega","n":"Lucario (Mega)","f":"BULLET_PUNCH","c":"METEOR_MASH","cp":3826,"lv":40,"d":50.7,"d0":48.19,"d1":52.63,"dp":100,"m":0,"m0":0,"m1":0,"td":600,"td0":600,"td1":600,"e":0.07,"e0":0.06,"e1":0.07,"tw":11.9,"er":94.04,"bu":0.7,"bd":16.3},{"i":"zamazenta_crowned_shield","n":"Zamazenta (Crowned Shield)","f":"METAL_CLAW","c":"BEHEMOTH_BASH","cp":4172,"lv":40,"d":49.83,"d0":46.15,"d1":50.42,"dp":100,"m":0,"m0":0,"m1":0,"td":600,"td0":600,"td1":600,"e":0.07,"e0":0.07,"e1":0.07,"tw":12,"er":92.83,"bu":0.9,"bd":9.2},{"i":"metagross_mega","n":"Metagross (Mega)","f":"BULLET_PUNCH","c":"METEOR_MASH","cp":4911,"lv":40,"d":48.19,"d0":48.19,"d1":48.19,"dp":100,"m":0,"m0":0,"m1":0,"td":600,"td0":600,"td1":600,"e":0.07,"e0":0.07,"e1":0.07,"tw":12.4,"er":90.53,"bu":0.7,"bd":6.2},{"i":"metagross_shadow","n":"Metagross (Shadow)","f":"BULLET_PUNCH","c":"METEOR_MASH","cp":3791,"lv":40,"d":48.19,"d0":48.19,"d1":48.19,"dp":100,"m":0,"m0":0,"m1":0,"td":600,"td0":600,"td1":600,"e":0.07,"e0":0.07,"e1":0.07,"tw":12.4,"er":90.53,"bu":0.6,"bd":8.6},{"i":"regigigas_shadow","n":"Regigigas (Shadow)","f":"HIDDEN_POWER_POISON","c":"CRUSH_GRIP","cp":4346,"lv":40,"d":45.63,"d0":45.63,"d1":45.63,"dp":100,"m":0,"m0":0,"m1":0,"td":600,"td0":600,"td1":600,"e":0.07,"e0":0.07,"e1":0.07,"tw":13.1,"er":86.89,"bu":0.5,"bd":12.9},{"i":"regigigas_shadow","n":"Regigigas (Shadow)","f":"HIDDEN_POWER_STEEL","c":"CRUSH_GRIP","cp":4346,"lv":40,"d":45.63,"d0":45.63,"d1":45.63,"dp":100,"m":0,"m0":0,"m1":0,"td":600,"td0":600,"td1":600,"e":0.07,"e0":0.07,"e1":0.07,"tw":13.1,"er":86.89,"bu":0.4,"bd":12.9},{"i":"necrozma_dusk_mane","n":"Necrozma (Dusk Mane)","f":"PSYCHO_CUT","c":"SUNSTEEL_STRIKE","cp":4099,"lv":40,"d":43.01,"d0":43.01,"d1":43.01,"dp":100,"m":0,"m0":0,"m1":0,"td":600,"td0":600,"td1":600,"e":0.08,"e0":0.08,"e1":0.08,"tw":13.9,"er":83.12,"bu":0.8,"bd":7.1},{"i":"zamazenta_crowned_shield","n":"Zamazenta (Crowned Shield)","f":"ICE_FANG","c":"BEHEMOTH_BASH","cp":4172,"lv":40,"d":39.36,"d0":36.59,"d1":40.4,"dp":100,"m":0,"m0":0,"m1":0,"td":600,"td0":600,"td1":600,"e":0.08,"e0":0.08,"e1":0.09,"tw":15.3,"er":77.77,"bu":0.8,"bd":9.2},{"i":"metagross_mega","n":"Metagross (Mega)","f":"ZEN_HEADBUTT","c":"METEOR_MASH","cp":4911,"lv":40,"d":41.32,"d0":41.24,"d1":44.44,"dp":100,"m":0,"m0":0,"m1":0,"td":600,"td0":600,"td1":600,"e":0.08,"e0":0.08,"e1":0.08,"tw":14.5,"er":80.66,"bu":0.8,"bd":6.2},{"i":"metagross_shadow","n":"Metagross (Shadow)","f":"ZEN_HEADBUTT","c":"METEOR_MASH","cp":3791,"lv":40,"d":43.79,"d0":41.24,"d1":44.44,"dp":100,"m":0,"m0":0,"m1":0,"td":600,"td0":600,"td1":600,"e":0.08,"e0":0.08,"e1":0.08,"tw":13.7,"er":84.24,"bu":0.8,"bd":8.6},{"i":"beedrill_mega","n":"Beedrill (Mega)","f":"POISON_JAB","c":"SLUDGE_BOMB","cp":3383,"lv":40,"d":43.74,"d0":41.24,"d1":44.44,"dp":100,"m":0,"m0":0,"m1":0,"td":600,"td0":600,"td1":600,"e":0.08,"e0":0.08,"e1":0.08,"tw":13.7,"er":84.18,"bu":0.8,"bd":12.9},{"i":"naganadel","n":"Naganadel","f":"POISON_JAB","c":"SLUDGE_BOMB","cp":3173,"lv":40,"d":43.66,"d0":41.24,"d1":44.44,"dp":100,"m":0,"m0":0,"m1":0,"td":600,"td0":600,"td1":600,"e":0.08,"e0":0.08,"e1":0.08,"tw":13.8,"er":84.07,"bu":0.8,"bd":17.2},{"i":"blacephalon","n":"Blacephalon","f":"ASTONISH","c":"MIND_BLOWN","cp":3297,"lv":40,"d":43.83,"d0":41.24,"d1":44.44,"dp":100,"m":0,"m0":0,"m1":0,"td":600,"td0":600,"td1":600,"e":0.08,"e0":0.08,"e1":0.08,"tw":13.7,"er":84.31,"bu":0.9,"bd":14.5},{"i":"blacephalon","n":"Blacephalon","f":"INCINERATE","c":"MIND_BLOWN","cp":3297,"lv":40,"d":40.68,"d0":40.68,"d1":40.68,"dp":100,"m":0,"m0":0,"m1":0,"td":600,"td0":600,"td1":600,"e":0.08,"e0":0.08,"e1":0.08,"tw":14.8,"er":79.72,"bu":0.6,"bd":14.5},{"i":"eternatus","n":"Eternatus","f":"POISON_JAB","c":"SLUDGE_BOMB","cp":4429,"lv":40,"d":43.68,"d0":41.24,"d1":44.44,"dp":100,"m":0,"m0":0,"m1":0,"td":600,"td0":600,"td1":600,"e":0.08,"e0":0.08,"e1":0.08,"tw":13.8,"er":84.09,"bu":0.8,"bd":9.9},{"i":"rayquaza_mega","n":"Rayquaza (Mega)","f":"AIR_SLASH","c":"DRAGON_ASCENT","cp":5713,"lv":40,"d":40.41,"d0":36.14,"d1":41.38,"dp":100,"m":0,"m0":0,"m1":0,"td":600,"td0":600,"td1":600,"e":0.08,"e0":0.08,"e1":0.09,"tw":14.9,"er":79.33,"bu":0.9,"bd":16.8},{"i":"zacian_crowned_sword","n":"Zacian (Crowned Sword)","f":"METAL_CLAW","c":"GIGA_IMPACT","cp":4979,"lv":40,"d":35.09,"d0":35.09,"d1":35.09,"dp":100,"m":0,"m0":0,"m1":0,"td":600,"td0":600,"td1":600,"e":0.09,"e0":0.1,"e1":0.1,"tw":17.1,"er":71.35,"bu":0.9,"bd":6.7},{"i":"lucario_mega","n":"Lucario (Mega)","f":"FORCE_PALM","c":"METEOR_MASH","cp":3826,"lv":40,"d":38.62,"d0":36.36,"d1":38.83,"dp":100,"m":0,"m0":0,"m1":0,"td":600,"td0":600,"td1":600,"e":0.09,"e0":0.09,"e1":0.09,"tw":15.5,"er":76.67,"bu":0.8,"bd":16.3},{"i":"metagross_mega","n":"Metagross (Mega)","f":"SHADOW_CLAW","c":"METEOR_MASH","cp":4911,"lv":40,"d":38.2,"d0":37.04,"d1":38.34,"dp":100,"m":0,"m0":0,"m1":0,"td":600,"td0":600,"td1":600,"e":0.09,"e0":0.09,"e1":0.09,"tw":15.7,"er":76.05,"bu":0.9,"bd":6.2},{"i":"metagross_mega","n":"Metagross (Mega)","f":"FURY_CUTTER","c":"METEOR_MASH","cp":4911,"lv":40,"d":37.71,"d0":36.47,"d1":37.74,"dp":100,"m":0,"m0":0,"m1":0,"td":600,"td0":600,"td1":600,"e":0.09,"e0":0.09,"e1":0.09,"tw":15.9,"er":75.31,"bu":0.9,"bd":6.2},{"i":"metagross_shadow","n":"Metagross (Shadow)","f":"SHADOW_CLAW","c":"METEOR_MASH","cp":3791,"lv":40,"d":38.34,"d0":37.04,"d1":39.74,"dp":100,"m":0,"m0":0,"m1":0,"td":600,"td0":600,"td1":600,"e":0.09,"e0":0.08,"e1":0.09,"tw":15.7,"er":76.25,"bu":0.9,"bd":8.6},{"i":"metagross_shadow","n":"Metagross (Shadow)","f":"FURY_CUTTER","c":"METEOR_MASH","cp":3791,"lv":40,"d":37.71,"d0":36.47,"d1":37.74,"dp":100,"m":0,"m0":0,"m1":0,"td":600,"td0":600,"td1":600,"e":0.09,"e0":0.09,"e1":0.09,"tw":15.9,"er":75.32,"bu":0.9,"bd":8.6},{"i":"dialga_shadow","n":"Dialga (Shadow)","f":"METAL_CLAW","c":"IRON_HEAD","cp":4038,"lv":40,"d":39.19,"d0":38.83,"d1":44.44,"dp":100,"m":0,"m0":0,"m1":0,"td":600,"td0":600,"td1":600,"e":0.09,"e0":0.08,"e1":0.09,"tw":15.3,"er":77.52,"bu":0.8,"bd":13.9},{"i":"metagross","n":"Metagross","f":"BULLET_PUNCH","c":"METEOR_MASH","cp":3791,"lv":40,"d":36.36,"d0":36.36,"d1":36.36,"dp":100,"m":0,"m0":0,"m1":0,"td":600,"td0":600,"td1":600,"e":0.09,"e0":0.09,"e1":0.09,"tw":16.5,"er":73.29,"bu":0.8,"bd":7.4},{"i":"metagross","n":"Metagross","f":"FURY_CUTTER","c":"METEOR_MASH","cp":3791,"lv":40,"d":37.71,"d0":36.47,"d1":37.74,"dp":100,"m":0,"m0":0,"m1":0,"td":600,"td0":600,"td1":600,"e":0.09,"e0":0.09,"e1":0.09,"tw":15.9,"er":75.31,"bu":0.8,"bd":7.4},{"i":"gengar_shadow","n":"Gengar (Shadow)","f":"SHADOW_CLAW","c":"SLUDGE_BOMB","cp":2878,"lv":40,"d":38.43,"d0":34.19,"d1":39.74,"dp":100,"m":0,"m0":0,"m1":0,"td":600,"td0":600,"td1":600,"e":0.09,"e0":0.08,"e1":0.1,"tw":15.7,"er":76.39,"bu":0.8,"bd":15.7},{"i":"gengar_mega","n":"Gengar (Mega)","f":"LICK","c":"SLUDGE_BOMB","cp":4336,"lv":40,"d":39.09,"d0":39.09,"d1":39.09,"dp":100,"m":0,"m0":0,"m1":0,"td":600,"td0":600,"td1":600,"e":0.09,"e0":0.09,"e1":0.09,"tw":15.4,"er":77.37,"bu":0.8,"bd":10.4},{"i":"gengar_mega","n":"Gengar (Mega)","f":"SHADOW_CLAW","c":"SLUDGE_BOMB","cp":4336,"lv":40,"d":38.32,"d0":37.04,"d1":39.74,"dp":100,"m":0,"m0":0,"m1":0,"td":600,"td0":600,"td1":600,"e":0.09,"e0":0.08,"e1":0.09,"tw":15.7,"er":76.22,"bu":0.9,"bd":10.4},{"i":"lucario","n":"Lucario","f":"FORCE_PALM","c":"METEOR_MASH","cp":2703,"lv":40,"d":38.63,"d0":36.36,"d1":38.83,"dp":100,"m":0,"m0":0,"m1":0,"td":600,"td0":600,"td1":600,"e":0.09,"e0":0.09,"e1":0.09,"tw":15.5,"er":76.69,"bu":0.8,"bd":19.7},{"i":"deoxys_attack","n":"Deoxys (Attack)","f":"POISON_JAB","c":"ZAP_CANNON","cp":2580,"lv":40,"d":38.59,"d0":38.59,"d1":38.59,"dp":100,"m":0,"m0":0,"m1":0,"td":600,"td0":600,"td1":600,"e":0.09,"e0":0.09,"e1":0.09,"tw":15.6,"er":76.62,"bu":0.8,"bd":61.7},{"i":"mewtwo_shadow","n":"Mewtwo (Shadow)","f":"PSYCHO_CUT","c":"PSYSTRIKE","cp":4178,"lv":40,"d":36.07,"d0":34.19,"d1":36.47,"dp":100,"m":0,"m0":0,"m1":0,"td":600,"td0":600,"td1":600,"e":0.09,"e0":0.09,"e1":0.1,"tw":16.6,"er":72.84,"bu":0.8,"bd":15.6},{"i":"toxicroak_shadow","n":"Toxicroak (Shadow)","f":"POISON_JAB","c":"SLUDGE_BOMB","cp":2488,"lv":40,"d":36.43,"d0":36.36,"d1":41.24,"dp":100,"m":0,"m0":0,"m1":0,"td":600,"td0":600,"td1":600,"e":0.09,"e0":0.08,"e1":0.09,"tw":16.5,"er":73.4,"bu":0.9,"bd":22.4},{"i":"darkrai_shadow","n":"Darkrai (Shadow)","f":"SNARL","c":"SLUDGE_BOMB","cp":3739,"lv":40,"d":35.81,"d0":32.26,"d1":36.36,"dp":100,"m":0,"m0":0,"m1":0,"td":600,"td0":600,"td1":600,"e":0.09,"e0":0.09,"e1":0.1,"tw":16.8,"er":72.45,"bu":0.9,"bd":27.9},{"i":"genesect","n":"Genesect","f":"METAL_CLAW","c":"MAGNET_BOMB","cp":3353,"lv":40,"d":35.41,"d0":34.38,"d1":35.5,"dp":100,"m":0,"m0":0,"m1":0,"td":600,"td0":600,"td1":600,"e":0.09,"e0":0.09,"e1":0.1,"tw":16.9,"er":71.84,"bu":0.9,"bd":9.4},{"i":"genesect_burn","n":"Genesect (Burn)","f":"METAL_CLAW","c":"MAGNET_BOMB","cp":3353,"lv":40,"d":35.4,"d0":34.38,"d1":35.5,"dp":100,"m":0,"m0":0,"m1":0,"td":600,"td0":600,"td1":600,"e":0.09,"e0":0.09,"e1":0.1,"tw":17,"er":71.83,"bu":0.9,"bd":9.4},{"i":"genesect_chill","n":"Genesect (Chill)","f":"METAL_CLAW","c":"MAGNET_BOMB","cp":3353,"lv":40,"d":35.38,"d0":34.38,"d1":35.5,"dp":100,"m":0,"m0":0,"m1":0,"td":600,"td0":600,"td1":600,"e":0.09,"e0":0.09,"e1":0.1,"tw":17,"er":71.8,"bu":0.9,"bd":9.4},{"i":"genesect_douse","n":"Genesect (Douse)","f":"METAL_CLAW","c":"MAGNET_BOMB","cp":3353,"lv":40,"d":35.37,"d0":34.38,"d1":35.5,"dp":100,"m":0,"m0":0,"m1":0,"td":600,"td0":600,"td1":600,"e":0.09,"e0":0.09,"e1":0.1,"tw":17,"er":71.78,"bu":0.9,"bd":9.4},{"i":"genesect_shock","n":"Genesect (Shock)","f":"METAL_CLAW","c":"MAGNET_BOMB","cp":3353,"lv":40,"d":35.41,"d0":34.38,"d1":35.5,"dp":100,"m":0,"m0":0,"m1":0,"td":600,"td0":600,"td1":600,"e":0.09,"e0":0.09,"e1":0.1,"tw":16.9,"er":71.85,"bu":0.9,"bd":9.4},{"i":"excadrill_shadow","n":"Excadrill (Shadow)","f":"METAL_CLAW","c":"IRON_HEAD","cp":3244,"lv":40,"d":35.09,"d0":35.09,"d1":35.09,"dp":100,"m":0,"m0":0,"m1":0,"td":600,"td0":600,"td1":600,"e":0.09,"e0":0.1,"e1":0.1,"tw":17.1,"er":71.35,"bu":0.9,"bd":11.8},{"i":"lucario_mega","n":"Lucario (Mega)","f":"COUNTER","c":"METEOR_MASH","cp":3826,"lv":40,"d":34.19,"d0":34.19,"d1":34.19,"dp":100,"m":0,"m0":0,"m1":0,"td":600,"td0":600,"td1":600,"e":0.1,"e0":0.1,"e1":0.1,"tw":17.5,"er":69.98,"bu":0.9,"bd":16.3},{"i":"regigigas_shadow","n":"Regigigas (Shadow)","f":"HIDDEN_POWER_POISON","c":"GIGA_IMPACT","cp":4346,"lv":40,"d":34.48,"d0":34.48,"d1":34.48,"dp":100,"m":0,"m0":0,"m1":0,"td":600,"td0":600,"td1":600,"e":0.1,"e0":0.1,"e1":0.1,"tw":17.4,"er":70.43,"bu":0.9,"bd":12.9},{"i":"regigigas_shadow","n":"Regigigas (Shadow)","f":"HIDDEN_POWER_STEEL","c":"GIGA_IMPACT","cp":4346,"lv":40,"d":34.48,"d0":34.48,"d1":34.48,"dp":100,"m":0,"m0":0,"m1":0,"td":600,"td0":600,"td1":600,"e":0.1,"e0":0.1,"e1":0.1,"tw":17.4,"er":70.43,"bu":0.8,"bd":12.9},{"i":"beedrill_mega","n":"Beedrill (Mega)","f":"INFESTATION","c":"SLUDGE_BOMB","cp":3383,"lv":40,"d":34.03,"d0":32.26,"d1":34.19,"dp":100,"m":0,"m0":0,"m1":0,"td":600,"td0":600,"td1":600,"e":0.1,"e0":0.1,"e1":0.1,"tw":17.6,"er":69.73,"bu":0.8,"bd":12.9},{"i":"beedrill_mega","n":"Beedrill (Mega)","f":"POISON_STING","c":"SLUDGE_BOMB","cp":3383,"lv":40,"d":34.19,"d0":34.19,"d1":34.19,"dp":100,"m":0,"m0":0,"m1":0,"td":600,"td0":600,"td1":600,"e":0.1,"e0":0.1,"e1":0.1,"tw":17.5,"er":69.98,"bu":0.9,"bd":12.9},{"i":"rayquaza_mega","n":"Rayquaza (Mega)","f":"DRAGON_TAIL","c":"DRAGON_ASCENT","cp":5713,"lv":40,"d":34.06,"d0":32.43,"d1":38.59,"dp":100,"m":0,"m0":0,"m1":0,"td":600,"td0":600,"td1":600,"e":0.1,"e0":0.09,"e1":0.1,"tw":17.7,"er":69.79,"bu":0.8,"bd":16.8},{"i":"gengar_shadow","n":"Gengar (Shadow)","f":"HEX","c":"SLUDGE_BOMB","cp":2878,"lv":40,"d":34.08,"d0":32.26,"d1":34.19,"dp":100,"m":0,"m0":0,"m1":0,"td":600,"td0":600,"td1":600,"e":0.1,"e0":0.1,"e1":0.1,"tw":17.6,"er":69.81,"bu":0.9,"bd":15.7},{"i":"gengar_mega","n":"Gengar (Mega)","f":"HEX","c":"SLUDGE_BOMB","cp":4336,"lv":40,"d":34.19,"d0":34.19,"d1":34.19,"dp":100,"m":0,"m0":0,"m1":0,"td":600,"td0":600,"td1":600,"e":0.1,"e0":0.1,"e1":0.1,"tw":17.5,"er":69.98,"bu":0.9,"bd":10.4},{"i":"deoxys_attack","n":"Deoxys (Attack)","f":"POISON_JAB","c":"PSYCHO_BOOST","cp":2580,"lv":40,"d":35.29,"d0":32.52,"d1":40,"dp":100,"m":0,"m0":0,"m1":0,"td":600,"td0":600,"td1":600,"e":0.1,"e0":0.08,"e1":0.1,"tw":17.2,"er":71.67,"bu":0.7,"bd":61.7},{"i":"mewtwo_shadow","n":"Mewtwo (Shadow)","f":"PSYCHO_CUT","c":"PSYCHIC","cp":4178,"lv":40,"d":34.06,"d0":32.35,"d1":34.38,"dp":100,"m":0,"m0":0,"m1":0,"td":600,"td0":600,"td1":600,"e":0.1,"e0":0.1,"e1":0.1,"tw":17.6,"er":69.79,"bu":0.9,"bd":15.6},{"i":"toxicroak_shadow","n":"Toxicroak (Shadow)","f":"MUD_SHOT","c":"SLUDGE_BOMB","cp":2488,"lv":40,"d":33.47,"d0":30,"d1":34.19,"dp":100,"m":0,"m0":0,"m1":0,"td":600,"td0":600,"td1":600,"e":0.1,"e0":0.1,"e1":0.11,"tw":18,"er":68.88,"bu":0.9,"bd":22.4},{"i":"toxicroak_shadow","n":"Toxicroak (Shadow)","f":"POISON_STING","c":"SLUDGE_BOMB","cp":2488,"lv":40,"d":34.01,"d0":32.17,"d1":35.29,"dp":100,"m":0,"m0":0,"m1":0,"td":600,"td0":600,"td1":600,"e":0.1,"e0":0.09,"e1":0.1,"tw":17.7,"er":69.7,"bu":0.9,"bd":22.4},{"i":"victreebel_mega","n":"Victreebel (Mega)","f":"ACID","c":"SLUDGE_BOMB","cp":3505,"lv":40,"d":34.19,"d0":34.19,"d1":34.19,"dp":100,"m":0,"m0":0,"m1":0,"td":600,"td0":600,"td1":600,"e":0.1,"e0":0.1,"e1":0.1,"tw":17.5,"er":69.98,"bu":0.9,"bd":9.3},{"i":"haunter_shadow","n":"Haunter (Shadow)","f":"ASTONISH","c":"SLUDGE_BOMB","cp":1963,"lv":40,"d":34.19,"d0":32.26,"d1":36.36,"dp":100,"m":0,"m0":0,"m1":0,"td":600,"td0":600,"td1":600,"e":0.1,"e0":0.09,"e1":0.1,"tw":17.6,"er":69.98,"bu":0.8,"bd":24.8},{"i":"gengar","n":"Gengar","f":"HEX","c":"SLUDGE_BOMB","cp":2878,"lv":40,"d":34.04,"d0":32.26,"d1":34.19,"dp":100,"m":0,"m0":0,"m1":0,"td":600,"td0":600,"td1":600,"e":0.1,"e0":0.1,"e1":0.1,"tw":17.6,"er":69.74,"bu":0.9,"bd":13.4}],"tackle_draining_kiss":[{"i":"necrozma_dusk_mane","n":"Necrozma (Dusk Mane)","f":"METAL_CLAW","c":"SUNSTEEL_STRIKE","cp":4099,"lv":40,"d":55.41,"d0":54.55,"d1":57.42,"dp":100,"m":0,"m0":0,"m1":0,"td":600,"td0":600,"td1":600,"e":0.06,"e0":0.06,"e1":0.06,"tw":10.8,"er":100.52,"bu":0.4,"bd":7.1},{"i":"zacian_crowned_sword","n":"Zacian (Crowned Sword)","f":"METAL_CLAW","c":"BEHEMOTH_BLADE","cp":4979,"lv":40,"d":55.38,"d0":54.55,"d1":60.61,"dp":100,"m":0,"m0":0,"m1":0,"td":600,"td0":600,"td1":600,"e":0.06,"e0":0.06,"e1":0.06,"tw":10.8,"er":100.47,"bu":0.4,"bd":6.7},{"i":"necrozma_dusk_mane","n":"Necrozma (Dusk Mane)","f":"SHADOW_CLAW","c":"SUNSTEEL_STRIKE","cp":4099,"lv":40,"d":45.45,"d0":45.45,"d1":45.45,"dp":100,"m":0,"m0":0,"m1":0,"td":600,"td0":600,"td1":600,"e":0.07,"e0":0.07,"e1":0.07,"tw":13.2,"er":86.64,"bu":0,"bd":7.1},{"i":"zacian_crowned_sword","n":"Zacian (Crowned Sword)","f":"AIR_SLASH","c":"BEHEMOTH_BLADE","cp":4979,"lv":40,"d":47.62,"d0":47.62,"d1":47.62,"dp":100,"m":0,"m0":0,"m1":0,"td":600,"td0":600,"td1":600,"e":0.07,"e0":0.07,"e1":0.07,"tw":12.6,"er":89.72,"bu":0,"bd":6.7},{"i":"lucario_mega","n":"Lucario (Mega)","f":"BULLET_PUNCH","c":"METEOR_MASH","cp":3826,"lv":40,"d":50.87,"d0":48.19,"d1":52.63,"dp":100,"m":0,"m0":0,"m1":0,"td":600,"td0":600,"td1":600,"e":0.07,"e0":0.06,"e1":0.07,"tw":11.8,"er":94.28,"bu":0.7,"bd":16.3},{"i":"zamazenta_crowned_shield","n":"Zamazenta (Crowned Shield)","f":"METAL_CLAW","c":"BEHEMOTH_BASH","cp":4172,"lv":40,"d":49.85,"d0":46.15,"d1":50.42,"dp":100,"m":0,"m0":0,"m1":0,"td":600,"td0":600,"td1":600,"e":0.07,"e0":0.07,"e1":0.07,"tw":12,"er":92.85,"bu":0.9,"bd":9.2},{"i":"metagross_mega","n":"Metagross (Mega)","f":"BULLET_PUNCH","c":"METEOR_MASH","cp":4911,"lv":40,"d":48.19,"d0":48.19,"d1":48.19,"dp":100,"m":0,"m0":0,"m1":0,"td":600,"td0":600,"td1":600,"e":0.07,"e0":0.07,"e1":0.07,"tw":12.4,"er":90.53,"bu":0.6,"bd":6.2},{"i":"metagross_shadow","n":"Metagross (Shadow)","f":"BULLET_PUNCH","c":"METEOR_MASH","cp":3791,"lv":40,"d":48.19,"d0":48.19,"d1":48.19,"dp":100,"m":0,"m0":0,"m1":0,"td":600,"td0":600,"td1":600,"e":0.07,"e0":0.07,"e1":0.07,"tw":12.4,"er":90.53,"bu":0.7,"bd":8.6},{"i":"regigigas_shadow","n":"Regigigas (Shadow)","f":"HIDDEN_POWER_POISON","c":"CRUSH_GRIP","cp":4346,"lv":40,"d":45.63,"d0":45.63,"d1":45.63,"dp":100,"m":0,"m0":0,"m1":0,"td":600,"td0":600,"td1":600,"e":0.07,"e0":0.07,"e1":0.07,"tw":13.1,"er":86.89,"bu":0.5,"bd":12.9},{"i":"regigigas_shadow","n":"Regigigas (Shadow)","f":"HIDDEN_POWER_STEEL","c":"CRUSH_GRIP","cp":4346,"lv":40,"d":45.63,"d0":45.63,"d1":45.63,"dp":100,"m":0,"m0":0,"m1":0,"td":600,"td0":600,"td1":600,"e":0.07,"e0":0.07,"e1":0.07,"tw":13.1,"er":86.89,"bu":0.5,"bd":12.9},{"i":"necrozma_dusk_mane","n":"Necrozma (Dusk Mane)","f":"PSYCHO_CUT","c":"SUNSTEEL_STRIKE","cp":4099,"lv":40,"d":43.01,"d0":43.01,"d1":43.01,"dp":100,"m":0,"m0":0,"m1":0,"td":600,"td0":600,"td1":600,"e":0.08,"e0":0.08,"e1":0.08,"tw":13.9,"er":83.12,"bu":0.8,"bd":7.1},{"i":"zamazenta_crowned_shield","n":"Zamazenta (Crowned Shield)","f":"ICE_FANG","c":"BEHEMOTH_BASH","cp":4172,"lv":40,"d":39.4,"d0":36.59,"d1":40.4,"dp":100,"m":0,"m0":0,"m1":0,"td":600,"td0":600,"td1":600,"e":0.08,"e0":0.08,"e1":0.09,"tw":15.3,"er":77.84,"bu":0.8,"bd":9.2},{"i":"metagross_mega","n":"Metagross (Mega)","f":"ZEN_HEADBUTT","c":"METEOR_MASH","cp":4911,"lv":40,"d":41.31,"d0":41.24,"d1":44.44,"dp":100,"m":0,"m0":0,"m1":0,"td":600,"td0":600,"td1":600,"e":0.08,"e0":0.08,"e1":0.08,"tw":14.5,"er":80.64,"bu":0.8,"bd":6.2},{"i":"metagross_shadow","n":"Metagross (Shadow)","f":"ZEN_HEADBUTT","c":"METEOR_MASH","cp":3791,"lv":40,"d":43.74,"d0":41.24,"d1":44.44,"dp":100,"m":0,"m0":0,"m1":0,"td":600,"td0":600,"td1":600,"e":0.08,"e0":0.08,"e1":0.08,"tw":13.7,"er":84.18,"bu":0.8,"bd":8.6},{"i":"beedrill_mega","n":"Beedrill (Mega)","f":"POISON_JAB","c":"SLUDGE_BOMB","cp":3383,"lv":40,"d":43.73,"d0":41.24,"d1":44.44,"dp":100,"m":0,"m0":0,"m1":0,"td":600,"td0":600,"td1":600,"e":0.08,"e0":0.08,"e1":0.08,"tw":13.7,"er":84.17,"bu":0.8,"bd":12.9},{"i":"naganadel","n":"Naganadel","f":"POISON_JAB","c":"SLUDGE_BOMB","cp":3173,"lv":40,"d":43.69,"d0":41.24,"d1":44.44,"dp":100,"m":0,"m0":0,"m1":0,"td":600,"td0":600,"td1":600,"e":0.08,"e0":0.08,"e1":0.08,"tw":13.7,"er":84.11,"bu":0.8,"bd":17.2},{"i":"blacephalon","n":"Blacephalon","f":"ASTONISH","c":"MIND_BLOWN","cp":3297,"lv":40,"d":43.86,"d0":41.24,"d1":44.44,"dp":100,"m":0,"m0":0,"m1":0,"td":600,"td0":600,"td1":600,"e":0.08,"e0":0.08,"e1":0.08,"tw":13.7,"er":84.34,"bu":0.9,"bd":14.5},{"i":"blacephalon","n":"Blacephalon","f":"INCINERATE","c":"MIND_BLOWN","cp":3297,"lv":40,"d":40.68,"d0":40.68,"d1":40.68,"dp":100,"m":0,"m0":0,"m1":0,"td":600,"td0":600,"td1":600,"e":0.08,"e0":0.08,"e1":0.08,"tw":14.8,"er":79.72,"bu":0.7,"bd":14.5},{"i":"eternatus","n":"Eternatus","f":"POISON_JAB","c":"SLUDGE_BOMB","cp":4429,"lv":40,"d":43.65,"d0":41.24,"d1":44.44,"dp":100,"m":0,"m0":0,"m1":0,"td":600,"td0":600,"td1":600,"e":0.08,"e0":0.08,"e1":0.08,"tw":13.8,"er":84.05,"bu":0.8,"bd":9.9},{"i":"rayquaza_mega","n":"Rayquaza (Mega)","f":"AIR_SLASH","c":"DRAGON_ASCENT","cp":5713,"lv":40,"d":40.39,"d0":36.14,"d1":41.38,"dp":100,"m":0,"m0":0,"m1":0,"td":600,"td0":600,"td1":600,"e":0.08,"e0":0.08,"e1":0.09,"tw":14.9,"er":79.29,"bu":0.9,"bd":16.8},{"i":"dialga_shadow","n":"Dialga (Shadow)","f":"METAL_CLAW","c":"IRON_HEAD","cp":4038,"lv":40,"d":39.29,"d0":38.83,"d1":44.44,"dp":100,"m":0,"m0":0,"m1":0,"td":600,"td0":600,"td1":600,"e":0.08,"e0":0.08,"e1":0.09,"tw":15.3,"er":77.68,"bu":0.9,"bd":13.9},{"i":"zacian_crowned_sword","n":"Zacian (Crowned Sword)","f":"METAL_CLAW","c":"GIGA_IMPACT","cp":4979,"lv":40,"d":35.09,"d0":35.09,"d1":35.09,"dp":100,"m":0,"m0":0,"m1":0,"td":600,"td0":600,"td1":600,"e":0.09,"e0":0.1,"e1":0.1,"tw":17.1,"er":71.35,"bu":0.9,"bd":6.7},{"i":"lucario_mega","n":"Lucario (Mega)","f":"FORCE_PALM","c":"METEOR_MASH","cp":3826,"lv":40,"d":38.67,"d0":36.36,"d1":38.83,"dp":100,"m":0,"m0":0,"m1":0,"td":600,"td0":600,"td1":600,"e":0.09,"e0":0.09,"e1":0.09,"tw":15.5,"er":76.75,"bu":0.8,"bd":16.3},{"i":"metagross_mega","n":"Metagross (Mega)","f":"SHADOW_CLAW","c":"METEOR_MASH","cp":4911,"lv":40,"d":38.15,"d0":37.04,"d1":38.34,"dp":100,"m":0,"m0":0,"m1":0,"td":600,"td0":600,"td1":600,"e":0.09,"e0":0.09,"e1":0.09,"tw":15.7,"er":75.98,"bu":0.9,"bd":6.2},{"i":"metagross_mega","n":"Metagross (Mega)","f":"FURY_CUTTER","c":"METEOR_MASH","cp":4911,"lv":40,"d":37.71,"d0":36.47,"d1":37.74,"dp":100,"m":0,"m0":0,"m1":0,"td":600,"td0":600,"td1":600,"e":0.09,"e0":0.09,"e1":0.09,"tw":15.9,"er":75.31,"bu":0.9,"bd":6.2},{"i":"metagross_shadow","n":"Metagross (Shadow)","f":"SHADOW_CLAW","c":"METEOR_MASH","cp":3791,"lv":40,"d":38.34,"d0":37.04,"d1":39.74,"dp":100,"m":0,"m0":0,"m1":0,"td":600,"td0":600,"td1":600,"e":0.09,"e0":0.08,"e1":0.09,"tw":15.7,"er":76.26,"bu":0.9,"bd":8.6},{"i":"metagross_shadow","n":"Metagross (Shadow)","f":"FURY_CUTTER","c":"METEOR_MASH","cp":3791,"lv":40,"d":37.71,"d0":36.47,"d1":37.74,"dp":100,"m":0,"m0":0,"m1":0,"td":600,"td0":600,"td1":600,"e":0.09,"e0":0.09,"e1":0.09,"tw":15.9,"er":75.32,"bu":0.9,"bd":8.6},{"i":"metagross","n":"Metagross","f":"BULLET_PUNCH","c":"METEOR_MASH","cp":3791,"lv":40,"d":36.36,"d0":36.36,"d1":36.36,"dp":100,"m":0,"m0":0,"m1":0,"td":600,"td0":600,"td1":600,"e":0.09,"e0":0.09,"e1":0.09,"tw":16.5,"er":73.29,"bu":0.8,"bd":7.4},{"i":"metagross","n":"Metagross","f":"FURY_CUTTER","c":"METEOR_MASH","cp":3791,"lv":40,"d":37.7,"d0":36.47,"d1":37.74,"dp":100,"m":0,"m0":0,"m1":0,"td":600,"td0":600,"td1":600,"e":0.09,"e0":0.09,"e1":0.09,"tw":15.9,"er":75.3,"bu":0.8,"bd":7.4},{"i":"gengar_shadow","n":"Gengar (Shadow)","f":"SHADOW_CLAW","c":"SLUDGE_BOMB","cp":2878,"lv":40,"d":38.26,"d0":34.19,"d1":39.74,"dp":100,"m":0,"m0":0,"m1":0,"td":600,"td0":600,"td1":600,"e":0.09,"e0":0.08,"e1":0.1,"tw":15.7,"er":76.14,"bu":0.8,"bd":15.7},{"i":"gengar_mega","n":"Gengar (Mega)","f":"LICK","c":"SLUDGE_BOMB","cp":4336,"lv":40,"d":39.09,"d0":39.09,"d1":39.09,"dp":100,"m":0,"m0":0,"m1":0,"td":600,"td0":600,"td1":600,"e":0.09,"e0":0.09,"e1":0.09,"tw":15.4,"er":77.37,"bu":0.8,"bd":10.4},{"i":"gengar_mega","n":"Gengar (Mega)","f":"SHADOW_CLAW","c":"SLUDGE_BOMB","cp":4336,"lv":40,"d":38.37,"d0":37.04,"d1":39.74,"dp":100,"m":0,"m0":0,"m1":0,"td":600,"td0":600,"td1":600,"e":0.09,"e0":0.08,"e1":0.09,"tw":15.6,"er":76.3,"bu":0.9,"bd":10.4},{"i":"lucario","n":"Lucario","f":"FORCE_PALM","c":"METEOR_MASH","cp":2703,"lv":40,"d":38.66,"d0":36.36,"d1":38.83,"dp":100,"m":0,"m0":0,"m1":0,"td":600,"td0":600,"td1":600,"e":0.09,"e0":0.09,"e1":0.09,"tw":15.5,"er":76.74,"bu":0.8,"bd":19.7},{"i":"deoxys_attack","n":"Deoxys (Attack)","f":"POISON_JAB","c":"ZAP_CANNON","cp":2580,"lv":40,"d":38.59,"d0":38.59,"d1":38.59,"dp":100,"m":0,"m0":0,"m1":0,"td":600,"td0":600,"td1":600,"e":0.09,"e0":0.09,"e1":0.09,"tw":15.6,"er":76.62,"bu":0.8,"bd":61.7},{"i":"mewtwo_shadow","n":"Mewtwo (Shadow)","f":"PSYCHO_CUT","c":"PSYSTRIKE","cp":4178,"lv":40,"d":36.11,"d0":34.19,"d1":36.47,"dp":100,"m":0,"m0":0,"m1":0,"td":600,"td0":600,"td1":600,"e":0.09,"e0":0.09,"e1":0.1,"tw":16.6,"er":72.9,"bu":0.9,"bd":15.6},{"i":"toxicroak_shadow","n":"Toxicroak (Shadow)","f":"POISON_JAB","c":"SLUDGE_BOMB","cp":2488,"lv":40,"d":36.41,"d0":36.36,"d1":41.24,"dp":100,"m":0,"m0":0,"m1":0,"td":600,"td0":600,"td1":600,"e":0.09,"e0":0.08,"e1":0.09,"tw":16.5,"er":73.36,"bu":0.9,"bd":22.4},{"i":"darkrai_shadow","n":"Darkrai (Shadow)","f":"SNARL","c":"SLUDGE_BOMB","cp":3739,"lv":40,"d":35.78,"d0":32.26,"d1":36.36,"dp":100,"m":0,"m0":0,"m1":0,"td":600,"td0":600,"td1":600,"e":0.09,"e0":0.09,"e1":0.1,"tw":16.8,"er":72.41,"bu":0.9,"bd":27.9},{"i":"genesect","n":"Genesect","f":"METAL_CLAW","c":"MAGNET_BOMB","cp":3353,"lv":40,"d":35.37,"d0":34.38,"d1":35.5,"dp":100,"m":0,"m0":0,"m1":0,"td":600,"td0":600,"td1":600,"e":0.09,"e0":0.09,"e1":0.1,"tw":17,"er":71.79,"bu":0.9,"bd":9.4},{"i":"genesect_burn","n":"Genesect (Burn)","f":"METAL_CLAW","c":"MAGNET_BOMB","cp":3353,"lv":40,"d":35.39,"d0":34.38,"d1":35.5,"dp":100,"m":0,"m0":0,"m1":0,"td":600,"td0":600,"td1":600,"e":0.09,"e0":0.09,"e1":0.1,"tw":17,"er":71.81,"bu":0.9,"bd":9.4},{"i":"genesect_chill","n":"Genesect (Chill)","f":"METAL_CLAW","c":"MAGNET_BOMB","cp":3353,"lv":40,"d":35.4,"d0":34.38,"d1":35.5,"dp":100,"m":0,"m0":0,"m1":0,"td":600,"td0":600,"td1":600,"e":0.09,"e0":0.09,"e1":0.1,"tw":17,"er":71.83,"bu":0.9,"bd":9.4},{"i":"genesect_douse","n":"Genesect (Douse)","f":"METAL_CLAW","c":"MAGNET_BOMB","cp":3353,"lv":40,"d":35.41,"d0":34.38,"d1":35.5,"dp":100,"m":0,"m0":0,"m1":0,"td":600,"td0":600,"td1":600,"e":0.09,"e0":0.09,"e1":0.1,"tw":16.9,"er":71.84,"bu":0.9,"bd":9.4},{"i":"genesect_shock","n":"Genesect (Shock)","f":"METAL_CLAW","c":"MAGNET_BOMB","cp":3353,"lv":40,"d":35.38,"d0":34.38,"d1":35.5,"dp":100,"m":0,"m0":0,"m1":0,"td":600,"td0":600,"td1":600,"e":0.09,"e0":0.09,"e1":0.1,"tw":17,"er":71.79,"bu":0.9,"bd":9.4},{"i":"excadrill_shadow","n":"Excadrill (Shadow)","f":"METAL_CLAW","c":"IRON_HEAD","cp":3244,"lv":40,"d":35.09,"d0":35.09,"d1":35.09,"dp":100,"m":0,"m0":0,"m1":0,"td":600,"td0":600,"td1":600,"e":0.09,"e0":0.1,"e1":0.1,"tw":17.1,"er":71.35,"bu":0.9,"bd":11.8},{"i":"lucario_mega","n":"Lucario (Mega)","f":"COUNTER","c":"METEOR_MASH","cp":3826,"lv":40,"d":34.19,"d0":34.19,"d1":34.19,"dp":100,"m":0,"m0":0,"m1":0,"td":600,"td0":600,"td1":600,"e":0.1,"e0":0.1,"e1":0.1,"tw":17.5,"er":69.98,"bu":0.9,"bd":16.3},{"i":"regigigas_shadow","n":"Regigigas (Shadow)","f":"HIDDEN_POWER_POISON","c":"GIGA_IMPACT","cp":4346,"lv":40,"d":34.48,"d0":34.48,"d1":34.48,"dp":100,"m":0,"m0":0,"m1":0,"td":600,"td0":600,"td1":600,"e":0.1,"e0":0.1,"e1":0.1,"tw":17.4,"er":70.43,"bu":0.8,"bd":12.9},{"i":"regigigas_shadow","n":"Regigigas (Shadow)","f":"HIDDEN_POWER_STEEL","c":"GIGA_IMPACT","cp":4346,"lv":40,"d":34.48,"d0":34.48,"d1":34.48,"dp":100,"m":0,"m0":0,"m1":0,"td":600,"td0":600,"td1":600,"e":0.1,"e0":0.1,"e1":0.1,"tw":17.4,"er":70.43,"bu":0.8,"bd":12.9},{"i":"beedrill_mega","n":"Beedrill (Mega)","f":"INFESTATION","c":"SLUDGE_BOMB","cp":3383,"lv":40,"d":34.04,"d0":32.26,"d1":34.19,"dp":100,"m":0,"m0":0,"m1":0,"td":600,"td0":600,"td1":600,"e":0.1,"e0":0.1,"e1":0.1,"tw":17.6,"er":69.75,"bu":0.8,"bd":12.9},{"i":"beedrill_mega","n":"Beedrill (Mega)","f":"POISON_STING","c":"SLUDGE_BOMB","cp":3383,"lv":40,"d":34.19,"d0":34.19,"d1":34.19,"dp":100,"m":0,"m0":0,"m1":0,"td":600,"td0":600,"td1":600,"e":0.1,"e0":0.1,"e1":0.1,"tw":17.5,"er":69.98,"bu":0.8,"bd":12.9},{"i":"rayquaza_mega","n":"Rayquaza (Mega)","f":"DRAGON_TAIL","c":"DRAGON_ASCENT","cp":5713,"lv":40,"d":33.99,"d0":32.43,"d1":38.59,"dp":100,"m":0,"m0":0,"m1":0,"td":600,"td0":600,"td1":600,"e":0.1,"e0":0.09,"e1":0.1,"tw":17.7,"er":69.68,"bu":0.8,"bd":16.8},{"i":"gengar_shadow","n":"Gengar (Shadow)","f":"HEX","c":"SLUDGE_BOMB","cp":2878,"lv":40,"d":34.12,"d0":32.26,"d1":34.19,"dp":100,"m":0,"m0":0,"m1":0,"td":600,"td0":600,"td1":600,"e":0.1,"e0":0.1,"e1":0.1,"tw":17.6,"er":69.87,"bu":0.9,"bd":15.7},{"i":"gengar_mega","n":"Gengar (Mega)","f":"HEX","c":"SLUDGE_BOMB","cp":4336,"lv":40,"d":34.19,"d0":34.19,"d1":34.19,"dp":100,"m":0,"m0":0,"m1":0,"td":600,"td0":600,"td1":600,"e":0.1,"e0":0.1,"e1":0.1,"tw":17.5,"er":69.98,"bu":0.9,"bd":10.4},{"i":"deoxys_attack","n":"Deoxys (Attack)","f":"POISON_JAB","c":"PSYCHO_BOOST","cp":2580,"lv":40,"d":35.04,"d0":32.52,"d1":40,"dp":100,"m":0,"m0":0,"m1":0,"td":600,"td0":600,"td1":600,"e":0.1,"e0":0.08,"e1":0.1,"tw":17.3,"er":71.27,"bu":0.8,"bd":61.7},{"i":"mewtwo_shadow","n":"Mewtwo (Shadow)","f":"PSYCHO_CUT","c":"PSYCHIC","cp":4178,"lv":40,"d":34.06,"d0":32.35,"d1":34.38,"dp":100,"m":0,"m0":0,"m1":0,"td":600,"td0":600,"td1":600,"e":0.1,"e0":0.1,"e1":0.1,"tw":17.6,"er":69.78,"bu":0.9,"bd":15.6},{"i":"toxicroak_shadow","n":"Toxicroak (Shadow)","f":"POISON_STING","c":"SLUDGE_BOMB","cp":2488,"lv":40,"d":34.02,"d0":32.17,"d1":35.29,"dp":100,"m":0,"m0":0,"m1":0,"td":600,"td0":600,"td1":600,"e":0.1,"e0":0.09,"e1":0.1,"tw":17.6,"er":69.72,"bu":0.9,"bd":22.4},{"i":"victreebel_mega","n":"Victreebel (Mega)","f":"ACID","c":"SLUDGE_BOMB","cp":3505,"lv":40,"d":34.19,"d0":34.19,"d1":34.19,"dp":100,"m":0,"m0":0,"m1":0,"td":600,"td0":600,"td1":600,"e":0.1,"e0":0.1,"e1":0.1,"tw":17.5,"er":69.98,"bu":0.9,"bd":9.3},{"i":"haunter_shadow","n":"Haunter (Shadow)","f":"ASTONISH","c":"SLUDGE_BOMB","cp":1963,"lv":40,"d":34.17,"d0":32.26,"d1":36.36,"dp":100,"m":0,"m0":0,"m1":0,"td":600,"td0":600,"td1":600,"e":0.1,"e0":0.09,"e1":0.1,"tw":17.6,"er":69.95,"bu":0.8,"bd":24.8},{"i":"gengar","n":"Gengar","f":"HEX","c":"SLUDGE_BOMB","cp":2878,"lv":40,"d":34.01,"d0":32.26,"d1":34.19,"dp":100,"m":0,"m0":0,"m1":0,"td":600,"td0":600,"td1":600,"e":0.1,"e0":0.1,"e1":0.1,"tw":17.6,"er":69.71,"bu":0.8,"bd":13.4}],"tackle_energy_ball":[{"i":"necrozma_dusk_mane","n":"Necrozma (Dusk Mane)","f":"METAL_CLAW","c":"SUNSTEEL_STRIKE","cp":4099,"lv":40,"d":55.93,"d0":54.55,"d1":60.61,"dp":100,"m":0,"m0":0,"m1":0,"td":600,"td0":600,"td1":600,"e":0.06,"e0":0.06,"e1":0.06,"tw":10.7,"er":101.22,"bu":0.4,"bd":8.9},{"i":"zacian_crowned_sword","n":"Zacian (Crowned Sword)","f":"METAL_CLAW","c":"BEHEMOTH_BLADE","cp":4979,"lv":40,"d":55.76,"d0":54.55,"d1":60.61,"dp":100,"m":0,"m0":0,"m1":0,"td":600,"td0":600,"td1":600,"e":0.06,"e0":0.06,"e1":0.06,"tw":10.8,"er":100.99,"bu":0.4,"bd":8.6},{"i":"necrozma_dusk_mane","n":"Necrozma (Dusk Mane)","f":"SHADOW_CLAW","c":"SUNSTEEL_STRIKE","cp":4099,"lv":40,"d":45.45,"d0":45.45,"d1":45.45,"dp":100,"m":0,"m0":0,"m1":0,"td":600,"td0":600,"td1":600,"e":0.07,"e0":0.07,"e1":0.07,"tw":13.2,"er":86.64,"bu":0,"bd":8.9},{"i":"zacian_crowned_sword","n":"Zacian (Crowned Sword)","f":"AIR_SLASH","c":"BEHEMOTH_BLADE","cp":4979,"lv":40,"d":47.62,"d0":47.62,"d1":47.62,"dp":100,"m":0,"m0":0,"m1":0,"td":600,"td0":600,"td1":600,"e":0.07,"e0":0.07,"e1":0.07,"tw":12.6,"er":89.72,"bu":0,"bd":8.6},{"i":"metagross_shadow","n":"Metagross (Shadow)","f":"BULLET_PUNCH","c":"METEOR_MASH","cp":3791,"lv":40,"d":50.65,"d0":48.19,"d1":52.63,"dp":100,"m":0,"m0":0,"m1":0,"td":600,"td0":600,"td1":600,"e":0.07,"e0":0.06,"e1":0.07,"tw":11.9,"er":93.96,"bu":0.7,"bd":11.1},{"i":"lucario_mega","n":"Lucario (Mega)","f":"BULLET_PUNCH","c":"METEOR_MASH","cp":3826,"lv":40,"d":50.66,"d0":48.19,"d1":52.63,"dp":100,"m":0,"m0":0,"m1":0,"td":600,"td0":600,"td1":600,"e":0.07,"e0":0.06,"e1":0.07,"tw":11.9,"er":93.98,"bu":0.7,"bd":12.9},{"i":"metagross_mega","n":"Metagross (Mega)","f":"BULLET_PUNCH","c":"METEOR_MASH","cp":4911,"lv":40,"d":48.19,"d0":48.19,"d1":48.19,"dp":100,"m":0,"m0":0,"m1":0,"td":600,"td0":600,"td1":600,"e":0.07,"e0":0.07,"e1":0.07,"tw":12.4,"er":90.53,"bu":0.6,"bd":7.4},{"i":"zamazenta_crowned_shield","n":"Zamazenta (Crowned Shield)","f":"METAL_CLAW","c":"BEHEMOTH_BASH","cp":4172,"lv":40,"d":48.17,"d0":46.15,"d1":50.42,"dp":100,"m":0,"m0":0,"m1":0,"td":600,"td0":600,"td1":600,"e":0.07,"e0":0.07,"e1":0.07,"tw":12.5,"er":90.49,"bu":0.9,"bd":7.4},{"i":"regigigas_shadow","n":"Regigigas (Shadow)","f":"HIDDEN_POWER_POISON","c":"CRUSH_GRIP","cp":4346,"lv":40,"d":45.63,"d0":45.63,"d1":45.63,"dp":100,"m":0,"m0":0,"m1":0,"td":600,"td0":600,"td1":600,"e":0.07,"e0":0.07,"e1":0.07,"tw":13.1,"er":86.89,"bu":0.4,"bd":16.1},{"i":"regigigas_shadow","n":"Regigigas (Shadow)","f":"HIDDEN_POWER_STEEL","c":"CRUSH_GRIP","cp":4346,"lv":40,"d":45.63,"d0":45.63,"d1":45.63,"dp":100,"m":0,"m0":0,"m1":0,"td":600,"td0":600,"td1":600,"e":0.07,"e0":0.07,"e1":0.07,"tw":13.1,"er":86.89,"bu":0.4,"bd":16.1},{"i":"necrozma_dusk_mane","n":"Necrozma (Dusk Mane)","f":"PSYCHO_CUT","c":"SUNSTEEL_STRIKE","cp":4099,"lv":40,"d":43.01,"d0":43.01,"d1":43.01,"dp":100,"m":0,"m0":0,"m1":0,"td":600,"td0":600,"td1":600,"e":0.08,"e0":0.08,"e1":0.08,"tw":13.9,"er":83.12,"bu":0.8,"bd":8.9},{"i":"metagross_shadow","n":"Metagross (Shadow)","f":"ZEN_HEADBUTT","c":"METEOR_MASH","cp":3791,"lv":40,"d":43.65,"d0":41.24,"d1":44.44,"dp":100,"m":0,"m0":0,"m1":0,"td":600,"td0":600,"td1":600,"e":0.08,"e0":0.08,"e1":0.08,"tw":13.8,"er":84.05,"bu":0.8,"bd":11.1},{"i":"metagross_shadow","n":"Metagross (Shadow)","f":"SHADOW_CLAW","c":"METEOR_MASH","cp":3791,"lv":40,"d":39.35,"d0":37.04,"d1":39.74,"dp":100,"m":0,"m0":0,"m1":0,"td":600,"td0":600,"td1":600,"e":0.08,"e0":0.08,"e1":0.09,"tw":15.3,"er":77.76,"bu":0.9,"bd":11.1},{"i":"metagross_mega","n":"Metagross (Mega)","f":"ZEN_HEADBUTT","c":"METEOR_MASH","cp":4911,"lv":40,"d":42.16,"d0":41.24,"d1":44.44,"dp":100,"m":0,"m0":0,"m1":0,"td":600,"td0":600,"td1":600,"e":0.08,"e0":0.08,"e1":0.08,"tw":14.2,"er":81.88,"bu":0.9,"bd":7.4},{"i":"beedrill_mega","n":"Beedrill (Mega)","f":"POISON_JAB","c":"SLUDGE_BOMB","cp":3383,"lv":40,"d":43.63,"d0":41.24,"d1":44.44,"dp":100,"m":0,"m0":0,"m1":0,"td":600,"td0":600,"td1":600,"e":0.08,"e0":0.08,"e1":0.08,"tw":13.8,"er":84.02,"bu":0.8,"bd":10},{"i":"naganadel","n":"Naganadel","f":"POISON_JAB","c":"SLUDGE_BOMB","cp":3173,"lv":40,"d":43.7,"d0":41.24,"d1":44.44,"dp":100,"m":0,"m0":0,"m1":0,"td":600,"td0":600,"td1":600,"e":0.08,"e0":0.08,"e1":0.08,"tw":13.7,"er":84.12,"bu":0.8,"bd":8.6},{"i":"blacephalon","n":"Blacephalon","f":"ASTONISH","c":"MIND_BLOWN","cp":3297,"lv":40,"d":43.77,"d0":41.24,"d1":44.44,"dp":100,"m":0,"m0":0,"m1":0,"td":600,"td0":600,"td1":600,"e":0.08,"e0":0.08,"e1":0.08,"tw":13.7,"er":84.23,"bu":0.8,"bd":17.7},{"i":"blacephalon","n":"Blacephalon","f":"INCINERATE","c":"MIND_BLOWN","cp":3297,"lv":40,"d":40.68,"d0":40.68,"d1":40.68,"dp":100,"m":0,"m0":0,"m1":0,"td":600,"td0":600,"td1":600,"e":0.08,"e0":0.08,"e1":0.08,"tw":14.8,"er":79.72,"bu":0.6,"bd":17.7},{"i":"eternatus","n":"Eternatus","f":"POISON_JAB","c":"SLUDGE_BOMB","cp":4429,"lv":40,"d":42.08,"d0":41.24,"d1":44.44,"dp":100,"m":0,"m0":0,"m1":0,"td":600,"td0":600,"td1":600,"e":0.08,"e0":0.08,"e1":0.08,"tw":14.3,"er":81.77,"bu":0.8,"bd":4.9},{"i":"gengar_mega","n":"Gengar (Mega)","f":"SHADOW_CLAW","c":"SLUDGE_BOMB","cp":4336,"lv":40,"d":39.35,"d0":37.04,"d1":39.74,"dp":100,"m":0,"m0":0,"m1":0,"td":600,"td0":600,"td1":600,"e":0.08,"e0":0.08,"e1":0.09,"tw":15.3,"er":77.76,"bu":0.9,"bd":12.7},{"i":"dialga_shadow","n":"Dialga (Shadow)","f":"METAL_CLAW","c":"IRON_HEAD","cp":4038,"lv":40,"d":39.29,"d0":38.83,"d1":44.44,"dp":100,"m":0,"m0":0,"m1":0,"td":600,"td0":600,"td1":600,"e":0.08,"e0":0.08,"e1":0.09,"tw":15.3,"er":77.68,"bu":0.8,"bd":6.9},{"i":"zacian_crowned_sword","n":"Zacian (Crowned Sword)","f":"METAL_CLAW","c":"GIGA_IMPACT","cp":4979,"lv":40,"d":35.09,"d0":35.09,"d1":35.09,"dp":100,"m":0,"m0":0,"m1":0,"td":600,"td0":600,"td1":600,"e":0.09,"e0":0.1,"e1":0.1,"tw":17.1,"er":71.35,"bu":0.9,"bd":8.6},{"i":"metagross_shadow","n":"Metagross (Shadow)","f":"FURY_CUTTER","c":"METEOR_MASH","cp":3791,"lv":40,"d":37.85,"d0":36.47,"d1":39.09,"dp":100,"m":0,"m0":0,"m1":0,"td":600,"td0":600,"td1":600,"e":0.09,"e0":0.09,"e1":0.09,"tw":15.9,"er":75.52,"bu":0.9,"bd":11.1},{"i":"lucario_mega","n":"Lucario (Mega)","f":"FORCE_PALM","c":"METEOR_MASH","cp":3826,"lv":40,"d":38.67,"d0":36.36,"d1":38.83,"dp":100,"m":0,"m0":0,"m1":0,"td":600,"td0":600,"td1":600,"e":0.09,"e0":0.09,"e1":0.09,"tw":15.5,"er":76.75,"bu":0.8,"bd":12.9},{"i":"metagross_mega","n":"Metagross (Mega)","f":"SHADOW_CLAW","c":"METEOR_MASH","cp":4911,"lv":40,"d":38.18,"d0":37.04,"d1":38.34,"dp":100,"m":0,"m0":0,"m1":0,"td":600,"td0":600,"td1":600,"e":0.09,"e0":0.09,"e1":0.09,"tw":15.7,"er":76.01,"bu":0.9,"bd":7.4},{"i":"metagross_mega","n":"Metagross (Mega)","f":"FURY_CUTTER","c":"METEOR_MASH","cp":4911,"lv":40,"d":37.71,"d0":36.47,"d1":37.74,"dp":100,"m":0,"m0":0,"m1":0,"td":600,"td0":600,"td1":600,"e":0.09,"e0":0.09,"e1":0.09,"tw":15.9,"er":75.31,"bu":0.9,"bd":7.4},{"i":"zamazenta_crowned_shield","n":"Zamazenta (Crowned Shield)","f":"ICE_FANG","c":"BEHEMOTH_BASH","cp":4172,"lv":40,"d":38.77,"d0":36.59,"d1":40.4,"dp":100,"m":0,"m0":0,"m1":0,"td":600,"td0":600,"td1":600,"e":0.09,"e0":0.08,"e1":0.09,"tw":15.5,"er":76.89,"bu":0.9,"bd":7.4},{"i":"gengar_mega","n":"Gengar (Mega)","f":"LICK","c":"SLUDGE_BOMB","cp":4336,"lv":40,"d":39.09,"d0":39.09,"d1":39.09,"dp":100,"m":0,"m0":0,"m1":0,"td":600,"td0":600,"td1":600,"e":0.09,"e0":0.09,"e1":0.09,"tw":15.4,"er":77.37,"bu":0.8,"bd":12.7},{"i":"metagross","n":"Metagross","f":"BULLET_PUNCH","c":"METEOR_MASH","cp":3791,"lv":40,"d":36.36,"d0":36.36,"d1":36.36,"dp":100,"m":0,"m0":0,"m1":0,"td":600,"td0":600,"td1":600,"e":0.09,"e0":0.09,"e1":0.09,"tw":16.5,"er":73.29,"bu":0.8,"bd":9.3},{"i":"metagross","n":"Metagross","f":"FURY_CUTTER","c":"METEOR_MASH","cp":3791,"lv":40,"d":37.71,"d0":36.47,"d1":39.09,"dp":100,"m":0,"m0":0,"m1":0,"td":600,"td0":600,"td1":600,"e":0.09,"e0":0.09,"e1":0.09,"tw":15.9,"er":75.31,"bu":0.8,"bd":9.3},{"i":"lucario","n":"Lucario","f":"FORCE_PALM","c":"METEOR_MASH","cp":2703,"lv":40,"d":38.64,"d0":36.36,"d1":38.83,"dp":100,"m":0,"m0":0,"m1":0,"td":600,"td0":600,"td1":600,"e":0.09,"e0":0.09,"e1":0.09,"tw":15.5,"er":76.71,"bu":0.7,"bd":15},{"i":"deoxys_attack","n":"Deoxys (Attack)","f":"POISON_JAB","c":"ZAP_CANNON","cp":2580,"lv":40,"d":38.37,"d0":35.23,"d1":40.86,"dp":100,"m":0,"m0":0,"m1":1,"td":600,"td0":600,"td1":600,"e":0.09,"e0":0.08,"e1":0.09,"tw":15.6,"er":76.31,"bu":0.8,"bd":76.7},{"i":"mewtwo_shadow","n":"Mewtwo (Shadow)","f":"PSYCHO_CUT","c":"PSYSTRIKE","cp":4178,"lv":40,"d":36.08,"d0":34.19,"d1":37.74,"dp":100,"m":0,"m0":0,"m1":0,"td":600,"td0":600,"td1":600,"e":0.09,"e0":0.09,"e1":0.1,"tw":16.6,"er":72.85,"bu":0.9,"bd":19.4},{"i":"haunter_shadow","n":"Haunter (Shadow)","f":"ASTONISH","c":"SLUDGE_BOMB","cp":1963,"lv":40,"d":35.57,"d0":32.26,"d1":36.36,"dp":100,"m":0,"m0":0,"m1":0,"td":600,"td0":600,"td1":600,"e":0.09,"e0":0.09,"e1":0.1,"tw":16.9,"er":72.09,"bu":0.8,"bd":31},{"i":"toxicroak_shadow","n":"Toxicroak (Shadow)","f":"POISON_JAB","c":"SLUDGE_BOMB","cp":2488,"lv":40,"d":36.44,"d0":36.36,"d1":41.24,"dp":100,"m":0,"m0":0,"m1":0,"td":600,"td0":600,"td1":600,"e":0.09,"e0":0.08,"e1":0.09,"tw":16.5,"er":73.41,"bu":0.9,"bd":17.6},{"i":"darkrai_shadow","n":"Darkrai (Shadow)","f":"SNARL","c":"SLUDGE_BOMB","cp":3739,"lv":40,"d":35.72,"d0":32.26,"d1":36.36,"dp":100,"m":0,"m0":0,"m1":0,"td":600,"td0":600,"td1":600,"e":0.09,"e0":0.09,"e1":0.1,"tw":16.8,"er":72.32,"bu":0.9,"bd":21.8},{"i":"rayquaza_mega","n":"Rayquaza (Mega)","f":"AIR_SLASH","c":"DRAGON_ASCENT","cp":5713,"lv":40,"d":36.14,"d0":36.14,"d1":36.14,"dp":100,"m":0,"m0":0,"m1":0,"td":600,"td0":600,"td1":600,"e":0.09,"e0":0.09,"e1":0.09,"tw":16.6,"er":72.96,"bu":0.9,"bd":5.2},{"i":"rayquaza_mega","n":"Rayquaza (Mega)","f":"DRAGON_TAIL","c":"DRAGON_ASCENT","cp":5713,"lv":40,"d":36.14,"d0":36.14,"d1":36.14,"dp":100,"m":0,"m0":0,"m1":0,"td":600,"td0":600,"td1":600,"e":0.09,"e0":0.09,"e1":0.09,"tw":16.6,"er":72.96,"bu":0.8,"bd":5.2},{"i":"genesect","n":"Genesect","f":"METAL_CLAW","c":"MAGNET_BOMB","cp":3353,"lv":40,"d":35.39,"d0":34.38,"d1":35.5,"dp":100,"m":0,"m0":0,"m1":0,"td":600,"td0":600,"td1":600,"e":0.09,"e0":0.09,"e1":0.1,"tw":17,"er":71.81,"bu":0.9,"bd":7.4},{"i":"genesect_burn","n":"Genesect (Burn)","f":"METAL_CLAW","c":"MAGNET_BOMB","cp":3353,"lv":40,"d":35.4,"d0":34.38,"d1":35.5,"dp":100,"m":0,"m0":0,"m1":0,"td":600,"td0":600,"td1":600,"e":0.09,"e0":0.09,"e1":0.1,"tw":16.9,"er":71.83,"bu":0.9,"bd":7.4},{"i":"genesect_chill","n":"Genesect (Chill)","f":"METAL_CLAW","c":"MAGNET_BOMB","cp":3353,"lv":40,"d":35.4,"d0":34.38,"d1":35.5,"dp":100,"m":0,"m0":0,"m1":0,"td":600,"td0":600,"td1":600,"e":0.09,"e0":0.09,"e1":0.1,"tw":16.9,"er":71.83,"bu":0.9,"bd":7.4},{"i":"genesect_douse","n":"Genesect (Douse)","f":"METAL_CLAW","c":"MAGNET_BOMB","cp":3353,"lv":40,"d":35.41,"d0":34.38,"d1":35.5,"dp":100,"m":0,"m0":0,"m1":0,"td":600,"td0":600,"td1":600,"e":0.09,"e0":0.09,"e1":0.1,"tw":16.9,"er":71.85,"bu":0.9,"bd":7.4},{"i":"genesect_shock","n":"Genesect (Shock)","f":"METAL_CLAW","c":"MAGNET_BOMB","cp":3353,"lv":40,"d":35.39,"d0":34.38,"d1":35.5,"dp":100,"m":0,"m0":0,"m1":0,"td":600,"td0":600,"td1":600,"e":0.09,"e0":0.09,"e1":0.1,"tw":17,"er":71.81,"bu":0.9,"bd":7.4},{"i":"gengar_shadow","n":"Gengar (Shadow)","f":"SHADOW_CLAW","c":"SLUDGE_BOMB","cp":2878,"lv":40,"d":35.42,"d0":34.19,"d1":39.74,"dp":100,"m":0,"m0":0,"m1":0,"td":600,"td0":600,"td1":600,"e":0.09,"e0":0.08,"e1":0.1,"tw":17,"er":71.86,"bu":0.8,"bd":19.4},{"i":"excadrill_shadow","n":"Excadrill (Shadow)","f":"METAL_CLAW","c":"IRON_HEAD","cp":3244,"lv":40,"d":35.09,"d0":35.09,"d1":35.09,"dp":100,"m":0,"m0":0,"m1":0,"td":600,"td0":600,"td1":600,"e":0.09,"e0":0.1,"e1":0.1,"tw":17.1,"er":71.35,"bu":0.9,"bd":23.2},{"i":"lucario_mega","n":"Lucario (Mega)","f":"COUNTER","c":"METEOR_MASH","cp":3826,"lv":40,"d":34.19,"d0":34.19,"d1":34.19,"dp":100,"m":0,"m0":0,"m1":0,"td":600,"td0":600,"td1":600,"e":0.1,"e0":0.1,"e1":0.1,"tw":17.5,"er":69.98,"bu":0.9,"bd":12.9},{"i":"regigigas_shadow","n":"Regigigas (Shadow)","f":"HIDDEN_POWER_POISON","c":"GIGA_IMPACT","cp":4346,"lv":40,"d":34.48,"d0":34.48,"d1":34.48,"dp":100,"m":0,"m0":0,"m1":0,"td":600,"td0":600,"td1":600,"e":0.1,"e0":0.1,"e1":0.1,"tw":17.4,"er":70.43,"bu":0.8,"bd":16.1},{"i":"regigigas_shadow","n":"Regigigas (Shadow)","f":"HIDDEN_POWER_STEEL","c":"GIGA_IMPACT","cp":4346,"lv":40,"d":34.48,"d0":34.48,"d1":34.48,"dp":100,"m":0,"m0":0,"m1":0,"td":600,"td0":600,"td1":600,"e":0.1,"e0":0.1,"e1":0.1,"tw":17.4,"er":70.43,"bu":0.8,"bd":16.1},{"i":"beedrill_mega","n":"Beedrill (Mega)","f":"INFESTATION","c":"SLUDGE_BOMB","cp":3383,"lv":40,"d":34.02,"d0":32.26,"d1":34.19,"dp":100,"m":0,"m0":0,"m1":0,"td":600,"td0":600,"td1":600,"e":0.1,"e0":0.1,"e1":0.1,"tw":17.6,"er":69.72,"bu":0.8,"bd":10},{"i":"beedrill_mega","n":"Beedrill (Mega)","f":"POISON_STING","c":"SLUDGE_BOMB","cp":3383,"lv":40,"d":34.19,"d0":34.19,"d1":34.19,"dp":100,"m":0,"m0":0,"m1":0,"td":600,"td0":600,"td1":600,"e":0.1,"e0":0.1,"e1":0.1,"tw":17.5,"er":69.98,"bu":0.8,"bd":10},{"i":"gengar_mega","n":"Gengar (Mega)","f":"HEX","c":"SLUDGE_BOMB","cp":4336,"lv":40,"d":34.19,"d0":34.19,"d1":34.19,"dp":100,"m":0,"m0":0,"m1":0,"td":600,"td0":600,"td1":600,"e":0.1,"e0":0.1,"e1":0.1,"tw":17.5,"er":69.98,"bu":0.9,"bd":12.7},{"i":"deoxys_attack","n":"Deoxys (Attack)","f":"POISON_JAB","c":"PSYCHO_BOOST","cp":2580,"lv":40,"d":33.56,"d0":30.08,"d1":40,"dp":100,"m":1,"m0":0,"m1":1,"td":600,"td0":600,"td1":600,"e":0.1,"e0":0.08,"e1":0.11,"tw":18.1,"er":69,"bu":0.7,"bd":76.7},{"i":"mewtwo_shadow","n":"Mewtwo (Shadow)","f":"PSYCHO_CUT","c":"PSYCHIC","cp":4178,"lv":40,"d":34.14,"d0":32.35,"d1":35.5,"dp":100,"m":0,"m0":0,"m1":0,"td":600,"td0":600,"td1":600,"e":0.1,"e0":0.09,"e1":0.1,"tw":17.6,"er":69.9,"bu":0.9,"bd":19.4},{"i":"gengar_shadow","n":"Gengar (Shadow)","f":"HEX","c":"SLUDGE_BOMB","cp":2878,"lv":40,"d":34.1,"d0":32.26,"d1":34.19,"dp":100,"m":0,"m0":0,"m1":0,"td":600,"td0":600,"td1":600,"e":0.1,"e0":0.1,"e1":0.1,"tw":17.6,"er":69.85,"bu":0.9,"bd":19.4},{"i":"aggron_shadow","n":"Aggron (Shadow)","f":"IRON_TAIL","c":"HEAVY_SLAM","cp":3000,"lv":40,"d":34.53,"d0":31.09,"d1":34.88,"dp":100,"m":0,"m0":0,"m1":0,"td":600,"td0":600,"td1":600,"e":0.1,"e0":0.1,"e1":0.11,"tw":17.4,"er":70.5,"bu":1,"bd":17},{"i":"alakazam_mega","n":"Alakazam (Mega)","f":"PSYCHO_CUT","c":"PSYCHIC","cp":4510,"lv":40,"d":34.07,"d0":32.35,"d1":34.38,"dp":100,"m":0,"m0":0,"m1":0,"td":600,"td0":600,"td1":600,"e":0.1,"e0":0.1,"e1":0.1,"tw":17.6,"er":69.79,"bu":0.9,"bd":20.5}]}