{"average":[{"i":"porygon_z_shadow","n":"Porygon-Z (Shadow)","f":"CHARGE_BEAM","c":"SOLAR_BEAM","cp":3266,"lv":40,"d":81.63,"d0":81.63,"d1":81.63,"dp":100,"m":0,"m0":0,"m1":0,"td":600,"td0":600,"td1":600,"e":0.04,"e0":0.04,"e1":0.04,"tw":7.3,"er":134.41,"bu":0,"bd":23.2},{"i":"zapdos_shadow","n":"Zapdos (Shadow)","f":"THUNDER_SHOCK","c":"ZAP_CANNON","cp":3527,"lv":40,"d":77.92,"d0":77.92,"d1":77.92,"dp":100,"m":0,"m0":0,"m1":0,"td":600,"td0":600,"td1":600,"e":0.04,"e0":0.04,"e1":0.04,"tw":7.7,"er":129.8,"bu":0,"bd":18.9},{"i":"regieleki","n":"Regieleki","f":"THUNDER_SHOCK","c":"THUNDER_CAGE","cp":2803,"lv":40,"d":77.92,"d0":77.92,"d1":77.92,"dp":100,"m":0,"m0":0,"m1":0,"td":600,"td0":600,"td1":600,"e":0.04,"e0":0.04,"e1":0.04,"tw":7.7,"er":129.8,"bu":0,"bd":24.1},{"i":"regieleki","n":"Regieleki","f":"VOLT_SWITCH","c":"THUNDER_CAGE","cp":2803,"lv":40,"d":77.42,"d0":77.42,"d1":77.42,"dp":100,"m":0,"m0":0,"m1":0,"td":600,"td0":600,"td1":600,"e":0.04,"e0":0.04,"e1":0.04,"tw":7.8,"er":129.17,"bu":0,"bd":24.1},{"i":"ampharos_mega","n":"Ampharos (Mega)","f":"VOLT_SWITCH","c":"ZAP_CANNON","cp":4245,"lv":40,"d":77.42,"d0":77.42,"d1":77.42,"dp":100,"m":0,"m0":0,"m1":0,"td":600,"td0":600,"td1":600,"e":0.04,"e0":0.04,"e1":0.04,"tw":7.8,"er":129.17,"bu":0,"bd":9.1},{"i":"magnezone_shadow","n":"Magnezone (Shadow)","f":"VOLT_SWITCH","c":"ZAP_CANNON","cp":3205,"lv":40,"d":77.42,"d0":77.42,"d1":77.42,"dp":100,"m":0,"m0":0,"m1":0,"td":600,"td0":600,"td1":600,"e":0.04,"e0":0.04,"e1":0.04,"tw":7.8,"er":129.17,"bu":0,"bd":20.4},{"i":"thundurus_therian","n":"Thundurus (Therian)","f":"VOLT_SWITCH","c":"WILDBOLT_STORM","cp":3659,"lv":40,"d":77.42,"d0":77.42,"d1":77.42,"dp":100,"m":0,"m0":0,"m1":0,"td":600,"td0":600,"td1":600,"e":0.04,"e0":0.04,"e1":0.04,"tw":7.8,"er":129.17,"bu":0,"bd":19.4},{"i":"regieleki","n":"Regieleki","f":"LOCK_ON","c":"THUNDER_CAGE","cp":2803,"lv":40,"d":60.91,"d0":60.91,"d1":60.91,"dp":100,"m":0,"m0":0,"m1":0,"td":600,"td0":600,"td1":600,"e":0.05,"e0":0.05,"e1":0.05,"tw":9.9,"er":107.91,"bu":0.7,"bd":24.1},{"i":"magnezone_shadow","n":"Magnezone (Shadow)","f":"SPARK","c":"ZAP_CANNON","cp":3205,"lv":40,"d":64.73,"d0":64.17,"d1":68.18,"dp":100,"m":0,"m0":0,"m1":0,"td":600,"td0":600,"td1":600,"e":0.05,"e0":0.05,"e1":0.05,"tw":9.3,"er":112.94,"bu":0,"bd":20.4},{"i":"exeggutor_alolan_shadow","n":"Exeggutor (Alolan) (Shadow)","f":"BULLET_SEED","c":"SOLAR_BEAM","cp":3014,"lv":40,"d":71.43,"d0":71.43,"d1":71.43,"dp":100,"m":0,"m0":0,"m1":0,"td":600,"td0":600,"td1":600,"e":0.05,"e0":0.05,"e1":0.05,"tw":8.4,"er":121.6,"bu":0,"bd":8.2},{"i":"exeggutor_shadow","n":"Exeggutor (Shadow)","f":"BULLET_SEED","c":"SOLAR_BEAM","cp":3014,"lv":40,"d":71.43,"d0":71.43,"d1":71.43,"dp":100,"m":0,"m0":0,"m1":0,"td":600,"td0":600,"td1":600,"e":0.05,"e0":0.05,"e1":0.05,"tw":8.4,"er":121.6,"bu":0,"bd":13.7},{"i":"exeggutor_shadow","n":"Exeggutor (Shadow)","f":"EXTRASENSORY","c":"SOLAR_BEAM","cp":3014,"lv":40,"d":63.49,"d0":63.49,"d1":63.49,"dp":100,"m":0,"m0":0,"m1":0,"td":600,"td0":600,"td1":600,"e":0.05,"e0":0.05,"e1":0.05,"tw":9.4,"er":111.32,"bu":0,"bd":13.7},{"i":"tapu_bulu","n":"Tapu Bulu","f":"BULLET_SEED","c":"SOLAR_BEAM","cp":3419,"lv":40,"d":71.43,"d0":71.43,"d1":71.43,"dp":100,"m":0,"m0":0,"m1":0,"td":600,"td0":600,"td1":600,"e":0.05,"e0":0.05,"e1":0.05,"tw":8.4,"er":121.6,"bu":0,"bd":10.2},{"i":"groudon_primal","n":"Groudon (Primal)","f":"MUD_SHOT","c":"SOLAR_BEAM","cp":5902,"lv":40,"d":64.86,"d0":64.17,"d1":68.18,"dp":100,"m":0,"m0":0,"m1":0,"td":600,"td0":600,"td1":600,"e":0.05,"e0":0.05,"e1":0.05,"tw":9.3,"er":113.11,"bu":0,"bd":26.6},{"i":"groudon_shadow","n":"Groudon (Shadow)","f":"MUD_SHOT","c":"SOLAR_BEAM","cp":4115,"lv":40,"d":68.18,"d0":68.18,"d1":68.18,"dp":100,"m":0,"m0":0,"m1":0,"td":600,"td0":600,"td1":600,"e":0.05,"e0":0.05,"e1":0.05,"tw":8.8,"er":117.43,"bu":0,"bd":24.9},{"i":"sceptile_mega","n":"Sceptile (Mega)","f":"FURY_CUTTER","c":"FRENZY_PLANT","cp":4056,"lv":40,"d":62.8,"d0":62.5,"d1":66.3,"dp":100,"m":0,"m0":0,"m1":0,"td":600,"td0":600,"td1":600,"e":0.05,"e0":0.05,"e1":0.05,"tw":9.6,"er":110.41,"bu":0.6,"bd":7.5},{"i":"sceptile_shadow","n":"Sceptile (Shadow)","f":"FURY_CUTTER","c":"FRENZY_PLANT","cp":2757,"lv":40,"d":63.02,"d0":62.5,"d1":66.3,"dp":100,"m":0,"m0":0,"m1":0,"td":600,"td0":600,"td1":600,"e":0.05,"e0":0.05,"e1":0.05,"tw":9.5,"er":110.71,"bu":0.3,"bd":15},{"i":"electivire_shadow","n":"Electivire (Shadow)","f":"THUNDER_SHOCK","c":"WILD_CHARGE","cp":3079,"lv":40,"d":62.65,"d0":56.07,"d1":66.3,"dp":100,"m":0,"m0":0,"m1":0,"td":600,"td0":600,"td1":600,"e":0.05,"e0":0.05,"e1":0.06,"tw":9.6,"er":110.22,"bu":0.7,"bd":24},{"i":"victreebel","n":"Victreebel","f":"MAGICAL_LEAF","c":"SOLAR_BEAM","cp":2431,"lv":40,"d":64.52,"d0":64.52,"d1":64.52,"dp":100,"m":0,"m0":0,"m1":0,"td":600,"td0":600,"td1":600,"e":0.05,"e0":0.05,"e1":0.05,"tw":9.3,"er":112.67,"bu":0,"bd":14.2},{"i":"victreebel_mega","n":"Victreebel (Mega)","f":"MAGICAL_LEAF","c":"SOLAR_BEAM","cp":3505,"lv":40,"d":64.52,"d0":64.52,"d1":64.52,"dp":100,"m":0,"m0":0,"m1":0,"td":600,"td0":600,"td1":600,"e":0.05,"e0":0.05,"e1":0.05,"tw":9.3,"er":112.67,"bu":0,"bd":11.1},{"i":"victreebel_shadow","n":"Victreebel (Shadow)","f":"MAGICAL_LEAF","c":"SOLAR_BEAM","cp":2431,"lv":40,"d":64.52,"d0":64.52,"d1":64.52,"dp":100,"m":0,"m0":0,"m1":0,"td":600,"td0":600,"td1":600,"e":0.05,"e0":0.05,"e1":0.05,"tw":9.3,"er":112.67,"bu":0,"bd":16.7},{"i":"meganium_shadow","n":"Meganium (Shadow)","f":"MAGICAL_LEAF","c":"SOLAR_BEAM","cp":2410,"lv":40,"d":64.52,"d0":64.52,"d1":64.52,"dp":100,"m":0,"m0":0,"m1":0,"td":600,"td0":600,"td1":600,"e":0.05,"e0":0.05,"e1":0.05,"tw":9.3,"er":112.67,"bu":0,"bd":11.7},{"i":"roserade","n":"Roserade","f":"MAGICAL_LEAF","c":"SOLAR_BEAM","cp":2971,"lv":40,"d":64.52,"d0":64.52,"d1":64.52,"dp":100,"m":0,"m0":0,"m1":0,"td":600,"td0":600,"td1":600,"e":0.05,"e0":0.05,"e1":0.05,"tw":9.3,"er":112.67,"bu":0,"bd":12.7},{"i":"shaymin_land","n":"Shaymin (Land)","f":"MAGICAL_LEAF","c":"SOLAR_BEAM","cp":3265,"lv":40,"d":64.52,"d0":64.52,"d1":64.52,"dp":100,"m":0,"m0":0,"m1":0,"td":600,"td0":600,"td1":600,"e":0.05,"e0":0.05,"e1":0.05,"tw":9.3,"er":112.67,"bu":0,"bd":7.9},{"i":"shaymin_sky","n":"Shaymin (Sky)","f":"MAGICAL_LEAF","c":"SOLAR_BEAM","cp":3592,"lv":40,"d":64.52,"d0":64.52,"d1":64.52,"dp":100,"m":0,"m0":0,"m1":0,"td":600,"td0":600,"td1":600,"e":0.05,"e0":0.05,"e1":0.05,"tw":9.3,"er":112.67,"bu":0,"bd":10.1},{"i":"lilligant","n":"Lilligant","f":"MAGICAL_LEAF","c":"SOLAR_BEAM","cp":2550,"lv":40,"d":64.52,"d0":64.52,"d1":64.52,"dp":100,"m":0,"m0":0,"m1":0,"td":600,"td0":600,"td1":600,"e":0.05,"e0":0.05,"e1":0.05,"tw":9.3,"er":112.67,"bu":0,"bd":13.6},{"i":"lilligant_hisuian","n":"Lilligant (Hisuian)","f":"MAGICAL_LEAF","c":"SOLAR_BEAM","cp":2512,"lv":40,"d":64.52,"d0":64.52,"d1":64.52,"dp":100,"m":0,"m0":0,"m1":0,"td":600,"td0":600,"td1":600,"e":0.05,"e0":0.05,"e1":0.05,"tw":9.3,"er":112.67,"bu":0,"bd":13.6},{"i":"zapdos_shadow","n":"Zapdos (Shadow)","f":"THUNDER_SHOCK","c":"THUNDERBOLT","cp":3527,"lv":40,"d":60.34,"d0":56.07,"d1":66.3,"dp":100,"m":0,"m0":0,"m1":0,"td":600,"td0":600,"td1":600,"e":0.06,"e0":0.05,"e1":0.06,"tw":10,"er":107.14,"bu":0.7,"bd":18.9},{"i":"zapdos_shadow","n":"Zapdos (Shadow)","f":"CHARGE_BEAM","c":"THUNDERBOLT","cp":3527,"lv":40,"d":60.58,"d0":57.97,"d1":64.52,"dp":100,"m":0,"m0":0,"m1":0,"td":600,"td0":600,"td1":600,"e":0.06,"e0":0.05,"e1":0.06,"tw":9.9,"er":107.47,"bu":0.6,"bd":18.9},{"i":"magnezone_shadow","n":"Magnezone (Shadow)","f":"CHARGE_BEAM","c":"WILD_CHARGE","cp":3205,"lv":40,"d":60.43,"d0":57.97,"d1":64.52,"dp":100,"m":0,"m0":0,"m1":0,"td":600,"td0":600,"td1":600,"e":0.06,"e0":0.05,"e1":0.06,"tw":10,"er":107.28,"bu":0.6,"bd":20.4},{"i":"thundurus_therian","n":"Thundurus (Therian)","f":"VOLT_SWITCH","c":"THUNDERBOLT","cp":3659,"lv":40,"d":57.69,"d0":55.81,"d1":65.22,"dp":100,"m":0,"m0":0,"m1":0,"td":600,"td0":600,"td1":600,"e":0.06,"e0":0.05,"e1":0.06,"tw":10.4,"er":103.61,"bu":0.5,"bd":19.4},{"i":"sceptile_mega","n":"Sceptile (Mega)","f":"BULLET_SEED","c":"FRENZY_PLANT","cp":4056,"lv":40,"d":56.97,"d0":52.63,"d1":57.97,"dp":100,"m":0,"m0":0,"m1":0,"td":600,"td0":600,"td1":600,"e":0.06,"e0":0.06,"e1":0.06,"tw":10.5,"er":102.63,"bu":0.9,"bd":7.5},{"i":"sceptile_shadow","n":"Sceptile (Shadow)","f":"BULLET_SEED","c":"FRENZY_PLANT","cp":2757,"lv":40,"d":55.3,"d0":52.63,"d1":57.97,"dp":100,"m":0,"m0":0,"m1":0,"td":600,"td0":600,"td1":600,"e":0.06,"e0":0.06,"e1":0.06,"tw":10.9,"er":100.37,"bu":0.6,"bd":15},{"i":"victreebel_mega","n":"Victreebel (Mega)","f":"ACID","c":"SOLAR_BEAM","cp":3505,"lv":40,"d":57.14,"d0":57.14,"d1":57.14,"dp":100,"m":0,"m0":0,"m1":0,"td":600,"td0":600,"td1":600,"e":0.06,"e0":0.06,"e1":0.06,"tw":10.5,"er":102.86,"bu":0,"bd":11.1},{"i":"victreebel_shadow","n":"Victreebel (Shadow)","f":"RAZOR_LEAF","c":"LEAF_BLADE","cp":2431,"lv":40,"d":53.18,"d0":48.19,"d1":57.97,"dp":100,"m":0,"m0":0,"m1":0,"td":600,"td0":600,"td1":600,"e":0.06,"e0":0.06,"e1":0.07,"tw":11.4,"er":97.46,"bu":0.7,"bd":16.7},{"i":"victreebel_shadow","n":"Victreebel (Shadow)","f":"ACID","c":"SOLAR_BEAM","cp":2431,"lv":40,"d":57.14,"d0":57.14,"d1":57.14,"dp":100,"m":0,"m0":0,"m1":0,"td":600,"td0":600,"td1":600,"e":0.06,"e0":0.06,"e1":0.06,"tw":10.5,"er":102.86,"bu":0,"bd":16.7},{"i":"meganium_shadow","n":"Meganium (Shadow)","f":"VINE_WHIP","c":"SOLAR_BEAM","cp":2410,"lv":40,"d":57.9,"d0":57.42,"d1":60.61,"dp":100,"m":0,"m0":0,"m1":0,"td":600,"td0":600,"td1":600,"e":0.06,"e0":0.06,"e1":0.06,"tw":10.4,"er":103.88,"bu":0.3,"bd":11.7},{"i":"xurkitree","n":"Xurkitree","f":"THUNDER_SHOCK","c":"POWER_WHIP","cp":3937,"lv":40,"d":60.6,"d0":56.07,"d1":66.3,"dp":100,"m":0,"m0":0,"m1":0,"td":600,"td0":600,"td1":600,"e":0.06,"e0":0.05,"e1":0.06,"tw":9.9,"er":107.5,"bu":0.7,"bd":20.6},{"i":"xurkitree","n":"Xurkitree","f":"SPARK","c":"POWER_WHIP","cp":3937,"lv":40,"d":55.24,"d0":50.85,"d1":59.11,"dp":100,"m":0,"m0":0,"m1":0,"td":600,"td0":600,"td1":600,"e":0.06,"e0":0.06,"e1":0.07,"tw":10.9,"er":100.28,"bu":0.8,"bd":20.6},{"i":"mewtwo_shadow","n":"Mewtwo (Shadow)","f":"PSYCHO_CUT","c":"THUNDERBOLT","cp":4178,"lv":40,"d":58.66,"d0":56.07,"d1":66.3,"dp":100,"m":0,"m0":0,"m1":0,"td":600,"td0":600,"td1":600,"e":0.06,"e0":0.05,"e1":0.06,"tw":10.3,"er":104.9,"bu":0.5,"bd":18.3},{"i":"golem_alolan_shadow","n":"Golem (Alolan) (Shadow)","f":"VOLT_SWITCH","c":"WILD_CHARGE","cp":2949,"lv":40,"d":57.92,"d0":55.81,"d1":65.22,"dp":100,"m":0,"m0":0,"m1":0,"td":600,"td0":600,"td1":600,"e":0.06,"e0":0.05,"e1":0.06,"tw":10.4,"er":103.91,"bu":0.5,"bd":30.2},{"i":"raikou_shadow","n":"Raikou (Shadow)","f":"VOLT_SWITCH","c":"THUNDERBOLT","cp":3452,"lv":40,"d":57.83,"d0":55.81,"d1":65.22,"dp":100,"m":0,"m0":0,"m1":0,"td":600,"td0":600,"td1":600,"e":0.06,"e0":0.05,"e1":0.06,"tw":10.4,"er":103.79,"bu":0.5,"bd":17.7},{"i":"raikou_shadow","n":"Raikou (Shadow)","f":"VOLT_SWITCH","c":"WILD_CHARGE","cp":3452,"lv":40,"d":57.88,"d0":55.81,"d1":65.22,"dp":100,"m":0,"m0":0,"m1":0,"td":600,"td0":600,"td1":600,"e":0.06,"e0":0.05,"e1":0.06,"tw":10.4,"er":103.86,"bu":0.5,"bd":17.7},{"i":"raikou_shadow","n":"Raikou (Shadow)","f":"THUNDER_SHOCK","c":"THUNDERBOLT","cp":3452,"lv":40,"d":59.88,"d0":56.07,"d1":62.5,"dp":100,"m":0,"m0":0,"m1":0,"td":600,"td0":600,"td1":600,"e":0.06,"e0":0.05,"e1":0.06,"tw":10,"er":106.54,"bu":0.7,"bd":17.7},{"i":"raikou_shadow","n":"Raikou (Shadow)","f":"THUNDER_SHOCK","c":"WILD_CHARGE","cp":3452,"lv":40,"d":60.2,"d0":56.07,"d1":62.5,"dp":100,"m":0,"m0":0,"m1":0,"td":600,"td0":600,"td1":600,"e":0.06,"e0":0.05,"e1":0.06,"tw":10,"er":106.96,"bu":0.7,"bd":17.7},{"i":"zeraora","n":"Zeraora","f":"VOLT_SWITCH","c":"WILD_CHARGE","cp":3419,"lv":40,"d":57.23,"d0":55.81,"d1":65.22,"dp":100,"m":0,"m0":0,"m1":0,"td":600,"td0":600,"td1":600,"e":0.06,"e0":0.05,"e1":0.06,"tw":10.5,"er":102.98,"bu":0.5,"bd":16.2},{"i":"zeraora","n":"Zeraora","f":"SPARK","c":"WILD_CHARGE","cp":3419,"lv":40,"d":55.04,"d0":50.85,"d1":56.07,"dp":100,"m":0,"m0":0,"m1":0,"td":600,"td0":600,"td1":600,"e":0.06,"e0":0.06,"e1":0.07,"tw":10.9,"er":100.01,"bu":0.8,"bd":16.2},{"i":"manectric_mega","n":"Manectric (Mega)","f":"CHARGE_BEAM","c":"WILD_CHARGE","cp":3580,"lv":40,"d":60.18,"d0":57.97,"d1":64.52,"dp":100,"m":0,"m0":0,"m1":0,"td":600,"td0":600,"td1":600,"e":0.06,"e0":0.05,"e1":0.06,"tw":10,"er":106.94,"bu":0.5,"bd":19},{"i":"manectric_mega","n":"Manectric (Mega)","f":"SNARL","c":"WILD_CHARGE","cp":3580,"lv":40,"d":54.86,"d0":52.63,"d1":57.97,"dp":100,"m":0,"m0":0,"m1":0,"td":600,"td0":600,"td1":600,"e":0.06,"e0":0.06,"e1":0.06,"tw":11,"er":99.77,"bu":0.5,"bd":19},{"i":"manectric_mega","n":"Manectric (Mega)","f":"THUNDER_FANG","c":"WILD_CHARGE","cp":3580,"lv":40,"d":55.73,"d0":52.63,"d1":57.97,"dp":100,"m":0,"m0":0,"m1":0,"td":600,"td0":600,"td1":600,"e":0.06,"e0":0.06,"e1":0.06,"tw":10.8,"er":100.95,"bu":0.7,"bd":19},{"i":"manectric_shadow","n":"Manectric (Shadow)","f":"THUNDER_FANG","c":"WILD_CHARGE","cp":2340,"lv":40,"d":58.03,"d0":52.63,"d1":64.52,"dp":100,"m":0,"m0":0,"m1":0,"td":600,"td0":600,"td1":600,"e":0.06,"e0":0.05,"e1":0.06,"tw":10.4,"er":104.06,"bu":0.6,"bd":31.3}],"pound_water_pulse":[{"i":"porygon_z_shadow","n":"Porygon-Z (Shadow)","f":"CHARGE_BEAM","c":"SOLAR_BEAM","cp":3266,"lv":40,"d":81.63,"d0":81.63,"d1":81.63,"dp":100,"m":0,"m0":0,"m1":0,"td":600,"td0":600,"td1":600,"e":0.04,"e0":0.04,"e1":0.04,"tw":7.3,"er":134.41,"bu":0,"bd":23.2},{"i":"zapdos_shadow","n":"Zapdos (Shadow)","f":"THUNDER_SHOCK","c":"ZAP_CANNON","cp":3527,"lv":40,"d":77.92,"d0":77.92,"d1":77.92,"dp":100,"m":0,"m0":0,"m1":0,"td":600,"td0":600,"td1":600,"e":0.04,"e0":0.04,"e1":0.04,"tw":7.7,"er":129.8,"bu":0,"bd":18.9},{"i":"regieleki","n":"Regieleki","f":"THUNDER_SHOCK","c":"THUNDER_CAGE","cp":2803,"lv":40,"d":77.92,"d0":77.92,"d1":77.92,"dp":100,"m":0,"m0":0,"m1":0,"td":600,"td0":600,"td1":600,"e":0.04,"e0":0.04,"e1":0.04,"tw":7.7,"er":129.8,"bu":0,"bd":24.1},{"i":"regieleki","n":"Regieleki","f":"VOLT_SWITCH","c":"THUNDER_CAGE","cp":2803,"lv":40,"d":77.42,"d0":77.42,"d1":77.42,"dp":100,"m":0,"m0":0,"m1":0,"td":600,"td0":600,"td1":600,"e":0.04,"e0":0.04,"e1":0.04,"tw":7.8,"er":129.17,"bu":0,"bd":24.1},{"i":"ampharos_mega","n":"Ampharos (Mega)","f":"VOLT_SWITCH","c":"ZAP_CANNON","cp":4245,"lv":40,"d":77.42,"d0":77.42,"d1":77.42,"dp":100,"m":0,"m0":0,"m1":0,"td":600,"td0":600,"td1":600,"e":0.04,"e0":0.04,"e1":0.04,"tw":7.8,"er":129.17,"bu":0,"bd":9.1},{"i":"magnezone_shadow","n":"Magnezone (Shadow)","f":"VOLT_SWITCH","c":"ZAP_CANNON","cp":3205,"lv":40,"d":77.42,"d0":77.42,"d1":77.42,"dp":100,"m":0,"m0":0,"m1":0,"td":600,"td0":600,"td1":600,"e":0.04,"e0":0.04,"e1":0.04,"tw":7.8,"er":129.17,"bu":0,"bd":20.4},{"i":"thundurus_therian","n":"Thundurus (Therian)","f":"VOLT_SWITCH","c":"WILDBOLT_STORM","cp":3659,"lv":40,"d":77.42,"d0":77.42,"d1":77.42,"dp":100,"m":0,"m0":0,"m1":0,"td":600,"td0":600,"td1":600,"e":0.04,"e0":0.04,"e1":0.04,"tw":7.8,"er":129.17,"bu":0,"bd":19.4},{"i":"regieleki","n":"Regieleki","f":"LOCK_ON","c":"THUNDER_CAGE","cp":2803,"lv":40,"d":60.91,"d0":60.91,"d1":60.91,"dp":100,"m":0,"m0":0,"m1":0,"td":600,"td0":600,"td1":600,"e":0.05,"e0":0.05,"e1":0.05,"tw":9.9,"er":107.91,"bu":0.6,"bd":24.1},{"i":"magnezone_shadow","n":"Magnezone (Shadow)","f":"SPARK","c":"ZAP_CANNON","cp":3205,"lv":40,"d":64.74,"d0":64.17,"d1":68.18,"dp":100,"m":0,"m0":0,"m1":0,"td":600,"td0":600,"td1":600,"e":0.05,"e0":0.05,"e1":0.05,"tw":9.3,"er":112.96,"bu":0,"bd":20.4},{"i":"exeggutor_alolan_shadow","n":"Exeggutor (Alolan) (Shadow)","f":"BULLET_SEED","c":"SOLAR_BEAM","cp":3014,"lv":40,"d":71.43,"d0":71.43,"d1":71.43,"dp":100,"m":0,"m0":0,"m1":0,"td":600,"td0":600,"td1":600,"e":0.05,"e0":0.05,"e1":0.05,"tw":8.4,"er":121.6,"bu":0,"bd":8.2},{"i":"exeggutor_shadow","n":"Exeggutor (Shadow)","f":"BULLET_SEED","c":"SOLAR_BEAM","cp":3014,"lv":40,"d":71.43,"d0":71.43,"d1":71.43,"dp":100,"m":0,"m0":0,"m1":0,"td":600,"td0":600,"td1":600,"e":0.05,"e0":0.05,"e1":0.05,"tw":8.4,"er":121.6,"bu":0,"bd":13.7},{"i":"exeggutor_shadow","n":"Exeggutor (Shadow)","f":"EXTRASENSORY","c":"SOLAR_BEAM","cp":3014,"lv":40,"d":63.49,"d0":63.49,"d1":63.49,"dp":100,"m":0,"m0":0,"m1":0,"td":600,"td0":600,"td1":600,"e":0.05,"e0":0.05,"e1":0.05,"tw":9.4,"er":111.32,"bu":0,"bd":13.7},{"i":"tapu_bulu","n":"Tapu Bulu","f":"BULLET_SEED","c":"SOLAR_BEAM","cp":3419,"lv":40,"d":71.43,"d0":71.43,"d1":71.43,"dp":100,"m":0,"m0":0,"m1":0,"td":600,"td0":600,"td1":600,"e":0.05,"e0":0.05,"e1":0.05,"tw":8.4,"er":121.6,"bu":0,"bd":10.2},{"i":"groudon_primal","n":"Groudon (Primal)","f":"MUD_SHOT","c":"SOLAR_BEAM","cp":5902,"lv":40,"d":64.73,"d0":64.17,"d1":68.18,"dp":100,"m":0,"m0":0,"m1":0,"td":600,"td0":600,"td1":600,"e":0.05,"e0":0.05,"e1":0.05,"tw":9.3,"er":112.95,"bu":0,"bd":26.6},{"i":"groudon_shadow","n":"Groudon (Shadow)","f":"MUD_SHOT","c":"SOLAR_BEAM","cp":4115,"lv":40,"d":68.18,"d0":68.18,"d1":68.18,"dp":100,"m":0,"m0":0,"m1":0,"td":600,"td0":600,"td1":600,"e":0.05,"e0":0.05,"e1":0.05,"tw":8.8,"er":117.43,"bu":0,"bd":24.9},{"i":"sceptile_mega","n":"Sceptile (Mega)","f":"FURY_CUTTER","c":"FRENZY_PLANT","cp":4056,"lv":40,"d":62.86,"d0":62.5,"d1":66.3,"dp":100,"m":0,"m0":0,"m1":0,"td":600,"td0":600,"td1":600,"e":0.05,"e0":0.05,"e1":0.05,"tw":9.5,"er":110.49,"bu":0.6,"bd":7.5},{"i":"sceptile_shadow","n":"Sceptile (Shadow)","f":"FURY_CUTTER","c":"FRENZY_PLANT","cp":2757,"lv":40,"d":62.91,"d0":62.5,"d1":66.3,"dp":100,"m":0,"m0":0,"m1":0,"td":600,"td0":600,"td1":600,"e":0.05,"e0":0.05,"e1":0.05,"tw":9.5,"er":110.56,"bu":0.2,"bd":15},{"i":"electivire_shadow","n":"Electivire (Shadow)","f":"THUNDER_SHOCK","c":"WILD_CHARGE","cp":3079,"lv":40,"d":62.91,"d0":56.07,"d1":66.3,"dp":100,"m":0,"m0":0,"m1":0,"td":600,"td0":600,"td1":600,"e":0.05,"e0":0.05,"e1":0.06,"tw":9.6,"er":110.55,"bu":0.8,"bd":24},{"i":"victreebel","n":"Victreebel","f":"MAGICAL_LEAF","c":"SOLAR_BEAM","cp":2431,"lv":40,"d":64.52,"d0":64.52,"d1":64.52,"dp":100,"m":0,"m0":0,"m1":0,"td":600,"td0":600,"td1":600,"e":0.05,"e0":0.05,"e1":0.05,"tw":9.3,"er":112.67,"bu":0,"bd":14.2},{"i":"victreebel_mega","n":"Victreebel (Mega)","f":"MAGICAL_LEAF","c":"SOLAR_BEAM","cp":3505,"lv":40,"d":64.52,"d0":64.52,"d1":64.52,"dp":100,"m":0,"m0":0,"m1":0,"td":600,"td0":600,"td1":600,"e":0.05,"e0":0.05,"e1":0.05,"tw":9.3,"er":112.67,"bu":0,"bd":11.1},{"i":"victreebel_shadow","n":"Victreebel (Shadow)","f":"MAGICAL_LEAF","c":"SOLAR_BEAM","cp":2431,"lv":40,"d":64.52,"d0":64.52,"d1":64.52,"dp":100,"m":0,"m0":0,"m1":0,"td":600,"td0":600,"td1":600,"e":0.05,"e0":0.05,"e1":0.05,"tw":9.3,"er":112.67,"bu":0,"bd":16.7},{"i":"meganium_shadow","n":"Meganium (Shadow)","f":"MAGICAL_LEAF","c":"SOLAR_BEAM","cp":2410,"lv":40,"d":64.52,"d0":64.52,"d1":64.52,"dp":100,"m":0,"m0":0,"m1":0,"td":600,"td0":600,"td1":600,"e":0.05,"e0":0.05,"e1":0.05,"tw":9.3,"er":112.67,"bu":0,"bd":11.7},{"i":"roserade","n":"Roserade","f":"MAGICAL_LEAF","c":"SOLAR_BEAM","cp":2971,"lv":40,"d":64.52,"d0":64.52,"d1":64.52,"dp":100,"m":0,"m0":0,"m1":0,"td":600,"td0":600,"td1":600,"e":0.05,"e0":0.05,"e1":0.05,"tw":9.3,"er":112.67,"bu":0,"bd":12.7},{"i":"shaymin_land","n":"Shaymin (Land)","f":"MAGICAL_LEAF","c":"SOLAR_BEAM","cp":3265,"lv":40,"d":64.52,"d0":64.52,"d1":64.52,"dp":100,"m":0,"m0":0,"m1":0,"td":600,"td0":600,"td1":600,"e":0.05,"e0":0.05,"e1":0.05,"tw":9.3,"er":112.67,"bu":0,"bd":7.9},{"i":"shaymin_sky","n":"Shaymin (Sky)","f":"MAGICAL_LEAF","c":"SOLAR_BEAM","cp":3592,"lv":40,"d":64.52,"d0":64.52,"d1":64.52,"dp":100,"m":0,"m0":0,"m1":0,"td":600,"td0":600,"td1":600,"e":0.05,"e0":0.05,"e1":0.05,"tw":9.3,"er":112.67,"bu":0,"bd":10.1},{"i":"lilligant","n":"Lilligant","f":"MAGICAL_LEAF","c":"SOLAR_BEAM","cp":2550,"lv":40,"d":64.52,"d0":64.52,"d1":64.52,"dp":100,"m":0,"m0":0,"m1":0,"td":600,"td0":600,"td1":600,"e":0.05,"e0":0.05,"e1":0.05,"tw":9.3,"er":112.67,"bu":0,"bd":13.6},{"i":"lilligant_hisuian","n":"Lilligant (Hisuian)","f":"MAGICAL_LEAF","c":"SOLAR_BEAM","cp":2512,"lv":40,"d":64.52,"d0":64.52,"d1":64.52,"dp":100,"m":0,"m0":0,"m1":0,"td":600,"td0":600,"td1":600,"e":0.05,"e0":0.05,"e1":0.05,"tw":9.3,"er":112.67,"bu":0,"bd":13.6},{"i":"zapdos_shadow","n":"Zapdos (Shadow)","f":"THUNDER_SHOCK","c":"THUNDERBOLT","cp":3527,"lv":40,"d":60.41,"d0":56.07,"d1":66.3,"dp":100,"m":0,"m0":0,"m1":0,"td":600,"td0":600,"td1":600,"e":0.06,"e0":0.05,"e1":0.06,"tw":10,"er":107.25,"bu":0.7,"bd":18.9},{"i":"zapdos_shadow","n":"Zapdos (Shadow)","f":"CHARGE_BEAM","c":"THUNDERBOLT","cp":3527,"lv":40,"d":60.17,"d0":57.97,"d1":64.52,"dp":100,"m":0,"m0":0,"m1":0,"td":600,"td0":600,"td1":600,"e":0.06,"e0":0.05,"e1":0.06,"tw":10,"er":106.93,"bu":0.5,"bd":18.9},{"i":"magnezone_shadow","n":"Magnezone (Shadow)","f":"CHARGE_BEAM","c":"WILD_CHARGE","cp":3205,"lv":40,"d":60.36,"d0":57.97,"d1":64.52,"dp":100,"m":0,"m0":0,"m1":0,"td":600,"td0":600,"td1":600,"e":0.06,"e0":0.05,"e1":0.06,"tw":10,"er":107.18,"bu":0.6,"bd":20.4},{"i":"thundurus_therian","n":"Thundurus (Therian)","f":"VOLT_SWITCH","c":"THUNDERBOLT","cp":3659,"lv":40,"d":57.88,"d0":55.81,"d1":65.22,"dp":100,"m":0,"m0":0,"m1":0,"td":600,"td0":600,"td1":600,"e":0.06,"e0":0.05,"e1":0.06,"tw":10.4,"er":103.86,"bu":0.5,"bd":19.4},{"i":"sceptile_mega","n":"Sceptile (Mega)","f":"BULLET_SEED","c":"FRENZY_PLANT","cp":4056,"lv":40,"d":57.17,"d0":52.63,"d1":57.97,"dp":100,"m":0,"m0":0,"m1":0,"td":600,"td0":600,"td1":600,"e":0.06,"e0":0.06,"e1":0.06,"tw":10.5,"er":102.91,"bu":0.9,"bd":7.5},{"i":"sceptile_shadow","n":"Sceptile (Shadow)","f":"BULLET_SEED","c":"FRENZY_PLANT","cp":2757,"lv":40,"d":55.1,"d0":52.63,"d1":57.97,"dp":100,"m":0,"m0":0,"m1":0,"td":600,"td0":600,"td1":600,"e":0.06,"e0":0.06,"e1":0.06,"tw":10.9,"er":100.09,"bu":0.6,"bd":15},{"i":"victreebel_mega","n":"Victreebel (Mega)","f":"ACID","c":"SOLAR_BEAM","cp":3505,"lv":40,"d":57.14,"d0":57.14,"d1":57.14,"dp":100,"m":0,"m0":0,"m1":0,"td":600,"td0":600,"td1":600,"e":0.06,"e0":0.06,"e1":0.06,"tw":10.5,"er":102.86,"bu":0,"bd":11.1},{"i":"victreebel_shadow","n":"Victreebel (Shadow)","f":"RAZOR_LEAF","c":"LEAF_BLADE","cp":2431,"lv":40,"d":53.46,"d0":48.19,"d1":57.97,"dp":100,"m":0,"m0":0,"m1":0,"td":600,"td0":600,"td1":600,"e":0.06,"e0":0.06,"e1":0.07,"tw":11.3,"er":97.85,"bu":0.7,"bd":16.7},{"i":"victreebel_shadow","n":"Victreebel (Shadow)","f":"ACID","c":"SOLAR_BEAM","cp":2431,"lv":40,"d":57.14,"d0":57.14,"d1":57.14,"dp":100,"m":0,"m0":0,"m1":0,"td":600,"td0":600,"td1":600,"e":0.06,"e0":0.06,"e1":0.06,"tw":10.5,"er":102.86,"bu":0,"bd":16.7},{"i":"meganium_shadow","n":"Meganium (Shadow)","f":"VINE_WHIP","c":"SOLAR_BEAM","cp":2410,"lv":40,"d":57.97,"d0":57.42,"d1":60.61,"dp":100,"m":0,"m0":0,"m1":0,"td":600,"td0":600,"td1":600,"e":0.06,"e0":0.06,"e1":0.06,"tw":10.4,"er":103.97,"bu":0.3,"bd":11.7},{"i":"raikou_shadow","n":"Raikou (Shadow)","f":"THUNDER_SHOCK","c":"WILD_CHARGE","cp":3452,"lv":40,"d":60.33,"d0":56.07,"d1":62.5,"dp":100,"m":0,"m0":0,"m1":0,"td":600,"td0":600,"td1":600,"e":0.06,"e0":0.05,"e1":0.06,"tw":10,"er":107.14,"bu":0.7,"bd":17.7},{"i":"raikou_shadow","n":"Raikou (Shadow)","f":"VOLT_SWITCH","c":"THUNDERBOLT","cp":3452,"lv":40,"d":57.83,"d0":55.81,"d1":65.22,"dp":100,"m":0,"m0":0,"m1":0,"td":600,"td0":600,"td1":600,"e":0.06,"e0":0.05,"e1":0.06,"tw":10.4,"er":103.79,"bu":0.6,"bd":17.7},{"i":"raikou_shadow","n":"Raikou (Shadow)","f":"VOLT_SWITCH","c":"WILD_CHARGE","cp":3452,"lv":40,"d":57.87,"d0":55.81,"d1":65.22,"dp":100,"m":0,"m0":0,"m1":0,"td":600,"td0":600,"td1":600,"e":0.06,"e0":0.05,"e1":0.06,"tw":10.4,"er":103.84,"bu":0.5,"bd":17.7},{"i":"raikou_shadow","n":"Raikou (Shadow)","f":"THUNDER_SHOCK","c":"THUNDERBOLT","cp":3452,"lv":40,"d":59.74,"d0":56.07,"d1":62.5,"dp":100,"m":0,"m0":0,"m1":0,"td":600,"td0":600,"td1":600,"e":0.06,"e0":0.05,"e1":0.06,"tw":10.1,"er":106.35,"bu":0.6,"bd":17.7},{"i":"xurkitree","n":"Xurkitree","f":"THUNDER_SHOCK","c":"POWER_WHIP","cp":3937,"lv":40,"d":60.72,"d0":56.07,"d1":66.3,"dp":100,"m":0,"m0":0,"m1":0,"td":600,"td0":600,"td1":600,"e":0.06,"e0":0.05,"e1":0.06,"tw":9.9,"er":107.65,"bu":0.7,"bd":20.6},{"i":"xurkitree","n":"Xurkitree","f":"SPARK","c":"POWER_WHIP","cp":3937,"lv":40,"d":55.57,"d0":50.85,"d1":59.11,"dp":100,"m":0,"m0":0,"m1":0,"td":600,"td0":600,"td1":600,"e":0.06,"e0":0.06,"e1":0.07,"tw":10.8,"er":100.73,"bu":0.8,"bd":20.6},{"i":"mewtwo_shadow","n":"Mewtwo (Shadow)","f":"PSYCHO_CUT","c":"THUNDERBOLT","cp":4178,"lv":40,"d":58.84,"d0":56.07,"d1":66.3,"dp":100,"m":0,"m0":0,"m1":0,"td":600,"td0":600,"td1":600,"e":0.06,"e0":0.05,"e1":0.06,"tw":10.2,"er":105.14,"bu":0.5,"bd":18.3},{"i":"golem_alolan_shadow","n":"Golem (Alolan) (Shadow)","f":"VOLT_SWITCH","c":"WILD_CHARGE","cp":2949,"lv":40,"d":57.8,"d0":55.81,"d1":65.22,"dp":100,"m":0,"m0":0,"m1":0,"td":600,"td0":600,"td1":600,"e":0.06,"e0":0.05,"e1":0.06,"tw":10.4,"er":103.75,"bu":0.5,"bd":30.2},{"i":"zeraora","n":"Zeraora","f":"VOLT_SWITCH","c":"WILD_CHARGE","cp":3419,"lv":40,"d":57.32,"d0":55.81,"d1":65.22,"dp":100,"m":0,"m0":0,"m1":0,"td":600,"td0":600,"td1":600,"e":0.06,"e0":0.05,"e1":0.06,"tw":10.5,"er":103.1,"bu":0.6,"bd":16.2},{"i":"zeraora","n":"Zeraora","f":"SPARK","c":"WILD_CHARGE","cp":3419,"lv":40,"d":55.06,"d0":50.85,"d1":56.07,"dp":100,"m":0,"m0":0,"m1":0,"td":600,"td0":600,"td1":600,"e":0.06,"e0":0.06,"e1":0.07,"tw":10.9,"er":100.04,"bu":0.8,"bd":16.2},{"i":"manectric_mega","n":"Manectric (Mega)","f":"CHARGE_BEAM","c":"WILD_CHARGE","cp":3580,"lv":40,"d":60.41,"d0":57.97,"d1":64.52,"dp":100,"m":0,"m0":0,"m1":0,"td":600,"td0":600,"td1":600,"e":0.06,"e0":0.05,"e1":0.06,"tw":10,"er":107.24,"bu":0.6,"bd":19},{"i":"manectric_mega","n":"Manectric (Mega)","f":"SNARL","c":"WILD_CHARGE","cp":3580,"lv":40,"d":55.23,"d0":52.63,"d1":57.97,"dp":100,"m":0,"m0":0,"m1":0,"td":600,"td0":600,"td1":600,"e":0.06,"e0":0.06,"e1":0.06,"tw":10.9,"er":100.27,"bu":0.6,"bd":19},{"i":"manectric_mega","n":"Manectric (Mega)","f":"THUNDER_FANG","c":"WILD_CHARGE","cp":3580,"lv":40,"d":55.7,"d0":52.63,"d1":57.97,"dp":100,"m":0,"m0":0,"m1":0,"td":600,"td0":600,"td1":600,"e":0.06,"e0":0.06,"e1":0.06,"tw":10.8,"er":100.91,"bu":0.6,"bd":19},{"i":"manectric_shadow","n":"Manectric (Shadow)","f":"THUNDER_FANG","c":"WILD_CHARGE","cp":2340,"lv":40,"d":58.24,"d0":52.63,"d1":64.52,"dp":100,"m":0,"m0":0,"m1":0,"td":600,"td0":600,"td1":600,"e":0.06,"e0":0.05,"e1":0.06,"tw":10.4,"er":104.35,"bu":0.7,"bd":31.3}],"pound_aerial_ace":[{"i":"porygon_z_shadow","n":"Porygon-Z (Shadow)","f":"CHARGE_BEAM","c":"SOLAR_BEAM","cp":3266,"lv":40,"d":81.63,"d0":81.63,"d1":81.63,"dp":100,"m":0,"m0":0,"m1":0,"td":600,"td0":600,"td1":600,"e":0.04,"e0":0.04,"e1":0.04,"tw":7.3,"er":134.41,"bu":0,"bd":16.7},{"i":"zapdos_shadow","n":"Zapdos (Shadow)","f":"THUNDER_SHOCK","c":"ZAP_CANNON","cp":3527,"lv":40,"d":79.86,"d0":77.92,"d1":83.92,"dp":100,"m":0,"m0":0,"m1":0,"td":600,"td0":600,"td1":600,"e":0.04,"e0":0.04,"e1":0.04,"tw":7.5,"er":132.22,"bu":0.5,"bd":8.6},{"i":"regieleki","n":"Regieleki","f":"THUNDER_SHOCK","c":"THUNDER_CAGE","cp":2803,"lv":40,"d":79.71,"d0":77.92,"d1":83.92,"dp":100,"m":0,"m0":0,"m1":0,"td":600,"td0":600,"td1":600,"e":0.04,"e0":0.04,"e1":0.04,"tw":7.5,"er":132.03,"bu":0.4,"bd":10.5},{"i":"regieleki","n":"Regieleki","f":"VOLT_SWITCH","c":"THUNDER_CAGE","cp":2803,"lv":40,"d":77.42,"d0":77.42,"d1":77.42,"dp":100,"m":0,"m0":0,"m1":0,"td":600,"td0":600,"td1":600,"e":0.04,"e0":0.04,"e1":0.04,"tw":7.8,"er":129.17,"bu":0,"bd":10.5},{"i":"ampharos_mega","n":"Ampharos (Mega)","f":"VOLT_SWITCH","c":"ZAP_CANNON","cp":4245,"lv":40,"d":77.42,"d0":77.42,"d1":77.42,"dp":100,"m":0,"m0":0,"m1":0,"td":600,"td0":600,"td1":600,"e":0.04,"e0":0.04,"e1":0.04,"tw":7.8,"er":129.17,"bu":0,"bd":6.3},{"i":"magnezone_shadow","n":"Magnezone (Shadow)","f":"VOLT_SWITCH","c":"ZAP_CANNON","cp":3205,"lv":40,"d":77.42,"d0":77.42,"d1":77.42,"dp":100,"m":0,"m0":0,"m1":0,"td":600,"td0":600,"td1":600,"e":0.04,"e0":0.04,"e1":0.04,"tw":7.8,"er":129.17,"bu":0,"bd":6.1},{"i":"thundurus_therian","n":"Thundurus (Therian)","f":"VOLT_SWITCH","c":"WILDBOLT_STORM","cp":3659,"lv":40,"d":77.42,"d0":77.42,"d1":77.42,"dp":100,"m":0,"m0":0,"m1":0,"td":600,"td0":600,"td1":600,"e":0.04,"e0":0.04,"e1":0.04,"tw":7.8,"er":129.17,"bu":0,"bd":8.8},{"i":"regieleki","n":"Regieleki","f":"LOCK_ON","c":"THUNDER_CAGE","cp":2803,"lv":40,"d":60.91,"d0":60.91,"d1":60.91,"dp":100,"m":0,"m0":0,"m1":0,"td":600,"td0":600,"td1":600,"e":0.05,"e0":0.05,"e1":0.05,"tw":9.9,"er":107.91,"bu":0.7,"bd":10.5},{"i":"magnezone_shadow","n":"Magnezone (Shadow)","f":"SPARK","c":"ZAP_CANNON","cp":3205,"lv":40,"d":66.43,"d0":64.17,"d1":68.18,"dp":100,"m":0,"m0":0,"m1":0,"td":600,"td0":600,"td1":600,"e":0.05,"e0":0.05,"e1":0.05,"tw":9,"er":115.16,"bu":0.6,"bd":6.1},{"i":"exeggutor_alolan_shadow","n":"Exeggutor (Alolan) (Shadow)","f":"BULLET_SEED","c":"SOLAR_BEAM","cp":3014,"lv":40,"d":71.43,"d0":71.43,"d1":71.43,"dp":100,"m":0,"m0":0,"m1":0,"td":600,"td0":600,"td1":600,"e":0.05,"e0":0.05,"e1":0.05,"tw":8.4,"er":121.6,"bu":0,"bd":24.2},{"i":"exeggutor_shadow","n":"Exeggutor (Shadow)","f":"BULLET_SEED","c":"SOLAR_BEAM","cp":3014,"lv":40,"d":71.43,"d0":71.43,"d1":71.43,"dp":100,"m":0,"m0":0,"m1":0,"td":600,"td0":600,"td1":600,"e":0.05,"e0":0.05,"e1":0.05,"tw":8.4,"er":121.6,"bu":0.1,"bd":24.7},{"i":"exeggutor_shadow","n":"Exeggutor (Shadow)","f":"EXTRASENSORY","c":"SOLAR_BEAM","cp":3014,"lv":40,"d":63.49,"d0":63.49,"d1":63.49,"dp":100,"m":0,"m0":0,"m1":0,"td":600,"td0":600,"td1":600,"e":0.05,"e0":0.05,"e1":0.05,"tw":9.4,"er":111.32,"bu":0.2,"bd":24.7},{"i":"tapu_bulu","n":"Tapu Bulu","f":"BULLET_SEED","c":"SOLAR_BEAM","cp":3419,"lv":40,"d":71.43,"d0":71.43,"d1":71.43,"dp":100,"m":0,"m0":0,"m1":0,"td":600,"td0":600,"td1":600,"e":0.05,"e0":0.05,"e1":0.05,"tw":8.4,"er":121.6,"bu":0,"bd":18.4},{"i":"sceptile_shadow","n":"Sceptile (Shadow)","f":"FURY_CUTTER","c":"FRENZY_PLANT","cp":2757,"lv":40,"d":68.52,"d0":62.5,"d1":70.59,"dp":100,"m":0,"m0":0,"m1":0,"td":600,"td0":600,"td1":600,"e":0.05,"e0":0.05,"e1":0.05,"tw":8.8,"er":117.87,"bu":0.8,"bd":27.2},{"i":"sceptile_shadow","n":"Sceptile (Shadow)","f":"BULLET_SEED","c":"FRENZY_PLANT","cp":2757,"lv":40,"d":62.55,"d0":52.63,"d1":64.52,"dp":100,"m":0,"m0":0,"m1":0,"td":600,"td0":600,"td1":600,"e":0.05,"e0":0.05,"e1":0.06,"tw":9.6,"er":110.08,"bu":0.9,"bd":27.2},{"i":"venusaur_shadow","n":"Venusaur (Shadow)","f":"VINE_WHIP","c":"SOLAR_BEAM","cp":2720,"lv":40,"d":63.7,"d0":57.42,"d1":68.18,"dp":100,"m":0,"m0":0,"m1":0,"td":600,"td0":600,"td1":600,"e":0.05,"e0":0.05,"e1":0.06,"tw":9.5,"er":111.59,"bu":0.7,"bd":22.2},{"i":"tangela_shadow","n":"Tangela (Shadow)","f":"VINE_WHIP","c":"SOLAR_BEAM","cp":2238,"lv":40,"d":63.93,"d0":57.42,"d1":72.73,"dp":100,"m":0,"m0":0,"m1":0,"td":600,"td0":600,"td1":600,"e":0.05,"e0":0.05,"e1":0.06,"tw":9.4,"er":111.9,"bu":0.8,"bd":28.6},{"i":"groudon_primal","n":"Groudon (Primal)","f":"MUD_SHOT","c":"SOLAR_BEAM","cp":5902,"lv":40,"d":64.8,"d0":64.17,"d1":68.18,"dp":100,"m":0,"m0":0,"m1":0,"td":600,"td0":600,"td1":600,"e":0.05,"e0":0.05,"e1":0.05,"tw":9.3,"er":113.03,"bu":0,"bd":7.6},{"i":"groudon_shadow","n":"Groudon (Shadow)","f":"MUD_SHOT","c":"SOLAR_BEAM","cp":4115,"lv":40,"d":68.18,"d0":68.18,"d1":68.18,"dp":100,"m":0,"m0":0,"m1":0,"td":600,"td0":600,"td1":600,"e":0.05,"e0":0.05,"e1":0.05,"tw":8.8,"er":117.43,"bu":0,"bd":11},{"i":"tangrowth_shadow","n":"Tangrowth (Shadow)","f":"VINE_WHIP","c":"SOLAR_BEAM","cp":3030,"lv":40,"d":64.09,"d0":57.42,"d1":72.73,"dp":100,"m":0,"m0":0,"m1":0,"td":600,"td0":600,"td1":600,"e":0.05,"e0":0.05,"e1":0.06,"tw":9.4,"er":112.1,"bu":0.7,"bd":19.6},{"i":"chesnaught_shadow","n":"Chesnaught (Shadow)","f":"VINE_WHIP","c":"SOLAR_BEAM","cp":2954,"lv":40,"d":68.78,"d0":57.42,"d1":77.92,"dp":100,"m":0,"m0":0,"m1":0,"td":600,"td0":600,"td1":600,"e":0.05,"e0":0.04,"e1":0.06,"tw":8.9,"er":118.21,"bu":0.7,"bd":30.6},{"i":"sceptile_mega","n":"Sceptile (Mega)","f":"FURY_CUTTER","c":"FRENZY_PLANT","cp":4056,"lv":40,"d":65.61,"d0":62.5,"d1":70.59,"dp":100,"m":0,"m0":0,"m1":0,"td":600,"td0":600,"td1":600,"e":0.05,"e0":0.05,"e1":0.05,"tw":9.2,"er":114.09,"bu":0.8,"bd":20.4},{"i":"victreebel","n":"Victreebel","f":"MAGICAL_LEAF","c":"SOLAR_BEAM","cp":2431,"lv":40,"d":64.52,"d0":64.52,"d1":64.52,"dp":100,"m":0,"m0":0,"m1":0,"td":600,"td0":600,"td1":600,"e":0.05,"e0":0.05,"e1":0.05,"tw":9.3,"er":112.67,"bu":0.2,"bd":25.3},{"i":"victreebel_mega","n":"Victreebel (Mega)","f":"MAGICAL_LEAF","c":"SOLAR_BEAM","cp":3505,"lv":40,"d":70.48,"d0":64.52,"d1":77.42,"dp":100,"m":0,"m0":0,"m1":0,"td":600,"td0":600,"td1":600,"e":0.05,"e0":0.04,"e1":0.05,"tw":8.6,"er":120.38,"bu":0.6,"bd":19.1},{"i":"victreebel_shadow","n":"Victreebel (Shadow)","f":"MAGICAL_LEAF","c":"SOLAR_BEAM","cp":2431,"lv":40,"d":70.55,"d0":64.52,"d1":77.42,"dp":100,"m":0,"m0":0,"m1":0,"td":600,"td0":600,"td1":600,"e":0.05,"e0":0.04,"e1":0.05,"tw":8.6,"er":120.47,"bu":0.6,"bd":30.2},{"i":"meganium_shadow","n":"Meganium (Shadow)","f":"MAGICAL_LEAF","c":"SOLAR_BEAM","cp":2410,"lv":40,"d":64.52,"d0":64.52,"d1":64.52,"dp":100,"m":0,"m0":0,"m1":0,"td":600,"td0":600,"td1":600,"e":0.05,"e0":0.05,"e1":0.05,"tw":9.3,"er":112.67,"bu":0.2,"bd":21},{"i":"roserade","n":"Roserade","f":"MAGICAL_LEAF","c":"SOLAR_BEAM","cp":2971,"lv":40,"d":70.76,"d0":64.52,"d1":77.42,"dp":100,"m":0,"m0":0,"m1":0,"td":600,"td0":600,"td1":600,"e":0.05,"e0":0.04,"e1":0.05,"tw":8.6,"er":120.74,"bu":0.6,"bd":23.1},{"i":"shaymin_land","n":"Shaymin (Land)","f":"MAGICAL_LEAF","c":"SOLAR_BEAM","cp":3265,"lv":40,"d":64.52,"d0":64.52,"d1":64.52,"dp":100,"m":0,"m0":0,"m1":0,"td":600,"td0":600,"td1":600,"e":0.05,"e0":0.05,"e1":0.05,"tw":9.3,"er":112.67,"bu":0.2,"bd":14.3},{"i":"shaymin_sky","n":"Shaymin (Sky)","f":"MAGICAL_LEAF","c":"SOLAR_BEAM","cp":3592,"lv":40,"d":70.94,"d0":64.52,"d1":77.42,"dp":100,"m":0,"m0":0,"m1":0,"td":600,"td0":600,"td1":600,"e":0.05,"e0":0.04,"e1":0.05,"tw":8.5,"er":120.98,"bu":0.6,"bd":18},{"i":"lilligant","n":"Lilligant","f":"MAGICAL_LEAF","c":"SOLAR_BEAM","cp":2550,"lv":40,"d":64.52,"d0":64.52,"d1":64.52,"dp":100,"m":0,"m0":0,"m1":0,"td":600,"td0":600,"td1":600,"e":0.05,"e0":0.05,"e1":0.05,"tw":9.3,"er":112.67,"bu":0.2,"bd":24.5},{"i":"lilligant_hisuian","n":"Lilligant (Hisuian)","f":"MAGICAL_LEAF","c":"SOLAR_BEAM","cp":2512,"lv":40,"d":64.52,"d0":64.52,"d1":64.52,"dp":100,"m":0,"m0":0,"m1":0,"td":600,"td0":600,"td1":600,"e":0.05,"e0":0.05,"e1":0.05,"tw":9.3,"er":112.67,"bu":0.2,"bd":38.1},{"i":"mewtwo_shadow","n":"Mewtwo (Shadow)","f":"PSYCHO_CUT","c":"THUNDERBOLT","cp":4178,"lv":40,"d":61.4,"d0":56.07,"d1":62.5,"dp":100,"m":0,"m0":0,"m1":0,"td":600,"td0":600,"td1":600,"e":0.05,"e0":0.05,"e1":0.06,"tw":9.8,"er":108.56,"bu":0.9,"bd":12.8},{"i":"porygon_z_shadow","n":"Porygon-Z (Shadow)","f":"HIDDEN_POWER_GRASS","c":"SOLAR_BEAM","cp":3266,"lv":40,"d":60.78,"d0":55.3,"d1":64.52,"dp":100,"m":0,"m0":0,"m1":0,"td":600,"td0":600,"td1":600,"e":0.06,"e0":0.05,"e1":0.06,"tw":9.9,"er":107.73,"bu":0.7,"bd":16.7},{"i":"porygon_z_shadow","n":"Porygon-Z (Shadow)","f":"HIDDEN_POWER_ELECTRIC","c":"ZAP_CANNON","cp":3266,"lv":40,"d":60.93,"d0":55.3,"d1":64.52,"dp":100,"m":0,"m0":0,"m1":0,"td":600,"td0":600,"td1":600,"e":0.06,"e0":0.05,"e1":0.06,"tw":9.9,"er":107.93,"bu":0.8,"bd":16.7},{"i":"porygon_z_shadow","n":"Porygon-Z (Shadow)","f":"HIDDEN_POWER_BUG","c":"SOLAR_BEAM","cp":3266,"lv":40,"d":57.04,"d0":55.3,"d1":64.52,"dp":100,"m":0,"m0":0,"m1":0,"td":600,"td0":600,"td1":600,"e":0.06,"e0":0.05,"e1":0.06,"tw":10.6,"er":102.73,"bu":0.5,"bd":16.7},{"i":"porygon_z_shadow","n":"Porygon-Z (Shadow)","f":"HIDDEN_POWER_DARK","c":"SOLAR_BEAM","cp":3266,"lv":40,"d":57.08,"d0":55.3,"d1":64.52,"dp":100,"m":0,"m0":0,"m1":0,"td":600,"td0":600,"td1":600,"e":0.06,"e0":0.05,"e1":0.06,"tw":10.6,"er":102.77,"bu":0.5,"bd":16.7},{"i":"porygon_z_shadow","n":"Porygon-Z (Shadow)","f":"HIDDEN_POWER_DRAGON","c":"SOLAR_BEAM","cp":3266,"lv":40,"d":57.29,"d0":55.3,"d1":64.52,"dp":100,"m":0,"m0":0,"m1":0,"td":600,"td0":600,"td1":600,"e":0.06,"e0":0.05,"e1":0.06,"tw":10.5,"er":103.07,"bu":0.6,"bd":16.7},{"i":"porygon_z_shadow","n":"Porygon-Z (Shadow)","f":"HIDDEN_POWER_ELECTRIC","c":"SOLAR_BEAM","cp":3266,"lv":40,"d":60.66,"d0":55.3,"d1":64.52,"dp":100,"m":0,"m0":0,"m1":0,"td":600,"td0":600,"td1":600,"e":0.06,"e0":0.05,"e1":0.06,"tw":9.9,"er":107.58,"bu":0.8,"bd":16.7},{"i":"porygon_z_shadow","n":"Porygon-Z (Shadow)","f":"HIDDEN_POWER_FIGHTING","c":"SOLAR_BEAM","cp":3266,"lv":40,"d":56.98,"d0":55.3,"d1":64.52,"dp":100,"m":0,"m0":0,"m1":0,"td":600,"td0":600,"td1":600,"e":0.06,"e0":0.05,"e1":0.06,"tw":10.6,"er":102.64,"bu":0.5,"bd":16.7},{"i":"porygon_z_shadow","n":"Porygon-Z (Shadow)","f":"HIDDEN_POWER_FLYING","c":"SOLAR_BEAM","cp":3266,"lv":40,"d":57.16,"d0":55.3,"d1":64.52,"dp":100,"m":0,"m0":0,"m1":0,"td":600,"td0":600,"td1":600,"e":0.06,"e0":0.05,"e1":0.06,"tw":10.5,"er":102.89,"bu":0.5,"bd":16.7},{"i":"porygon_z_shadow","n":"Porygon-Z (Shadow)","f":"HIDDEN_POWER_GHOST","c":"SOLAR_BEAM","cp":3266,"lv":40,"d":57.13,"d0":55.3,"d1":64.52,"dp":100,"m":0,"m0":0,"m1":0,"td":600,"td0":600,"td1":600,"e":0.06,"e0":0.05,"e1":0.06,"tw":10.5,"er":102.84,"bu":0.5,"bd":16.7},{"i":"porygon_z_shadow","n":"Porygon-Z (Shadow)","f":"HIDDEN_POWER_GRASS","c":"ZAP_CANNON","cp":3266,"lv":40,"d":60.28,"d0":55.3,"d1":64.52,"dp":100,"m":0,"m0":0,"m1":0,"td":600,"td0":600,"td1":600,"e":0.06,"e0":0.05,"e1":0.06,"tw":10,"er":107.07,"bu":0.7,"bd":16.7},{"i":"porygon_z_shadow","n":"Porygon-Z (Shadow)","f":"HIDDEN_POWER_GROUND","c":"SOLAR_BEAM","cp":3266,"lv":40,"d":56.93,"d0":55.3,"d1":64.52,"dp":100,"m":0,"m0":0,"m1":0,"td":600,"td0":600,"td1":600,"e":0.06,"e0":0.05,"e1":0.06,"tw":10.6,"er":102.57,"bu":0.5,"bd":16.7},{"i":"porygon_z_shadow","n":"Porygon-Z (Shadow)","f":"HIDDEN_POWER_POISON","c":"SOLAR_BEAM","cp":3266,"lv":40,"d":56.99,"d0":55.3,"d1":64.52,"dp":100,"m":0,"m0":0,"m1":0,"td":600,"td0":600,"td1":600,"e":0.06,"e0":0.05,"e1":0.06,"tw":10.6,"er":102.66,"bu":0.5,"bd":16.7},{"i":"porygon_z_shadow","n":"Porygon-Z (Shadow)","f":"HIDDEN_POWER_PSYCHIC","c":"SOLAR_BEAM","cp":3266,"lv":40,"d":56.94,"d0":55.3,"d1":64.52,"dp":100,"m":0,"m0":0,"m1":0,"td":600,"td0":600,"td1":600,"e":0.06,"e0":0.05,"e1":0.06,"tw":10.6,"er":102.59,"bu":0.5,"bd":16.7},{"i":"porygon_z_shadow","n":"Porygon-Z (Shadow)","f":"HIDDEN_POWER_ROCK","c":"SOLAR_BEAM","cp":3266,"lv":40,"d":57.03,"d0":55.3,"d1":64.52,"dp":100,"m":0,"m0":0,"m1":0,"td":600,"td0":600,"td1":600,"e":0.06,"e0":0.05,"e1":0.06,"tw":10.6,"er":102.7,"bu":0.6,"bd":16.7},{"i":"zapdos_shadow","n":"Zapdos (Shadow)","f":"THUNDER_SHOCK","c":"THUNDERBOLT","cp":3527,"lv":40,"d":58.73,"d0":56.07,"d1":59.11,"dp":100,"m":0,"m0":0,"m1":0,"td":600,"td0":600,"td1":600,"e":0.06,"e0":0.06,"e1":0.06,"tw":10.2,"er":105,"bu":0.9,"bd":8.6},{"i":"zapdos_shadow","n":"Zapdos (Shadow)","f":"CHARGE_BEAM","c":"THUNDERBOLT","cp":3527,"lv":40,"d":57.97,"d0":57.97,"d1":57.97,"dp":100,"m":0,"m0":0,"m1":0,"td":600,"td0":600,"td1":600,"e":0.06,"e0":0.06,"e1":0.06,"tw":10.4,"er":103.98,"bu":0.8,"bd":8.6},{"i":"magnezone_shadow","n":"Magnezone (Shadow)","f":"CHARGE_BEAM","c":"WILD_CHARGE","cp":3205,"lv":40,"d":57.97,"d0":57.97,"d1":57.97,"dp":100,"m":0,"m0":0,"m1":0,"td":600,"td0":600,"td1":600,"e":0.06,"e0":0.06,"e1":0.06,"tw":10.4,"er":103.98,"bu":0.8,"bd":6.1},{"i":"exeggutor_shadow","n":"Exeggutor (Shadow)","f":"CONFUSION","c":"SOLAR_BEAM","cp":3014,"lv":40,"d":57.51,"d0":55.3,"d1":64.52,"dp":100,"m":0,"m0":0,"m1":0,"td":600,"td0":600,"td1":600,"e":0.06,"e0":0.05,"e1":0.06,"tw":10.5,"er":103.36,"bu":0.5,"bd":24.7},{"i":"victreebel_mega","n":"Victreebel (Mega)","f":"ACID","c":"SOLAR_BEAM","cp":3505,"lv":40,"d":58.42,"d0":57.14,"d1":63.49,"dp":100,"m":0,"m0":0,"m1":0,"td":600,"td0":600,"td1":600,"e":0.06,"e0":0.05,"e1":0.06,"tw":10.3,"er":104.59,"bu":0.5,"bd":19.1},{"i":"victreebel_shadow","n":"Victreebel (Shadow)","f":"ACID","c":"SOLAR_BEAM","cp":2431,"lv":40,"d":58.48,"d0":57.14,"d1":63.49,"dp":100,"m":0,"m0":0,"m1":0,"td":600,"td0":600,"td1":600,"e":0.06,"e0":0.05,"e1":0.06,"tw":10.3,"er":104.67,"bu":0.5,"bd":30.2},{"i":"shaymin_sky","n":"Shaymin (Sky)","f":"HIDDEN_POWER_GRASS","c":"SOLAR_BEAM","cp":3592,"lv":40,"d":60.23,"d0":55.3,"d1":64.52,"dp":100,"m":0,"m0":0,"m1":0,"td":600,"td0":600,"td1":600,"e":0.06,"e0":0.05,"e1":0.06,"tw":10,"er":107,"bu":0.7,"bd":18},{"i":"regigigas_shadow","n":"Regigigas (Shadow)","f":"HIDDEN_POWER_ELECTRIC","c":"GIGA_IMPACT","cp":4346,"lv":40,"d":60.75,"d0":55.3,"d1":64.52,"dp":100,"m":0,"m0":0,"m1":0,"td":600,"td0":600,"td1":600,"e":0.06,"e0":0.05,"e1":0.06,"tw":9.9,"er":107.69,"bu":0.7,"bd":11.3},{"i":"regigigas_shadow","n":"Regigigas (Shadow)","f":"HIDDEN_POWER_GRASS","c":"CRUSH_GRIP","cp":4346,"lv":40,"d":60.66,"d0":55.3,"d1":64.52,"dp":100,"m":0,"m0":0,"m1":0,"td":600,"td0":600,"td1":600,"e":0.06,"e0":0.05,"e1":0.06,"tw":9.9,"er":107.58,"bu":0.7,"bd":11.3},{"i":"regigigas_shadow","n":"Regigigas (Shadow)","f":"HIDDEN_POWER_ELECTRIC","c":"CRUSH_GRIP","cp":4346,"lv":40,"d":60.75,"d0":55.3,"d1":64.52,"dp":100,"m":0,"m0":0,"m1":0,"td":600,"td0":600,"td1":600,"e":0.06,"e0":0.05,"e1":0.06,"tw":9.9,"er":107.69,"bu":0.7,"bd":11.3},{"i":"regigigas_shadow","n":"Regigigas (Shadow)","f":"HIDDEN_POWER_GRASS","c":"GIGA_IMPACT","cp":4346,"lv":40,"d":60.88,"d0":55.3,"d1":64.52,"dp":100,"m":0,"m0":0,"m1":0,"td":600,"td0":600,"td1":600,"e":0.06,"e0":0.05,"e1":0.06,"tw":9.9,"er":107.87,"bu":0.8,"bd":11.3},{"i":"regigigas_shadow","n":"Regigigas (Shadow)","f":"HIDDEN_POWER_BUG","c":"GIGA_IMPACT","cp":4346,"lv":40,"d":56.99,"d0":55.3,"d1":64.52,"dp":100,"m":0,"m0":0,"m1":0,"td":600,"td0":600,"td1":600,"e":0.06,"e0":0.05,"e1":0.06,"tw":10.6,"er":102.66,"bu":0.5,"bd":11.3},{"i":"regigigas_shadow","n":"Regigigas (Shadow)","f":"HIDDEN_POWER_DRAGON","c":"GIGA_IMPACT","cp":4346,"lv":40,"d":57.18,"d0":55.3,"d1":64.52,"dp":100,"m":0,"m0":0,"m1":0,"td":600,"td0":600,"td1":600,"e":0.06,"e0":0.05,"e1":0.06,"tw":10.5,"er":102.91,"bu":0.5,"bd":11.3},{"i":"regigigas_shadow","n":"Regigigas (Shadow)","f":"HIDDEN_POWER_BUG","c":"CRUSH_GRIP","cp":4346,"lv":40,"d":57.29,"d0":55.3,"d1":64.52,"dp":100,"m":0,"m0":0,"m1":0,"td":600,"td0":600,"td1":600,"e":0.06,"e0":0.05,"e1":0.06,"tw":10.5,"er":103.07,"bu":0.5,"bd":11.3},{"i":"exeggutor","n":"Exeggutor","f":"CONFUSION","c":"SOLAR_BEAM","cp":3014,"lv":40,"d":56.94,"d0":55.3,"d1":64.52,"dp":100,"m":0,"m0":0,"m1":0,"td":600,"td0":600,"td1":600,"e":0.06,"e0":0.05,"e1":0.06,"tw":10.6,"er":102.59,"bu":0.5,"bd":20.3},{"i":"ho_oh_shadow","n":"Ho-Oh (Shadow)","f":"HIDDEN_POWER_ELECTRIC","c":"SOLAR_BEAM","cp":3863,"lv":40,"d":57.11,"d0":55.3,"d1":64.52,"dp":100,"m":0,"m0":0,"m1":0,"td":600,"td0":600,"td1":600,"e":0.06,"e0":0.05,"e1":0.06,"tw":10.5,"er":102.82,"bu":0.6,"bd":10},{"i":"ho_oh_shadow","n":"Ho-Oh (Shadow)","f":"HIDDEN_POWER_FLYING","c":"SOLAR_BEAM","cp":3863,"lv":40,"d":56.91,"d0":55.3,"d1":64.52,"dp":100,"m":0,"m0":0,"m1":0,"td":600,"td0":600,"td1":600,"e":0.06,"e0":0.05,"e1":0.06,"tw":10.6,"er":102.55,"bu":0.5,"bd":10},{"i":"ho_oh_shadow","n":"Ho-Oh (Shadow)","f":"HIDDEN_POWER_GRASS","c":"SOLAR_BEAM","cp":3863,"lv":40,"d":57.03,"d0":55.3,"d1":64.52,"dp":100,"m":0,"m0":0,"m1":0,"td":600,"td0":600,"td1":600,"e":0.06,"e0":0.05,"e1":0.06,"tw":10.6,"er":102.7,"bu":0.5,"bd":10}],"pound_surf":[{"i":"porygon_z_shadow","n":"Porygon-Z (Shadow)","f":"CHARGE_BEAM","c":"SOLAR_BEAM","cp":3266,"lv":40,"d":81.63,"d0":81.63,"d1":81.63,"dp":100,"m":0,"m0":0,"m1":0,"td":600,"td0":600,"td1":600,"e":0.04,"e0":0.04,"e1":0.04,"tw":7.3,"er":134.41,"bu":0,"bd":21.4},{"i":"zapdos_shadow","n":"Zapdos (Shadow)","f":"THUNDER_SHOCK","c":"ZAP_CANNON","cp":3527,"lv":40,"d":77.92,"d0":77.92,"d1":77.92,"dp":100,"m":0,"m0":0,"m1":0,"td":600,"td0":600,"td1":600,"e":0.04,"e0":0.04,"e1":0.04,"tw":7.7,"er":129.8,"bu":0,"bd":17.1},{"i":"regieleki","n":"Regieleki","f":"THUNDER_SHOCK","c":"THUNDER_CAGE","cp":2803,"lv":40,"d":77.92,"d0":77.92,"d1":77.92,"dp":100,"m":0,"m0":0,"m1":0,"td":600,"td0":600,"td1":600,"e":0.04,"e0":0.04,"e1":0.04,"tw":7.7,"er":129.8,"bu":0,"bd":22.2},{"i":"regieleki","n":"Regieleki","f":"VOLT_SWITCH","c":"THUNDER_CAGE","cp":2803,"lv":40,"d":77.42,"d0":77.42,"d1":77.42,"dp":100,"m":0,"m0":0,"m1":0,"td":600,"td0":600,"td1":600,"e":0.04,"e0":0.04,"e1":0.04,"tw":7.8,"er":129.17,"bu":0,"bd":22.2},{"i":"ampharos_mega","n":"Ampharos (Mega)","f":"VOLT_SWITCH","c":"ZAP_CANNON","cp":4245,"lv":40,"d":77.42,"d0":77.42,"d1":77.42,"dp":100,"m":0,"m0":0,"m1":0,"td":600,"td0":600,"td1":600,"e":0.04,"e0":0.04,"e1":0.04,"tw":7.8,"er":129.17,"bu":0,"bd":8.6},{"i":"magnezone_shadow","n":"Magnezone (Shadow)","f":"VOLT_SWITCH","c":"ZAP_CANNON","cp":3205,"lv":40,"d":77.42,"d0":77.42,"d1":77.42,"dp":100,"m":0,"m0":0,"m1":0,"td":600,"td0":600,"td1":600,"e":0.04,"e0":0.04,"e1":0.04,"tw":7.8,"er":129.17,"bu":0,"bd":18.4},{"i":"thundurus_therian","n":"Thundurus (Therian)","f":"VOLT_SWITCH","c":"WILDBOLT_STORM","cp":3659,"lv":40,"d":77.42,"d0":77.42,"d1":77.42,"dp":100,"m":0,"m0":0,"m1":0,"td":600,"td0":600,"td1":600,"e":0.04,"e0":0.04,"e1":0.04,"tw":7.8,"er":129.17,"bu":0,"bd":18.1},{"i":"regieleki","n":"Regieleki","f":"LOCK_ON","c":"THUNDER_CAGE","cp":2803,"lv":40,"d":60.91,"d0":60.91,"d1":60.91,"dp":100,"m":0,"m0":0,"m1":0,"td":600,"td0":600,"td1":600,"e":0.05,"e0":0.05,"e1":0.05,"tw":9.9,"er":107.91,"bu":0.7,"bd":22.2},{"i":"magnezone_shadow","n":"Magnezone (Shadow)","f":"SPARK","c":"ZAP_CANNON","cp":3205,"lv":40,"d":64.76,"d0":64.17,"d1":68.18,"dp":100,"m":0,"m0":0,"m1":0,"td":600,"td0":600,"td1":600,"e":0.05,"e0":0.05,"e1":0.05,"tw":9.3,"er":112.99,"bu":0,"bd":18.4},{"i":"exeggutor_alolan_shadow","n":"Exeggutor (Alolan) (Shadow)","f":"BULLET_SEED","c":"SOLAR_BEAM","cp":3014,"lv":40,"d":71.43,"d0":71.43,"d1":71.43,"dp":100,"m":0,"m0":0,"m1":0,"td":600,"td0":600,"td1":600,"e":0.05,"e0":0.05,"e1":0.05,"tw":8.4,"er":121.6,"bu":0,"bd":7.7},{"i":"exeggutor_shadow","n":"Exeggutor (Shadow)","f":"BULLET_SEED","c":"SOLAR_BEAM","cp":3014,"lv":40,"d":71.43,"d0":71.43,"d1":71.43,"dp":100,"m":0,"m0":0,"m1":0,"td":600,"td0":600,"td1":600,"e":0.05,"e0":0.05,"e1":0.05,"tw":8.4,"er":121.6,"bu":0,"bd":12.6},{"i":"exeggutor_shadow","n":"Exeggutor (Shadow)","f":"EXTRASENSORY","c":"SOLAR_BEAM","cp":3014,"lv":40,"d":63.49,"d0":63.49,"d1":63.49,"dp":100,"m":0,"m0":0,"m1":0,"td":600,"td0":600,"td1":600,"e":0.05,"e0":0.05,"e1":0.05,"tw":9.4,"er":111.32,"bu":0,"bd":12.6},{"i":"tapu_bulu","n":"Tapu Bulu","f":"BULLET_SEED","c":"SOLAR_BEAM","cp":3419,"lv":40,"d":71.43,"d0":71.43,"d1":71.43,"dp":100,"m":0,"m0":0,"m1":0,"td":600,"td0":600,"td1":600,"e":0.05,"e0":0.05,"e1":0.05,"tw":8.4,"er":121.6,"bu":0,"bd":9.5},{"i":"groudon_primal","n":"Groudon (Primal)","f":"MUD_SHOT","c":"SOLAR_BEAM","cp":5902,"lv":40,"d":64.86,"d0":64.17,"d1":68.18,"dp":100,"m":0,"m0":0,"m1":0,"td":600,"td0":600,"td1":600,"e":0.05,"e0":0.05,"e1":0.05,"tw":9.3,"er":113.11,"bu":0,"bd":24.5},{"i":"groudon_shadow","n":"Groudon (Shadow)","f":"MUD_SHOT","c":"SOLAR_BEAM","cp":4115,"lv":40,"d":68.18,"d0":68.18,"d1":68.18,"dp":100,"m":0,"m0":0,"m1":0,"td":600,"td0":600,"td1":600,"e":0.05,"e0":0.05,"e1":0.05,"tw":8.8,"er":117.43,"bu":0,"bd":22.5},{"i":"sceptile_shadow","n":"Sceptile (Shadow)","f":"FURY_CUTTER","c":"FRENZY_PLANT","cp":2757,"lv":40,"d":63,"d0":62.5,"d1":66.3,"dp":100,"m":0,"m0":0,"m1":0,"td":600,"td0":600,"td1":600,"e":0.05,"e0":0.05,"e1":0.05,"tw":9.5,"er":110.68,"bu":0.3,"bd":14.3},{"i":"victreebel","n":"Victreebel","f":"MAGICAL_LEAF","c":"SOLAR_BEAM","cp":2431,"lv":40,"d":64.52,"d0":64.52,"d1":64.52,"dp":100,"m":0,"m0":0,"m1":0,"td":600,"td0":600,"td1":600,"e":0.05,"e0":0.05,"e1":0.05,"tw":9.3,"er":112.67,"bu":0,"bd":13},{"i":"victreebel_mega","n":"Victreebel (Mega)","f":"MAGICAL_LEAF","c":"SOLAR_BEAM","cp":3505,"lv":40,"d":64.52,"d0":64.52,"d1":64.52,"dp":100,"m":0,"m0":0,"m1":0,"td":600,"td0":600,"td1":600,"e":0.05,"e0":0.05,"e1":0.05,"tw":9.3,"er":112.67,"bu":0,"bd":9.9},{"i":"victreebel_shadow","n":"Victreebel (Shadow)","f":"MAGICAL_LEAF","c":"SOLAR_BEAM","cp":2431,"lv":40,"d":64.52,"d0":64.52,"d1":64.52,"dp":100,"m":0,"m0":0,"m1":0,"td":600,"td0":600,"td1":600,"e":0.05,"e0":0.05,"e1":0.05,"tw":9.3,"er":112.67,"bu":0,"bd":15.4},{"i":"meganium_shadow","n":"Meganium (Shadow)","f":"MAGICAL_LEAF","c":"SOLAR_BEAM","cp":2410,"lv":40,"d":64.52,"d0":64.52,"d1":64.52,"dp":100,"m":0,"m0":0,"m1":0,"td":600,"td0":600,"td1":600,"e":0.05,"e0":0.05,"e1":0.05,"tw":9.3,"er":112.67,"bu":0,"bd":11.1},{"i":"roserade","n":"Roserade","f":"MAGICAL_LEAF","c":"SOLAR_BEAM","cp":2971,"lv":40,"d":64.52,"d0":64.52,"d1":64.52,"dp":100,"m":0,"m0":0,"m1":0,"td":600,"td0":600,"td1":600,"e":0.05,"e0":0.05,"e1":0.05,"tw":9.3,"er":112.67,"bu":0,"bd":11.9},{"i":"shaymin_land","n":"Shaymin (Land)","f":"MAGICAL_LEAF","c":"SOLAR_BEAM","cp":3265,"lv":40,"d":64.52,"d0":64.52,"d1":64.52,"dp":100,"m":0,"m0":0,"m1":0,"td":600,"td0":600,"td1":600,"e":0.05,"e0":0.05,"e1":0.05,"tw":9.3,"er":112.67,"bu":0,"bd":7.4},{"i":"shaymin_sky","n":"Shaymin (Sky)","f":"MAGICAL_LEAF","c":"SOLAR_BEAM","cp":3592,"lv":40,"d":64.52,"d0":64.52,"d1":64.52,"dp":100,"m":0,"m0":0,"m1":0,"td":600,"td0":600,"td1":600,"e":0.05,"e0":0.05,"e1":0.05,"tw":9.3,"er":112.67,"bu":0,"bd":9.5},{"i":"lilligant","n":"Lilligant","f":"MAGICAL_LEAF","c":"SOLAR_BEAM","cp":2550,"lv":40,"d":64.52,"d0":64.52,"d1":64.52,"dp":100,"m":0,"m0":0,"m1":0,"td":600,"td0":600,"td1":600,"e":0.05,"e0":0.05,"e1":0.05,"tw":9.3,"er":112.67,"bu":0,"bd":12.9},{"i":"lilligant_hisuian","n":"Lilligant (Hisuian)","f":"MAGICAL_LEAF","c":"SOLAR_BEAM","cp":2512,"lv":40,"d":64.52,"d0":64.52,"d1":64.52,"dp":100,"m":0,"m0":0,"m1":0,"td":600,"td0":600,"td1":600,"e":0.05,"e0":0.05,"e1":0.05,"tw":9.3,"er":112.67,"bu":0,"bd":12.2},{"i":"sceptile_mega","n":"Sceptile (Mega)","f":"FURY_CUTTER","c":"FRENZY_PLANT","cp":4056,"lv":40,"d":62.5,"d0":62.5,"d1":62.5,"dp":100,"m":0,"m0":0,"m1":0,"td":600,"td0":600,"td1":600,"e":0.05,"e0":0.05,"e1":0.05,"tw":9.6,"er":110.01,"bu":0.6,"bd":6.8},{"i":"zapdos_shadow","n":"Zapdos (Shadow)","f":"CHARGE_BEAM","c":"THUNDERBOLT","cp":3527,"lv":40,"d":60.49,"d0":57.97,"d1":64.52,"dp":100,"m":0,"m0":0,"m1":0,"td":600,"td0":600,"td1":600,"e":0.06,"e0":0.05,"e1":0.06,"tw":9.9,"er":107.35,"bu":0.6,"bd":17.1},{"i":"zapdos_shadow","n":"Zapdos (Shadow)","f":"THUNDER_SHOCK","c":"THUNDERBOLT","cp":3527,"lv":40,"d":59.79,"d0":56.07,"d1":62.5,"dp":100,"m":0,"m0":0,"m1":0,"td":600,"td0":600,"td1":600,"e":0.06,"e0":0.05,"e1":0.06,"tw":10.1,"er":106.42,"bu":0.7,"bd":17.1},{"i":"magnezone_shadow","n":"Magnezone (Shadow)","f":"CHARGE_BEAM","c":"WILD_CHARGE","cp":3205,"lv":40,"d":60.58,"d0":57.97,"d1":64.52,"dp":100,"m":0,"m0":0,"m1":0,"td":600,"td0":600,"td1":600,"e":0.06,"e0":0.05,"e1":0.06,"tw":9.9,"er":107.47,"bu":0.6,"bd":18.4},{"i":"thundurus_therian","n":"Thundurus (Therian)","f":"VOLT_SWITCH","c":"THUNDERBOLT","cp":3659,"lv":40,"d":57.8,"d0":55.81,"d1":65.22,"dp":100,"m":0,"m0":0,"m1":0,"td":600,"td0":600,"td1":600,"e":0.06,"e0":0.05,"e1":0.06,"tw":10.4,"er":103.75,"bu":0.6,"bd":18.1},{"i":"sceptile_shadow","n":"Sceptile (Shadow)","f":"BULLET_SEED","c":"FRENZY_PLANT","cp":2757,"lv":40,"d":55.06,"d0":52.63,"d1":57.97,"dp":100,"m":0,"m0":0,"m1":0,"td":600,"td0":600,"td1":600,"e":0.06,"e0":0.06,"e1":0.06,"tw":10.9,"er":100.04,"bu":0.5,"bd":14.3},{"i":"victreebel_mega","n":"Victreebel (Mega)","f":"ACID","c":"SOLAR_BEAM","cp":3505,"lv":40,"d":57.14,"d0":57.14,"d1":57.14,"dp":100,"m":0,"m0":0,"m1":0,"td":600,"td0":600,"td1":600,"e":0.06,"e0":0.06,"e1":0.06,"tw":10.5,"er":102.86,"bu":0,"bd":9.9},{"i":"victreebel_shadow","n":"Victreebel (Shadow)","f":"RAZOR_LEAF","c":"LEAF_BLADE","cp":2431,"lv":40,"d":53.04,"d0":48.19,"d1":57.97,"dp":100,"m":0,"m0":0,"m1":0,"td":600,"td0":600,"td1":600,"e":0.06,"e0":0.06,"e1":0.07,"tw":11.4,"er":97.27,"bu":0.6,"bd":15.4},{"i":"victreebel_shadow","n":"Victreebel (Shadow)","f":"ACID","c":"SOLAR_BEAM","cp":2431,"lv":40,"d":57.14,"d0":57.14,"d1":57.14,"dp":100,"m":0,"m0":0,"m1":0,"td":600,"td0":600,"td1":600,"e":0.06,"e0":0.06,"e1":0.06,"tw":10.5,"er":102.86,"bu":0,"bd":15.4},{"i":"meganium_shadow","n":"Meganium (Shadow)","f":"VINE_WHIP","c":"SOLAR_BEAM","cp":2410,"lv":40,"d":57.92,"d0":57.42,"d1":60.61,"dp":100,"m":0,"m0":0,"m1":0,"td":600,"td0":600,"td1":600,"e":0.06,"e0":0.06,"e1":0.06,"tw":10.4,"er":103.9,"bu":0.3,"bd":11.1},{"i":"sceptile_mega","n":"Sceptile (Mega)","f":"BULLET_SEED","c":"FRENZY_PLANT","cp":4056,"lv":40,"d":57.1,"d0":52.63,"d1":57.97,"dp":100,"m":0,"m0":0,"m1":0,"td":600,"td0":600,"td1":600,"e":0.06,"e0":0.06,"e1":0.06,"tw":10.5,"er":102.8,"bu":0.9,"bd":6.8},{"i":"electivire_shadow","n":"Electivire (Shadow)","f":"THUNDER_SHOCK","c":"WILD_CHARGE","cp":3079,"lv":40,"d":60.5,"d0":56.07,"d1":66.3,"dp":100,"m":0,"m0":0,"m1":0,"td":600,"td0":600,"td1":600,"e":0.06,"e0":0.05,"e1":0.06,"tw":9.9,"er":107.37,"bu":0.7,"bd":22.1},{"i":"xurkitree","n":"Xurkitree","f":"THUNDER_SHOCK","c":"POWER_WHIP","cp":3937,"lv":40,"d":60.13,"d0":56.07,"d1":62.5,"dp":100,"m":0,"m0":0,"m1":0,"td":600,"td0":600,"td1":600,"e":0.06,"e0":0.05,"e1":0.06,"tw":10,"er":106.88,"bu":0.7,"bd":19.4},{"i":"xurkitree","n":"Xurkitree","f":"SPARK","c":"POWER_WHIP","cp":3937,"lv":40,"d":56.02,"d0":50.85,"d1":59.11,"dp":100,"m":0,"m0":0,"m1":0,"td":600,"td0":600,"td1":600,"e":0.06,"e0":0.06,"e1":0.07,"tw":10.7,"er":101.35,"bu":0.8,"bd":19.4},{"i":"golem_alolan_shadow","n":"Golem (Alolan) (Shadow)","f":"VOLT_SWITCH","c":"WILD_CHARGE","cp":2949,"lv":40,"d":57.71,"d0":55.81,"d1":65.22,"dp":100,"m":0,"m0":0,"m1":0,"td":600,"td0":600,"td1":600,"e":0.06,"e0":0.05,"e1":0.06,"tw":10.4,"er":103.63,"bu":0.5,"bd":27.8},{"i":"raikou_shadow","n":"Raikou (Shadow)","f":"VOLT_SWITCH","c":"THUNDERBOLT","cp":3452,"lv":40,"d":57.75,"d0":55.81,"d1":65.22,"dp":100,"m":0,"m0":0,"m1":0,"td":600,"td0":600,"td1":600,"e":0.06,"e0":0.05,"e1":0.06,"tw":10.4,"er":103.68,"bu":0.6,"bd":16.6},{"i":"raikou_shadow","n":"Raikou (Shadow)","f":"VOLT_SWITCH","c":"WILD_CHARGE","cp":3452,"lv":40,"d":57.32,"d0":55.81,"d1":65.22,"dp":100,"m":0,"m0":0,"m1":0,"td":600,"td0":600,"td1":600,"e":0.06,"e0":0.05,"e1":0.06,"tw":10.5,"er":103.1,"bu":0.5,"bd":16.6},{"i":"raikou_shadow","n":"Raikou (Shadow)","f":"THUNDER_SHOCK","c":"THUNDERBOLT","cp":3452,"lv":40,"d":59.81,"d0":56.07,"d1":62.5,"dp":100,"m":0,"m0":0,"m1":0,"td":600,"td0":600,"td1":600,"e":0.06,"e0":0.05,"e1":0.06,"tw":10.1,"er":106.44,"bu":0.7,"bd":16.6},{"i":"raikou_shadow","n":"Raikou (Shadow)","f":"THUNDER_SHOCK","c":"WILD_CHARGE","cp":3452,"lv":40,"d":60.43,"d0":56.07,"d1":62.5,"dp":100,"m":0,"m0":0,"m1":0,"td":600,"td0":600,"td1":600,"e":0.06,"e0":0.05,"e1":0.06,"tw":10,"er":107.27,"bu":0.8,"bd":16.6},{"i":"manectric_mega","n":"Manectric (Mega)","f":"CHARGE_BEAM","c":"WILD_CHARGE","cp":3580,"lv":40,"d":60.33,"d0":57.97,"d1":64.52,"dp":100,"m":0,"m0":0,"m1":0,"td":600,"td0":600,"td1":600,"e":0.06,"e0":0.05,"e1":0.06,"tw":10,"er":107.13,"bu":0.6,"bd":17.7},{"i":"manectric_mega","n":"Manectric (Mega)","f":"SNARL","c":"WILD_CHARGE","cp":3580,"lv":40,"d":55.14,"d0":52.63,"d1":57.97,"dp":100,"m":0,"m0":0,"m1":0,"td":600,"td0":600,"td1":600,"e":0.06,"e0":0.06,"e1":0.06,"tw":10.9,"er":100.14,"bu":0.6,"bd":17.7},{"i":"manectric_mega","n":"Manectric (Mega)","f":"THUNDER_FANG","c":"WILD_CHARGE","cp":3580,"lv":40,"d":55.8,"d0":52.63,"d1":57.97,"dp":100,"m":0,"m0":0,"m1":0,"td":600,"td0":600,"td1":600,"e":0.06,"e0":0.06,"e1":0.06,"tw":10.8,"er":101.04,"bu":0.7,"bd":17.7},{"i":"manectric_shadow","n":"Manectric (Shadow)","f":"THUNDER_FANG","c":"WILD_CHARGE","cp":2340,"lv":40,"d":57.94,"d0":52.63,"d1":64.52,"dp":100,"m":0,"m0":0,"m1":0,"td":600,"td0":600,"td1":600,"e":0.06,"e0":0.05,"e1":0.06,"tw":10.4,"er":103.94,"bu":0.6,"bd":28.6},{"i":"luxray_shadow","n":"Luxray (Shadow)","f":"SNARL","c":"WILD_CHARGE","cp":2888,"lv":40,"d":56.18,"d0":52.63,"d1":64.52,"dp":100,"m":0,"m0":0,"m1":0,"td":600,"td0":600,"td1":600,"e":0.06,"e0":0.05,"e1":0.06,"tw":10.7,"er":101.55,"bu":0.6,"bd":21.6},{"i":"luxray_shadow","n":"Luxray (Shadow)","f":"SPARK","c":"WILD_CHARGE","cp":2888,"lv":40,"d":57.24,"d0":50.85,"d1":59.11,"dp":100,"m":0,"m0":0,"m1":0,"td":600,"td0":600,"td1":600,"e":0.06,"e0":0.06,"e1":0.07,"tw":10.5,"er":103,"bu":0.8,"bd":21.6},{"i":"mewtwo_shadow","n":"Mewtwo (Shadow)","f":"PSYCHO_CUT","c":"THUNDERBOLT","cp":4178,"lv":40,"d":58.39,"d0":56.07,"d1":62.5,"dp":100,"m":0,"m0":0,"m1":0,"td":600,"td0":600,"td1":600,"e":0.06,"e0":0.05,"e1":0.06,"tw":10.3,"er":104.54,"bu":0.5,"bd":17.2}],"bubble_water_pulse":[{"i":"zapdos_shadow","n":"Zapdos (Shadow)","f":"THUNDER_SHOCK","c":"ZAP_CANNON","cp":3527,"lv":40,"d":78.02,"d0":77.92,"d1":83.92,"dp":100,"m":0,"m0":0,"m1":0,"td":600,"td0":600,"td1":600,"e":0.04,"e0":0.04,"e1":0.04,"tw":7.7,"er":129.93,"bu":0.1,"bd":18.9},{"i":"regieleki","n":"Regieleki","f":"THUNDER_SHOCK","c":"THUNDER_CAGE","cp":2803,"lv":40,"d":78.23,"d0":77.92,"d1":83.92,"dp":100,"m":0,"m0":0,"m1":0,"td":600,"td0":600,"td1":600,"e":0.04,"e0":0.04,"e1":0.04,"tw":7.7,"er":130.18,"bu":0.2,"bd":24.1},{"i":"regieleki","n":"Regieleki","f":"VOLT_SWITCH","c":"THUNDER_CAGE","cp":2803,"lv":40,"d":77.42,"d0":77.42,"d1":77.42,"dp":100,"m":0,"m0":0,"m1":0,"td":600,"td0":600,"td1":600,"e":0.04,"e0":0.04,"e1":0.04,"tw":7.8,"er":129.17,"bu":0,"bd":24.1},{"i":"porygon_z_shadow","n":"Porygon-Z (Shadow)","f":"CHARGE_BEAM","c":"SOLAR_BEAM","cp":3266,"lv":40,"d":81.63,"d0":81.63,"d1":81.63,"dp":100,"m":0,"m0":0,"m1":0,"td":600,"td0":600,"td1":600,"e":0.04,"e0":0.04,"e1":0.04,"tw":7.3,"er":134.41,"bu":0,"bd":23.2},{"i":"ampharos_mega","n":"Ampharos (Mega)","f":"VOLT_SWITCH","c":"ZAP_CANNON","cp":4245,"lv":40,"d":77.42,"d0":77.42,"d1":77.42,"dp":100,"m":0,"m0":0,"m1":0,"td":600,"td0":600,"td1":600,"e":0.04,"e0":0.04,"e1":0.04,"tw":7.8,"er":129.17,"bu":0,"bd":9.1},{"i":"magnezone_shadow","n":"Magnezone (Shadow)","f":"VOLT_SWITCH","c":"ZAP_CANNON","cp":3205,"lv":40,"d":77.42,"d0":77.42,"d1":77.42,"dp":100,"m":0,"m0":0,"m1":0,"td":600,"td0":600,"td1":600,"e":0.04,"e0":0.04,"e1":0.04,"tw":7.8,"er":129.17,"bu":0,"bd":20.4},{"i":"thundurus_therian","n":"Thundurus (Therian)","f":"VOLT_SWITCH","c":"WILDBOLT_STORM","cp":3659,"lv":40,"d":77.42,"d0":77.42,"d1":77.42,"dp":100,"m":0,"m0":0,"m1":0,"td":600,"td0":600,"td1":600,"e":0.04,"e0":0.04,"e1":0.04,"tw":7.8,"er":129.17,"bu":0,"bd":19.4},{"i":"zapdos_shadow","n":"Zapdos (Shadow)","f":"CHARGE_BEAM","c":"THUNDERBOLT","cp":3527,"lv":40,"d":61.24,"d0":57.97,"d1":64.52,"dp":100,"m":0,"m0":0,"m1":0,"td":600,"td0":600,"td1":600,"e":0.05,"e0":0.05,"e1":0.06,"tw":9.8,"er":108.35,"bu":0.5,"bd":18.9},{"i":"zapdos_shadow","n":"Zapdos (Shadow)","f":"THUNDER_SHOCK","c":"THUNDERBOLT","cp":3527,"lv":40,"d":62.51,"d0":59.11,"d1":66.3,"dp":100,"m":0,"m0":0,"m1":0,"td":600,"td0":600,"td1":600,"e":0.05,"e0":0.05,"e1":0.06,"tw":9.6,"er":110.03,"bu":0.8,"bd":18.9},{"i":"regieleki","n":"Regieleki","f":"LOCK_ON","c":"THUNDER_CAGE","cp":2803,"lv":40,"d":60.91,"d0":60.91,"d1":60.91,"dp":100,"m":0,"m0":0,"m1":0,"td":600,"td0":600,"td1":600,"e":0.05,"e0":0.05,"e1":0.05,"tw":9.9,"er":107.91,"bu":0.5,"bd":24.1},{"i":"magnezone_shadow","n":"Magnezone (Shadow)","f":"CHARGE_BEAM","c":"WILD_CHARGE","cp":3205,"lv":40,"d":62.75,"d0":57.97,"d1":64.52,"dp":100,"m":0,"m0":0,"m1":0,"td":600,"td0":600,"td1":600,"e":0.05,"e0":0.05,"e1":0.06,"tw":9.6,"er":110.35,"bu":0.8,"bd":20.4},{"i":"groudon_primal","n":"Groudon (Primal)","f":"MUD_SHOT","c":"SOLAR_BEAM","cp":5902,"lv":40,"d":71.42,"d0":68.18,"d1":72.73,"dp":100,"m":0,"m0":0,"m1":0,"td":600,"td0":600,"td1":600,"e":0.05,"e0":0.05,"e1":0.05,"tw":8.4,"er":121.59,"bu":0,"bd":26.6},{"i":"groudon_shadow","n":"Groudon (Shadow)","f":"MUD_SHOT","c":"SOLAR_BEAM","cp":4115,"lv":40,"d":71.49,"d0":68.18,"d1":72.73,"dp":100,"m":0,"m0":0,"m1":0,"td":600,"td0":600,"td1":600,"e":0.05,"e0":0.05,"e1":0.05,"tw":8.4,"er":121.68,"bu":0,"bd":24.9},{"i":"exeggutor_alolan_shadow","n":"Exeggutor (Alolan) (Shadow)","f":"BULLET_SEED","c":"SOLAR_BEAM","cp":3014,"lv":40,"d":71.43,"d0":71.43,"d1":71.43,"dp":100,"m":0,"m0":0,"m1":0,"td":600,"td0":600,"td1":600,"e":0.05,"e0":0.05,"e1":0.05,"tw":8.4,"er":121.6,"bu":0,"bd":8.2},{"i":"exeggutor_shadow","n":"Exeggutor (Shadow)","f":"BULLET_SEED","c":"SOLAR_BEAM","cp":3014,"lv":40,"d":71.43,"d0":71.43,"d1":71.43,"dp":100,"m":0,"m0":0,"m1":0,"td":600,"td0":600,"td1":600,"e":0.05,"e0":0.05,"e1":0.05,"tw":8.4,"er":121.6,"bu":0,"bd":13.7},{"i":"exeggutor_shadow","n":"Exeggutor (Shadow)","f":"EXTRASENSORY","c":"SOLAR_BEAM","cp":3014,"lv":40,"d":63.49,"d0":63.49,"d1":63.49,"dp":100,"m":0,"m0":0,"m1":0,"td":600,"td0":600,"td1":600,"e":0.05,"e0":0.05,"e1":0.05,"tw":9.4,"er":111.32,"bu":0,"bd":13.7},{"i":"tapu_bulu","n":"Tapu Bulu","f":"BULLET_SEED","c":"SOLAR_BEAM","cp":3419,"lv":40,"d":71.43,"d0":71.43,"d1":71.43,"dp":100,"m":0,"m0":0,"m1":0,"td":600,"td0":600,"td1":600,"e":0.05,"e0":0.05,"e1":0.05,"tw":8.4,"er":121.6,"bu":0,"bd":10.2},{"i":"mewtwo_shadow","n":"Mewtwo (Shadow)","f":"PSYCHO_CUT","c":"THUNDERBOLT","cp":4178,"lv":40,"d":62.77,"d0":59.11,"d1":66.3,"dp":100,"m":0,"m0":0,"m1":0,"td":600,"td0":600,"td1":600,"e":0.05,"e0":0.05,"e1":0.06,"tw":9.6,"er":110.37,"bu":0.5,"bd":18.3},{"i":"sceptile_shadow","n":"Sceptile (Shadow)","f":"FURY_CUTTER","c":"FRENZY_PLANT","cp":2757,"lv":40,"d":64.42,"d0":62.5,"d1":66.3,"dp":100,"m":0,"m0":0,"m1":0,"td":600,"td0":600,"td1":600,"e":0.05,"e0":0.05,"e1":0.05,"tw":9.3,"er":112.54,"bu":0.5,"bd":15},{"i":"victreebel","n":"Victreebel","f":"MAGICAL_LEAF","c":"SOLAR_BEAM","cp":2431,"lv":40,"d":64.52,"d0":64.52,"d1":64.52,"dp":100,"m":0,"m0":0,"m1":0,"td":600,"td0":600,"td1":600,"e":0.05,"e0":0.05,"e1":0.05,"tw":9.3,"er":112.67,"bu":0,"bd":14.2},{"i":"victreebel_mega","n":"Victreebel (Mega)","f":"MAGICAL_LEAF","c":"SOLAR_BEAM","cp":3505,"lv":40,"d":64.52,"d0":64.52,"d1":64.52,"dp":100,"m":0,"m0":0,"m1":0,"td":600,"td0":600,"td1":600,"e":0.05,"e0":0.05,"e1":0.05,"tw":9.3,"er":112.67,"bu":0.3,"bd":11.1},{"i":"victreebel_shadow","n":"Victreebel (Shadow)","f":"MAGICAL_LEAF","c":"SOLAR_BEAM","cp":2431,"lv":40,"d":64.52,"d0":64.52,"d1":64.52,"dp":100,"m":0,"m0":0,"m1":0,"td":600,"td0":600,"td1":600,"e":0.05,"e0":0.05,"e1":0.05,"tw":9.3,"er":112.67,"bu":0.3,"bd":16.7},{"i":"meganium_shadow","n":"Meganium (Shadow)","f":"MAGICAL_LEAF","c":"SOLAR_BEAM","cp":2410,"lv":40,"d":64.52,"d0":64.52,"d1":64.52,"dp":100,"m":0,"m0":0,"m1":0,"td":600,"td0":600,"td1":600,"e":0.05,"e0":0.05,"e1":0.05,"tw":9.3,"er":112.67,"bu":0,"bd":11.7},{"i":"ho_oh_shadow","n":"Ho-Oh (Shadow)","f":"HIDDEN_POWER_ELECTRIC","c":"SOLAR_BEAM","cp":3863,"lv":40,"d":64.52,"d0":64.52,"d1":64.52,"dp":100,"m":0,"m0":0,"m1":0,"td":600,"td0":600,"td1":600,"e":0.05,"e0":0.05,"e1":0.05,"tw":9.3,"er":112.67,"bu":0,"bd":22.2},{"i":"ho_oh_shadow","n":"Ho-Oh (Shadow)","f":"HIDDEN_POWER_FLYING","c":"SOLAR_BEAM","cp":3863,"lv":40,"d":64.52,"d0":64.52,"d1":64.52,"dp":100,"m":0,"m0":0,"m1":0,"td":600,"td0":600,"td1":600,"e":0.05,"e0":0.05,"e1":0.05,"tw":9.3,"er":112.67,"bu":0,"bd":22.2},{"i":"ho_oh_shadow","n":"Ho-Oh (Shadow)","f":"HIDDEN_POWER_GRASS","c":"SOLAR_BEAM","cp":3863,"lv":40,"d":64.52,"d0":64.52,"d1":64.52,"dp":100,"m":0,"m0":0,"m1":0,"td":600,"td0":600,"td1":600,"e":0.05,"e0":0.05,"e1":0.05,"tw":9.3,"er":112.67,"bu":0,"bd":22.2},{"i":"manectric_mega","n":"Manectric (Mega)","f":"CHARGE_BEAM","c":"WILD_CHARGE","cp":3580,"lv":40,"d":62.78,"d0":57.97,"d1":64.52,"dp":100,"m":0,"m0":0,"m1":0,"td":600,"td0":600,"td1":600,"e":0.05,"e0":0.05,"e1":0.06,"tw":9.6,"er":110.38,"bu":0.8,"bd":19},{"i":"manectric_shadow","n":"Manectric (Shadow)","f":"THUNDER_FANG","c":"WILD_CHARGE","cp":2340,"lv":40,"d":61.27,"d0":57.97,"d1":64.52,"dp":100,"m":0,"m0":0,"m1":0,"td":600,"td0":600,"td1":600,"e":0.05,"e0":0.05,"e1":0.06,"tw":9.8,"er":108.38,"bu":0.6,"bd":31.3},{"i":"luxray_shadow","n":"Luxray (Shadow)","f":"SNARL","c":"WILD_CHARGE","cp":2888,"lv":40,"d":61.35,"d0":57.97,"d1":64.52,"dp":100,"m":0,"m0":0,"m1":0,"td":600,"td0":600,"td1":600,"e":0.05,"e0":0.05,"e1":0.06,"tw":9.8,"er":108.49,"bu":0.6,"bd":23.5},{"i":"roserade","n":"Roserade","f":"MAGICAL_LEAF","c":"SOLAR_BEAM","cp":2971,"lv":40,"d":64.52,"d0":64.52,"d1":64.52,"dp":100,"m":0,"m0":0,"m1":0,"td":600,"td0":600,"td1":600,"e":0.05,"e0":0.05,"e1":0.05,"tw":9.3,"er":112.67,"bu":0.3,"bd":12.7},{"i":"shaymin_land","n":"Shaymin (Land)","f":"MAGICAL_LEAF","c":"SOLAR_BEAM","cp":3265,"lv":40,"d":64.52,"d0":64.52,"d1":64.52,"dp":100,"m":0,"m0":0,"m1":0,"td":600,"td0":600,"td1":600,"e":0.05,"e0":0.05,"e1":0.05,"tw":9.3,"er":112.67,"bu":0,"bd":7.9},{"i":"shaymin_sky","n":"Shaymin (Sky)","f":"MAGICAL_LEAF","c":"SOLAR_BEAM","cp":3592,"lv":40,"d":64.52,"d0":64.52,"d1":64.52,"dp":100,"m":0,"m0":0,"m1":0,"td":600,"td0":600,"td1":600,"e":0.05,"e0":0.05,"e1":0.05,"tw":9.3,"er":112.67,"bu":0.4,"bd":10.1},{"i":"lilligant","n":"Lilligant","f":"MAGICAL_LEAF","c":"SOLAR_BEAM","cp":2550,"lv":40,"d":64.52,"d0":64.52,"d1":64.52,"dp":100,"m":0,"m0":0,"m1":0,"td":600,"td0":600,"td1":600,"e":0.05,"e0":0.05,"e1":0.05,"tw":9.3,"er":112.67,"bu":0,"bd":13.6},{"i":"lilligant_hisuian","n":"Lilligant (Hisuian)","f":"MAGICAL_LEAF","c":"SOLAR_BEAM","cp":2512,"lv":40,"d":64.52,"d0":64.52,"d1":64.52,"dp":100,"m":0,"m0":0,"m1":0,"td":600,"td0":600,"td1":600,"e":0.05,"e0":0.05,"e1":0.05,"tw":9.3,"er":112.67,"bu":0,"bd":13.6},{"i":"deoxys_attack","n":"Deoxys (Attack)","f":"POISON_JAB","c":"ZAP_CANNON","cp":2580,"lv":40,"d":63.43,"d0":29.47,"d1":63.49,"dp":100,"m":0,"m0":0,"m1":1,"td":600,"td0":600,"td1":600,"e":0.05,"e0":0.05,"e1":0.11,"tw":9.5,"er":111.24,"bu":0.1,"bd":73.3},{"i":"deoxys_attack","n":"Deoxys (Attack)","f":"ZEN_HEADBUTT","c":"ZAP_CANNON","cp":2580,"lv":40,"d":63.49,"d0":63.49,"d1":63.49,"dp":100,"m":0,"m0":0,"m1":0,"td":600,"td0":600,"td1":600,"e":0.05,"e0":0.05,"e1":0.05,"tw":9.4,"er":111.32,"bu":0.1,"bd":73.3},{"i":"raikou_shadow","n":"Raikou (Shadow)","f":"THUNDER_SHOCK","c":"THUNDERBOLT","cp":3452,"lv":40,"d":61.69,"d0":59.11,"d1":62.5,"dp":100,"m":0,"m0":0,"m1":0,"td":600,"td0":600,"td1":600,"e":0.05,"e0":0.05,"e1":0.06,"tw":9.7,"er":108.94,"bu":0.8,"bd":17.7},{"i":"raikou_shadow","n":"Raikou (Shadow)","f":"THUNDER_SHOCK","c":"WILD_CHARGE","cp":3452,"lv":40,"d":61.6,"d0":59.11,"d1":62.5,"dp":100,"m":0,"m0":0,"m1":0,"td":600,"td0":600,"td1":600,"e":0.05,"e0":0.05,"e1":0.06,"tw":9.7,"er":108.82,"bu":0.7,"bd":17.7},{"i":"sceptile_mega","n":"Sceptile (Mega)","f":"FURY_CUTTER","c":"FRENZY_PLANT","cp":4056,"lv":40,"d":61.73,"d0":59.11,"d1":62.5,"dp":100,"m":0,"m0":0,"m1":0,"td":600,"td0":600,"td1":600,"e":0.05,"e0":0.05,"e1":0.06,"tw":9.7,"er":109,"bu":0.8,"bd":7.5},{"i":"electivire_shadow","n":"Electivire (Shadow)","f":"THUNDER_SHOCK","c":"WILD_CHARGE","cp":3079,"lv":40,"d":62.68,"d0":59.11,"d1":66.3,"dp":100,"m":0,"m0":0,"m1":0,"td":600,"td0":600,"td1":600,"e":0.05,"e0":0.05,"e1":0.06,"tw":9.6,"er":110.25,"bu":0.8,"bd":24},{"i":"porygon_z_shadow","n":"Porygon-Z (Shadow)","f":"HIDDEN_POWER_ELECTRIC","c":"SOLAR_BEAM","cp":3266,"lv":40,"d":58.6,"d0":55.3,"d1":64.52,"dp":100,"m":0,"m0":0,"m1":0,"td":600,"td0":600,"td1":600,"e":0.06,"e0":0.05,"e1":0.06,"tw":10.3,"er":104.83,"bu":0.5,"bd":23.2},{"i":"porygon_z_shadow","n":"Porygon-Z (Shadow)","f":"HIDDEN_POWER_ELECTRIC","c":"ZAP_CANNON","cp":3266,"lv":40,"d":58.65,"d0":55.3,"d1":64.52,"dp":100,"m":0,"m0":0,"m1":0,"td":600,"td0":600,"td1":600,"e":0.06,"e0":0.05,"e1":0.06,"tw":10.3,"er":104.89,"bu":0.5,"bd":23.2},{"i":"porygon_z_shadow","n":"Porygon-Z (Shadow)","f":"HIDDEN_POWER_GRASS","c":"SOLAR_BEAM","cp":3266,"lv":40,"d":58.33,"d0":55.3,"d1":64.52,"dp":100,"m":0,"m0":0,"m1":0,"td":600,"td0":600,"td1":600,"e":0.06,"e0":0.05,"e1":0.06,"tw":10.3,"er":104.47,"bu":0.5,"bd":23.2},{"i":"porygon_z_shadow","n":"Porygon-Z (Shadow)","f":"HIDDEN_POWER_GRASS","c":"ZAP_CANNON","cp":3266,"lv":40,"d":58.3,"d0":55.3,"d1":64.52,"dp":100,"m":0,"m0":0,"m1":0,"td":600,"td0":600,"td1":600,"e":0.06,"e0":0.05,"e1":0.06,"tw":10.3,"er":104.42,"bu":0.5,"bd":23.2},{"i":"magnezone_shadow","n":"Magnezone (Shadow)","f":"SPARK","c":"ZAP_CANNON","cp":3205,"lv":40,"d":61.09,"d0":48.98,"d1":68.18,"dp":100,"m":0,"m0":0,"m1":0,"td":600,"td0":600,"td1":600,"e":0.06,"e0":0.05,"e1":0.07,"tw":10.1,"er":108.15,"bu":0.5,"bd":20.4},{"i":"magnezone_shadow","n":"Magnezone (Shadow)","f":"VOLT_SWITCH","c":"WILD_CHARGE","cp":3205,"lv":40,"d":58.16,"d0":55.81,"d1":65.22,"dp":100,"m":0,"m0":0,"m1":0,"td":600,"td0":600,"td1":600,"e":0.06,"e0":0.05,"e1":0.06,"tw":10.4,"er":104.23,"bu":0.8,"bd":20.4},{"i":"thundurus_therian","n":"Thundurus (Therian)","f":"VOLT_SWITCH","c":"THUNDERBOLT","cp":3659,"lv":40,"d":60.52,"d0":55.81,"d1":65.22,"dp":100,"m":0,"m0":0,"m1":0,"td":600,"td0":600,"td1":600,"e":0.06,"e0":0.05,"e1":0.06,"tw":10,"er":107.38,"bu":0.6,"bd":19.4},{"i":"meganium_shadow","n":"Meganium (Shadow)","f":"VINE_WHIP","c":"SOLAR_BEAM","cp":2410,"lv":40,"d":59.07,"d0":57.42,"d1":60.61,"dp":100,"m":0,"m0":0,"m1":0,"td":600,"td0":600,"td1":600,"e":0.06,"e0":0.06,"e1":0.06,"tw":10.2,"er":105.45,"bu":0.5,"bd":11.7},{"i":"manectric_mega","n":"Manectric (Mega)","f":"SNARL","c":"WILD_CHARGE","cp":3580,"lv":40,"d":57.97,"d0":57.97,"d1":57.97,"dp":100,"m":0,"m0":0,"m1":0,"td":600,"td0":600,"td1":600,"e":0.06,"e0":0.06,"e1":0.06,"tw":10.4,"er":103.98,"bu":0.5,"bd":19},{"i":"shaymin_sky","n":"Shaymin (Sky)","f":"HIDDEN_POWER_GRASS","c":"SOLAR_BEAM","cp":3592,"lv":40,"d":58.5,"d0":55.3,"d1":64.52,"dp":100,"m":0,"m0":0,"m1":0,"td":600,"td0":600,"td1":600,"e":0.06,"e0":0.05,"e1":0.06,"tw":10.3,"er":104.69,"bu":0.5,"bd":10.1},{"i":"shaymin_sky","n":"Shaymin (Sky)","f":"HIDDEN_POWER_DRAGON","c":"SOLAR_BEAM","cp":3592,"lv":40,"d":55.3,"d0":55.3,"d1":55.3,"dp":100,"m":0,"m0":0,"m1":0,"td":600,"td0":600,"td1":600,"e":0.06,"e0":0.06,"e1":0.06,"tw":10.9,"er":100.36,"bu":0.2,"bd":10.1},{"i":"raikou_shadow","n":"Raikou (Shadow)","f":"VOLT_SWITCH","c":"THUNDERBOLT","cp":3452,"lv":40,"d":60.36,"d0":55.81,"d1":65.22,"dp":100,"m":0,"m0":0,"m1":0,"td":600,"td0":600,"td1":600,"e":0.06,"e0":0.05,"e1":0.06,"tw":10,"er":107.18,"bu":0.6,"bd":17.7},{"i":"raikou_shadow","n":"Raikou (Shadow)","f":"VOLT_SWITCH","c":"WILD_CHARGE","cp":3452,"lv":40,"d":58.55,"d0":55.81,"d1":65.22,"dp":100,"m":0,"m0":0,"m1":0,"td":600,"td0":600,"td1":600,"e":0.06,"e0":0.05,"e1":0.06,"tw":10.3,"er":104.76,"bu":0.8,"bd":17.7}],"bubble_aerial_ace":[{"i":"zapdos_shadow","n":"Zapdos (Shadow)","f":"THUNDER_SHOCK","c":"ZAP_CANNON","cp":3527,"lv":40,"d":78.14,"d0":77.92,"d1":83.92,"dp":100,"m":0,"m0":0,"m1":0,"td":600,"td0":600,"td1":600,"e":0.04,"e0":0.04,"e1":0.04,"tw":7.7,"er":130.07,"bu":0.1,"bd":8.6},{"i":"regieleki","n":"Regieleki","f":"THUNDER_SHOCK","c":"THUNDER_CAGE","cp":2803,"lv":40,"d":78.27,"d0":77.92,"d1":83.92,"dp":100,"m":0,"m0":0,"m1":0,"td":600,"td0":600,"td1":600,"e":0.04,"e0":0.04,"e1":0.04,"tw":7.7,"er":130.24,"bu":0.2,"bd":10.5},{"i":"regieleki","n":"Regieleki","f":"VOLT_SWITCH","c":"THUNDER_CAGE","cp":2803,"lv":40,"d":77.42,"d0":77.42,"d1":77.42,"dp":100,"m":0,"m0":0,"m1":0,"td":600,"td0":600,"td1":600,"e":0.04,"e0":0.04,"e1":0.04,"tw":7.8,"er":129.17,"bu":0.2,"bd":10.5},{"i":"porygon_z_shadow","n":"Porygon-Z (Shadow)","f":"CHARGE_BEAM","c":"SOLAR_BEAM","cp":3266,"lv":40,"d":81.63,"d0":81.63,"d1":81.63,"dp":100,"m":0,"m0":0,"m1":0,"td":600,"td0":600,"td1":600,"e":0.04,"e0":0.04,"e1":0.04,"tw":7.3,"er":134.41,"bu":0,"bd":16.7},{"i":"ampharos_mega","n":"Ampharos (Mega)","f":"VOLT_SWITCH","c":"ZAP_CANNON","cp":4245,"lv":40,"d":77.42,"d0":77.42,"d1":77.42,"dp":100,"m":0,"m0":0,"m1":0,"td":600,"td0":600,"td1":600,"e":0.04,"e0":0.04,"e1":0.04,"tw":7.8,"er":129.17,"bu":0.1,"bd":6.3},{"i":"magnezone_shadow","n":"Magnezone (Shadow)","f":"VOLT_SWITCH","c":"ZAP_CANNON","cp":3205,"lv":40,"d":77.42,"d0":77.42,"d1":77.42,"dp":100,"m":0,"m0":0,"m1":0,"td":600,"td0":600,"td1":600,"e":0.04,"e0":0.04,"e1":0.04,"tw":7.8,"er":129.17,"bu":0.2,"bd":6.1},{"i":"thundurus_therian","n":"Thundurus (Therian)","f":"VOLT_SWITCH","c":"WILDBOLT_STORM","cp":3659,"lv":40,"d":77.42,"d0":77.42,"d1":77.42,"dp":100,"m":0,"m0":0,"m1":0,"td":600,"td0":600,"td1":600,"e":0.04,"e0":0.04,"e1":0.04,"tw":7.8,"er":129.17,"bu":0.1,"bd":8.8},{"i":"regieleki","n":"Regieleki","f":"LOCK_ON","c":"THUNDER_CAGE","cp":2803,"lv":40,"d":60.91,"d0":60.91,"d1":60.91,"dp":100,"m":0,"m0":0,"m1":0,"td":600,"td0":600,"td1":600,"e":0.05,"e0":0.05,"e1":0.05,"tw":9.9,"er":107.91,"bu":0.5,"bd":10.5},{"i":"exeggutor_alolan_shadow","n":"Exeggutor (Alolan) (Shadow)","f":"BULLET_SEED","c":"SOLAR_BEAM","cp":3014,"lv":40,"d":71.82,"d0":71.43,"d1":81.63,"dp":100,"m":0,"m0":0,"m1":0,"td":600,"td0":600,"td1":600,"e":0.05,"e0":0.04,"e1":0.05,"tw":8.4,"er":122.1,"bu":0.4,"bd":24.2},{"i":"exeggutor_shadow","n":"Exeggutor (Shadow)","f":"BULLET_SEED","c":"SOLAR_BEAM","cp":3014,"lv":40,"d":72,"d0":71.43,"d1":81.63,"dp":100,"m":0,"m0":0,"m1":0,"td":600,"td0":600,"td1":600,"e":0.05,"e0":0.04,"e1":0.05,"tw":8.3,"er":122.34,"bu":0.4,"bd":24.7},{"i":"exeggutor_shadow","n":"Exeggutor (Shadow)","f":"EXTRASENSORY","c":"SOLAR_BEAM","cp":3014,"lv":40,"d":67.45,"d0":63.49,"d1":81.63,"dp":100,"m":0,"m0":0,"m1":0,"td":600,"td0":600,"td1":600,"e":0.05,"e0":0.04,"e1":0.05,"tw":8.9,"er":116.48,"bu":0.5,"bd":24.7},{"i":"deoxys_attack","n":"Deoxys (Attack)","f":"POISON_JAB","c":"ZAP_CANNON","cp":2580,"lv":40,"d":67,"d0":63.49,"d1":81.63,"dp":100,"m":0,"m0":0,"m1":0,"td":600,"td0":600,"td1":600,"e":0.05,"e0":0.04,"e1":0.05,"tw":9,"er":115.91,"bu":0.5,"bd":51.7},{"i":"deoxys_attack","n":"Deoxys (Attack)","f":"ZEN_HEADBUTT","c":"ZAP_CANNON","cp":2580,"lv":40,"d":67.18,"d0":63.49,"d1":81.63,"dp":100,"m":0,"m0":0,"m1":0,"td":600,"td0":600,"td1":600,"e":0.05,"e0":0.04,"e1":0.05,"tw":9,"er":116.14,"bu":0.5,"bd":51.7},{"i":"groudon_shadow","n":"Groudon (Shadow)","f":"MUD_SHOT","c":"SOLAR_BEAM","cp":4115,"lv":40,"d":71.97,"d0":68.18,"d1":77.92,"dp":100,"m":0,"m0":0,"m1":0,"td":600,"td0":600,"td1":600,"e":0.05,"e0":0.04,"e1":0.05,"tw":8.4,"er":122.3,"bu":0.5,"bd":11},{"i":"chesnaught_shadow","n":"Chesnaught (Shadow)","f":"VINE_WHIP","c":"SOLAR_BEAM","cp":2954,"lv":40,"d":65.85,"d0":57.42,"d1":77.92,"dp":100,"m":0,"m0":0,"m1":0,"td":600,"td0":600,"td1":600,"e":0.05,"e0":0.04,"e1":0.06,"tw":9.3,"er":114.4,"bu":0.6,"bd":30.6},{"i":"victreebel_mega","n":"Victreebel (Mega)","f":"MAGICAL_LEAF","c":"SOLAR_BEAM","cp":3505,"lv":40,"d":66.35,"d0":64.52,"d1":77.42,"dp":100,"m":0,"m0":0,"m1":0,"td":600,"td0":600,"td1":600,"e":0.05,"e0":0.04,"e1":0.05,"tw":9.1,"er":115.05,"bu":0.5,"bd":19.1},{"i":"victreebel_mega","n":"Victreebel (Mega)","f":"ACID","c":"SOLAR_BEAM","cp":3505,"lv":40,"d":63.29,"d0":57.14,"d1":71.43,"dp":100,"m":0,"m0":0,"m1":0,"td":600,"td0":600,"td1":600,"e":0.05,"e0":0.05,"e1":0.06,"tw":9.6,"er":111.06,"bu":0.5,"bd":19.1},{"i":"victreebel_shadow","n":"Victreebel (Shadow)","f":"MAGICAL_LEAF","c":"SOLAR_BEAM","cp":2431,"lv":40,"d":66.44,"d0":64.52,"d1":77.42,"dp":100,"m":0,"m0":0,"m1":0,"td":600,"td0":600,"td1":600,"e":0.05,"e0":0.04,"e1":0.05,"tw":9.1,"er":115.18,"bu":0.5,"bd":30.2},{"i":"victreebel_shadow","n":"Victreebel (Shadow)","f":"ACID","c":"SOLAR_BEAM","cp":2431,"lv":40,"d":62.2,"d0":46.69,"d1":71.43,"dp":100,"m":0,"m0":0,"m1":0,"td":600,"td0":600,"td1":600,"e":0.05,"e0":0.05,"e1":0.07,"tw":9.8,"er":109.62,"bu":0.6,"bd":30.2},{"i":"roserade","n":"Roserade","f":"MAGICAL_LEAF","c":"SOLAR_BEAM","cp":2971,"lv":40,"d":66.42,"d0":64.52,"d1":77.42,"dp":100,"m":0,"m0":0,"m1":0,"td":600,"td0":600,"td1":600,"e":0.05,"e0":0.04,"e1":0.05,"tw":9.1,"er":115.14,"bu":0.5,"bd":23.1},{"i":"shaymin_sky","n":"Shaymin (Sky)","f":"MAGICAL_LEAF","c":"SOLAR_BEAM","cp":3592,"lv":40,"d":66.63,"d0":64.52,"d1":77.42,"dp":100,"m":0,"m0":0,"m1":0,"td":600,"td0":600,"td1":600,"e":0.05,"e0":0.04,"e1":0.05,"tw":9,"er":115.42,"bu":0.5,"bd":18},{"i":"groudon_primal","n":"Groudon (Primal)","f":"MUD_SHOT","c":"SOLAR_BEAM","cp":5902,"lv":40,"d":71.31,"d0":68.18,"d1":72.73,"dp":100,"m":0,"m0":0,"m1":0,"td":600,"td0":600,"td1":600,"e":0.05,"e0":0.05,"e1":0.05,"tw":8.4,"er":121.45,"bu":0.5,"bd":7.6},{"i":"sceptile_shadow","n":"Sceptile (Shadow)","f":"FURY_CUTTER","c":"FRENZY_PLANT","cp":2757,"lv":40,"d":68.25,"d0":62.5,"d1":70.59,"dp":100,"m":0,"m0":0,"m1":0,"td":600,"td0":600,"td1":600,"e":0.05,"e0":0.05,"e1":0.05,"tw":8.8,"er":117.52,"bu":0.7,"bd":27.2},{"i":"sceptile_shadow","n":"Sceptile (Shadow)","f":"BULLET_SEED","c":"FRENZY_PLANT","cp":2757,"lv":40,"d":61.78,"d0":52.63,"d1":64.52,"dp":100,"m":0,"m0":0,"m1":0,"td":600,"td0":600,"td1":600,"e":0.05,"e0":0.05,"e1":0.06,"tw":9.8,"er":109.07,"bu":0.9,"bd":27.2},{"i":"venusaur_shadow","n":"Venusaur (Shadow)","f":"VINE_WHIP","c":"SOLAR_BEAM","cp":2720,"lv":40,"d":63.15,"d0":57.42,"d1":68.18,"dp":100,"m":0,"m0":0,"m1":0,"td":600,"td0":600,"td1":600,"e":0.05,"e0":0.05,"e1":0.06,"tw":9.6,"er":110.88,"bu":0.6,"bd":22.2},{"i":"tangela_shadow","n":"Tangela (Shadow)","f":"VINE_WHIP","c":"SOLAR_BEAM","cp":2238,"lv":40,"d":62.73,"d0":57.42,"d1":68.18,"dp":100,"m":0,"m0":0,"m1":0,"td":600,"td0":600,"td1":600,"e":0.05,"e0":0.05,"e1":0.06,"tw":9.6,"er":110.32,"bu":0.6,"bd":28.6},{"i":"tangrowth_shadow","n":"Tangrowth (Shadow)","f":"VINE_WHIP","c":"SOLAR_BEAM","cp":3030,"lv":40,"d":63.14,"d0":57.42,"d1":68.18,"dp":100,"m":0,"m0":0,"m1":0,"td":600,"td0":600,"td1":600,"e":0.05,"e0":0.05,"e1":0.06,"tw":9.6,"er":110.85,"bu":0.6,"bd":19.6},{"i":"sceptile_mega","n":"Sceptile (Mega)","f":"FURY_CUTTER","c":"FRENZY_PLANT","cp":4056,"lv":40,"d":64.55,"d0":59.11,"d1":66.3,"dp":100,"m":0,"m0":0,"m1":0,"td":600,"td0":600,"td1":600,"e":0.05,"e0":0.05,"e1":0.06,"tw":9.3,"er":112.71,"bu":0.8,"bd":20.4},{"i":"ho_oh_shadow","n":"Ho-Oh (Shadow)","f":"HIDDEN_POWER_ELECTRIC","c":"SOLAR_BEAM","cp":3863,"lv":40,"d":64.52,"d0":64.52,"d1":64.52,"dp":100,"m":0,"m0":0,"m1":0,"td":600,"td0":600,"td1":600,"e":0.05,"e0":0.05,"e1":0.05,"tw":9.3,"er":112.67,"bu":0.5,"bd":10},{"i":"ho_oh_shadow","n":"Ho-Oh (Shadow)","f":"HIDDEN_POWER_FLYING","c":"SOLAR_BEAM","cp":3863,"lv":40,"d":64.52,"d0":64.52,"d1":64.52,"dp":100,"m":0,"m0":0,"m1":0,"td":600,"td0":600,"td1":600,"e":0.05,"e0":0.05,"e1":0.05,"tw":9.3,"er":112.67,"bu":0.5,"bd":10},{"i":"ho_oh_shadow","n":"Ho-Oh (Shadow)","f":"HIDDEN_POWER_GRASS","c":"SOLAR_BEAM","cp":3863,"lv":40,"d":64.52,"d0":64.52,"d1":64.52,"dp":100,"m":0,"m0":0,"m1":0,"td":600,"td0":600,"td1":600,"e":0.05,"e0":0.05,"e1":0.05,"tw":9.3,"er":112.67,"bu":0.5,"bd":10},{"i":"mewtwo_shadow","n":"Mewtwo (Shadow)","f":"PSYCHO_CUT","c":"THUNDERBOLT","cp":4178,"lv":40,"d":61.05,"d0":59.11,"d1":62.5,"dp":100,"m":0,"m0":0,"m1":0,"td":600,"td0":600,"td1":600,"e":0.05,"e0":0.05,"e1":0.06,"tw":9.8,"er":108.1,"bu":0.8,"bd":12.8},{"i":"tapu_bulu","n":"Tapu Bulu","f":"BULLET_SEED","c":"SOLAR_BEAM","cp":3419,"lv":40,"d":70.21,"d0":46.69,"d1":71.43,"dp":100,"m":0,"m0":0,"m1":0,"td":600,"td0":600,"td1":600,"e":0.05,"e0":0.05,"e1":0.07,"tw":8.6,"er":120.05,"bu":0.5,"bd":18.4},{"i":"shaymin_land","n":"Shaymin (Land)","f":"MAGICAL_LEAF","c":"SOLAR_BEAM","cp":3265,"lv":40,"d":61.72,"d0":45.28,"d1":64.52,"dp":100,"m":0,"m0":0,"m1":0,"td":600,"td0":600,"td1":600,"e":0.05,"e0":0.05,"e1":0.07,"tw":9.9,"er":108.98,"bu":0.6,"bd":14.3},{"i":"victreebel","n":"Victreebel","f":"MAGICAL_LEAF","c":"SOLAR_BEAM","cp":2431,"lv":40,"d":61.68,"d0":45.28,"d1":64.52,"dp":100,"m":0,"m0":0,"m1":0,"td":600,"td0":600,"td1":600,"e":0.05,"e0":0.05,"e1":0.07,"tw":9.9,"er":108.93,"bu":0.6,"bd":25.3},{"i":"lilligant_hisuian","n":"Lilligant (Hisuian)","f":"MAGICAL_LEAF","c":"SOLAR_BEAM","cp":2512,"lv":40,"d":61.65,"d0":45.28,"d1":64.52,"dp":100,"m":0,"m0":0,"m1":0,"td":600,"td0":600,"td1":600,"e":0.05,"e0":0.05,"e1":0.07,"tw":9.9,"er":108.89,"bu":0.6,"bd":38.1},{"i":"lilligant","n":"Lilligant","f":"MAGICAL_LEAF","c":"SOLAR_BEAM","cp":2550,"lv":40,"d":62.17,"d0":45.28,"d1":64.52,"dp":100,"m":0,"m0":0,"m1":0,"td":600,"td0":600,"td1":600,"e":0.05,"e0":0.05,"e1":0.07,"tw":9.8,"er":109.58,"bu":0.6,"bd":24.5},{"i":"porygon_z_shadow","n":"Porygon-Z (Shadow)","f":"HIDDEN_POWER_GRASS","c":"ZAP_CANNON","cp":3266,"lv":40,"d":60.11,"d0":55.3,"d1":64.52,"dp":100,"m":0,"m0":0,"m1":0,"td":600,"td0":600,"td1":600,"e":0.06,"e0":0.05,"e1":0.06,"tw":10,"er":106.84,"bu":0.6,"bd":16.7},{"i":"porygon_z_shadow","n":"Porygon-Z (Shadow)","f":"HIDDEN_POWER_ELECTRIC","c":"SOLAR_BEAM","cp":3266,"lv":40,"d":59.86,"d0":55.3,"d1":64.52,"dp":100,"m":0,"m0":0,"m1":0,"td":600,"td0":600,"td1":600,"e":0.06,"e0":0.05,"e1":0.06,"tw":10.1,"er":106.51,"bu":0.6,"bd":16.7},{"i":"porygon_z_shadow","n":"Porygon-Z (Shadow)","f":"HIDDEN_POWER_ROCK","c":"SOLAR_BEAM","cp":3266,"lv":40,"d":59.74,"d0":55.3,"d1":64.52,"dp":100,"m":0,"m0":0,"m1":0,"td":600,"td0":600,"td1":600,"e":0.06,"e0":0.05,"e1":0.06,"tw":10.1,"er":106.35,"bu":0.6,"bd":16.7},{"i":"porygon_z_shadow","n":"Porygon-Z (Shadow)","f":"HIDDEN_POWER_BUG","c":"SOLAR_BEAM","cp":3266,"lv":40,"d":59.81,"d0":55.3,"d1":64.52,"dp":100,"m":0,"m0":0,"m1":0,"td":600,"td0":600,"td1":600,"e":0.06,"e0":0.05,"e1":0.06,"tw":10.1,"er":106.44,"bu":0.6,"bd":16.7},{"i":"porygon_z_shadow","n":"Porygon-Z (Shadow)","f":"HIDDEN_POWER_DARK","c":"SOLAR_BEAM","cp":3266,"lv":40,"d":60.09,"d0":55.3,"d1":64.52,"dp":100,"m":0,"m0":0,"m1":0,"td":600,"td0":600,"td1":600,"e":0.06,"e0":0.05,"e1":0.06,"tw":10,"er":106.82,"bu":0.6,"bd":16.7},{"i":"porygon_z_shadow","n":"Porygon-Z (Shadow)","f":"HIDDEN_POWER_DRAGON","c":"SOLAR_BEAM","cp":3266,"lv":40,"d":59.82,"d0":55.3,"d1":64.52,"dp":100,"m":0,"m0":0,"m1":0,"td":600,"td0":600,"td1":600,"e":0.06,"e0":0.05,"e1":0.06,"tw":10.1,"er":106.46,"bu":0.6,"bd":16.7},{"i":"porygon_z_shadow","n":"Porygon-Z (Shadow)","f":"HIDDEN_POWER_ELECTRIC","c":"ZAP_CANNON","cp":3266,"lv":40,"d":59.91,"d0":55.3,"d1":64.52,"dp":100,"m":0,"m0":0,"m1":0,"td":600,"td0":600,"td1":600,"e":0.06,"e0":0.05,"e1":0.06,"tw":10.1,"er":106.57,"bu":0.6,"bd":16.7},{"i":"porygon_z_shadow","n":"Porygon-Z (Shadow)","f":"HIDDEN_POWER_FIGHTING","c":"SOLAR_BEAM","cp":3266,"lv":40,"d":60.28,"d0":55.3,"d1":64.52,"dp":100,"m":0,"m0":0,"m1":0,"td":600,"td0":600,"td1":600,"e":0.06,"e0":0.05,"e1":0.06,"tw":10,"er":107.07,"bu":0.6,"bd":16.7},{"i":"porygon_z_shadow","n":"Porygon-Z (Shadow)","f":"HIDDEN_POWER_FLYING","c":"SOLAR_BEAM","cp":3266,"lv":40,"d":59.72,"d0":55.3,"d1":64.52,"dp":100,"m":0,"m0":0,"m1":0,"td":600,"td0":600,"td1":600,"e":0.06,"e0":0.05,"e1":0.06,"tw":10.1,"er":106.33,"bu":0.6,"bd":16.7},{"i":"porygon_z_shadow","n":"Porygon-Z (Shadow)","f":"HIDDEN_POWER_GHOST","c":"SOLAR_BEAM","cp":3266,"lv":40,"d":59.79,"d0":55.3,"d1":64.52,"dp":100,"m":0,"m0":0,"m1":0,"td":600,"td0":600,"td1":600,"e":0.06,"e0":0.05,"e1":0.06,"tw":10.1,"er":106.42,"bu":0.6,"bd":16.7},{"i":"porygon_z_shadow","n":"Porygon-Z (Shadow)","f":"HIDDEN_POWER_GRASS","c":"SOLAR_BEAM","cp":3266,"lv":40,"d":59.42,"d0":55.3,"d1":64.52,"dp":100,"m":0,"m0":0,"m1":0,"td":600,"td0":600,"td1":600,"e":0.06,"e0":0.05,"e1":0.06,"tw":10.2,"er":105.92,"bu":0.5,"bd":16.7},{"i":"porygon_z_shadow","n":"Porygon-Z (Shadow)","f":"HIDDEN_POWER_GROUND","c":"SOLAR_BEAM","cp":3266,"lv":40,"d":59.86,"d0":55.3,"d1":64.52,"dp":100,"m":0,"m0":0,"m1":0,"td":600,"td0":600,"td1":600,"e":0.06,"e0":0.05,"e1":0.06,"tw":10.1,"er":106.51,"bu":0.6,"bd":16.7},{"i":"porygon_z_shadow","n":"Porygon-Z (Shadow)","f":"HIDDEN_POWER_POISON","c":"SOLAR_BEAM","cp":3266,"lv":40,"d":60.06,"d0":55.3,"d1":64.52,"dp":100,"m":0,"m0":0,"m1":0,"td":600,"td0":600,"td1":600,"e":0.06,"e0":0.05,"e1":0.06,"tw":10,"er":106.77,"bu":0.6,"bd":16.7},{"i":"porygon_z_shadow","n":"Porygon-Z (Shadow)","f":"HIDDEN_POWER_PSYCHIC","c":"SOLAR_BEAM","cp":3266,"lv":40,"d":60.21,"d0":55.3,"d1":64.52,"dp":100,"m":0,"m0":0,"m1":0,"td":600,"td0":600,"td1":600,"e":0.06,"e0":0.05,"e1":0.06,"tw":10,"er":106.98,"bu":0.6,"bd":16.7},{"i":"magnezone_shadow","n":"Magnezone (Shadow)","f":"SPARK","c":"ZAP_CANNON","cp":3205,"lv":40,"d":61.48,"d0":48.98,"d1":68.18,"dp":100,"m":0,"m0":0,"m1":0,"td":600,"td0":600,"td1":600,"e":0.06,"e0":0.05,"e1":0.07,"tw":10,"er":108.66,"bu":0.6,"bd":6.1},{"i":"exeggutor_shadow","n":"Exeggutor (Shadow)","f":"CONFUSION","c":"SOLAR_BEAM","cp":3014,"lv":40,"d":59.24,"d0":55.3,"d1":64.52,"dp":100,"m":0,"m0":0,"m1":0,"td":600,"td0":600,"td1":600,"e":0.06,"e0":0.05,"e1":0.06,"tw":10.2,"er":105.68,"bu":0.6,"bd":24.7},{"i":"shaymin_sky","n":"Shaymin (Sky)","f":"HIDDEN_POWER_PSYCHIC","c":"SOLAR_BEAM","cp":3592,"lv":40,"d":59.92,"d0":55.3,"d1":64.52,"dp":100,"m":0,"m0":0,"m1":0,"td":600,"td0":600,"td1":600,"e":0.06,"e0":0.05,"e1":0.06,"tw":10.1,"er":106.6,"bu":0.6,"bd":18},{"i":"shaymin_sky","n":"Shaymin (Sky)","f":"HIDDEN_POWER_ROCK","c":"SOLAR_BEAM","cp":3592,"lv":40,"d":59.71,"d0":55.3,"d1":64.52,"dp":100,"m":0,"m0":0,"m1":0,"td":600,"td0":600,"td1":600,"e":0.06,"e0":0.05,"e1":0.06,"tw":10.1,"er":106.31,"bu":0.6,"bd":18},{"i":"shaymin_sky","n":"Shaymin (Sky)","f":"HIDDEN_POWER_POISON","c":"SOLAR_BEAM","cp":3592,"lv":40,"d":60.01,"d0":55.3,"d1":64.52,"dp":100,"m":0,"m0":0,"m1":0,"td":600,"td0":600,"td1":600,"e":0.06,"e0":0.05,"e1":0.06,"tw":10.1,"er":106.71,"bu":0.6,"bd":18},{"i":"lilligant","n":"Lilligant","f":"HIDDEN_POWER_GRASS","c":"SOLAR_BEAM","cp":2550,"lv":40,"d":60.13,"d0":55.3,"d1":64.52,"dp":100,"m":0,"m0":0,"m1":0,"td":600,"td0":600,"td1":600,"e":0.06,"e0":0.05,"e1":0.06,"tw":10,"er":106.86,"bu":0.6,"bd":24.5},{"i":"meganium_shadow","n":"Meganium (Shadow)","f":"MAGICAL_LEAF","c":"SOLAR_BEAM","cp":2410,"lv":40,"d":61.51,"d0":45.28,"d1":64.52,"dp":100,"m":0,"m0":0,"m1":0,"td":600,"td0":600,"td1":600,"e":0.06,"e0":0.05,"e1":0.07,"tw":9.9,"er":108.7,"bu":0.6,"bd":21},{"i":"porygon_z","n":"Porygon-Z","f":"HIDDEN_POWER_GRASS","c":"SOLAR_BEAM","cp":3266,"lv":40,"d":59.84,"d0":55.3,"d1":64.52,"dp":100,"m":0,"m0":0,"m1":0,"td":600,"td0":600,"td1":600,"e":0.06,"e0":0.05,"e1":0.06,"tw":10.1,"er":106.48,"bu":0.6,"bd":13.7},{"i":"porygon_z","n":"Porygon-Z","f":"HIDDEN_POWER_ELECTRIC","c":"SOLAR_BEAM","cp":3266,"lv":40,"d":59.66,"d0":55.3,"d1":64.52,"dp":100,"m":0,"m0":0,"m1":0,"td":600,"td0":600,"td1":600,"e":0.06,"e0":0.05,"e1":0.06,"tw":10.1,"er":106.24,"bu":0.6,"bd":13.7}],"bubble_surf":[{"i":"zapdos_shadow","n":"Zapdos (Shadow)","f":"THUNDER_SHOCK","c":"ZAP_CANNON","cp":3527,"lv":40,"d":78.13,"d0":77.92,"d1":83.92,"dp":100,"m":0,"m0":0,"m1":0,"td":600,"td0":600,"td1":600,"e":0.04,"e0":0.04,"e1":0.04,"tw":7.7,"er":130.06,"bu":0.1,"bd":17.1},{"i":"regieleki","n":"Regieleki","f":"THUNDER_SHOCK","c":"THUNDER_CAGE","cp":2803,"lv":40,"d":78.12,"d0":77.92,"d1":83.92,"dp":100,"m":0,"m0":0,"m1":0,"td":600,"td0":600,"td1":600,"e":0.04,"e0":0.04,"e1":0.04,"tw":7.7,"er":130.05,"bu":0.2,"bd":22.2},{"i":"regieleki","n":"Regieleki","f":"VOLT_SWITCH","c":"THUNDER_CAGE","cp":2803,"lv":40,"d":77.42,"d0":77.42,"d1":77.42,"dp":100,"m":0,"m0":0,"m1":0,"td":600,"td0":600,"td1":600,"e":0.04,"e0":0.04,"e1":0.04,"tw":7.8,"er":129.17,"bu":0,"bd":22.2},{"i":"porygon_z_shadow","n":"Porygon-Z (Shadow)","f":"CHARGE_BEAM","c":"SOLAR_BEAM","cp":3266,"lv":40,"d":81.63,"d0":81.63,"d1":81.63,"dp":100,"m":0,"m0":0,"m1":0,"td":600,"td0":600,"td1":600,"e":0.04,"e0":0.04,"e1":0.04,"tw":7.3,"er":134.41,"bu":0,"bd":21.4},{"i":"ampharos_mega","n":"Ampharos (Mega)","f":"VOLT_SWITCH","c":"ZAP_CANNON","cp":4245,"lv":40,"d":77.42,"d0":77.42,"d1":77.42,"dp":100,"m":0,"m0":0,"m1":0,"td":600,"td0":600,"td1":600,"e":0.04,"e0":0.04,"e1":0.04,"tw":7.8,"er":129.17,"bu":0,"bd":8.6},{"i":"magnezone_shadow","n":"Magnezone (Shadow)","f":"VOLT_SWITCH","c":"ZAP_CANNON","cp":3205,"lv":40,"d":77.42,"d0":77.42,"d1":77.42,"dp":100,"m":0,"m0":0,"m1":0,"td":600,"td0":600,"td1":600,"e":0.04,"e0":0.04,"e1":0.04,"tw":7.8,"er":129.17,"bu":0,"bd":18.4},{"i":"thundurus_therian","n":"Thundurus (Therian)","f":"VOLT_SWITCH","c":"WILDBOLT_STORM","cp":3659,"lv":40,"d":77.42,"d0":77.42,"d1":77.42,"dp":100,"m":0,"m0":0,"m1":0,"td":600,"td0":600,"td1":600,"e":0.04,"e0":0.04,"e1":0.04,"tw":7.8,"er":129.17,"bu":0,"bd":18.1},{"i":"zapdos_shadow","n":"Zapdos (Shadow)","f":"CHARGE_BEAM","c":"THUNDERBOLT","cp":3527,"lv":40,"d":61.1,"d0":57.97,"d1":64.52,"dp":100,"m":0,"m0":0,"m1":0,"td":600,"td0":600,"td1":600,"e":0.05,"e0":0.05,"e1":0.06,"tw":9.8,"er":108.16,"bu":0.5,"bd":17.1},{"i":"zapdos_shadow","n":"Zapdos (Shadow)","f":"THUNDER_SHOCK","c":"THUNDERBOLT","cp":3527,"lv":40,"d":61.61,"d0":59.11,"d1":62.5,"dp":100,"m":0,"m0":0,"m1":0,"td":600,"td0":600,"td1":600,"e":0.05,"e0":0.05,"e1":0.06,"tw":9.7,"er":108.83,"bu":0.7,"bd":17.1},{"i":"regieleki","n":"Regieleki","f":"LOCK_ON","c":"THUNDER_CAGE","cp":2803,"lv":40,"d":60.91,"d0":60.91,"d1":60.91,"dp":100,"m":0,"m0":0,"m1":0,"td":600,"td0":600,"td1":600,"e":0.05,"e0":0.05,"e1":0.05,"tw":9.9,"er":107.91,"bu":0.5,"bd":22.2},{"i":"magnezone_shadow","n":"Magnezone (Shadow)","f":"VOLT_SWITCH","c":"WILD_CHARGE","cp":3205,"lv":40,"d":62.62,"d0":55.81,"d1":65.22,"dp":100,"m":0,"m0":0,"m1":0,"td":600,"td0":600,"td1":600,"e":0.05,"e0":0.05,"e1":0.06,"tw":9.6,"er":110.17,"bu":0.8,"bd":18.4},{"i":"magnezone_shadow","n":"Magnezone (Shadow)","f":"CHARGE_BEAM","c":"WILD_CHARGE","cp":3205,"lv":40,"d":62.86,"d0":57.97,"d1":64.52,"dp":100,"m":0,"m0":0,"m1":0,"td":600,"td0":600,"td1":600,"e":0.05,"e0":0.05,"e1":0.06,"tw":9.6,"er":110.49,"bu":0.8,"bd":18.4},{"i":"groudon_primal","n":"Groudon (Primal)","f":"MUD_SHOT","c":"SOLAR_BEAM","cp":5902,"lv":40,"d":71.41,"d0":68.18,"d1":72.73,"dp":100,"m":0,"m0":0,"m1":0,"td":600,"td0":600,"td1":600,"e":0.05,"e0":0.05,"e1":0.05,"tw":8.4,"er":121.58,"bu":0,"bd":24.5},{"i":"groudon_shadow","n":"Groudon (Shadow)","f":"MUD_SHOT","c":"SOLAR_BEAM","cp":4115,"lv":40,"d":71.25,"d0":68.18,"d1":72.73,"dp":100,"m":0,"m0":0,"m1":0,"td":600,"td0":600,"td1":600,"e":0.05,"e0":0.05,"e1":0.05,"tw":8.4,"er":121.37,"bu":0,"bd":22.5},{"i":"exeggutor_alolan_shadow","n":"Exeggutor (Alolan) (Shadow)","f":"BULLET_SEED","c":"SOLAR_BEAM","cp":3014,"lv":40,"d":71.43,"d0":71.43,"d1":71.43,"dp":100,"m":0,"m0":0,"m1":0,"td":600,"td0":600,"td1":600,"e":0.05,"e0":0.05,"e1":0.05,"tw":8.4,"er":121.6,"bu":0,"bd":7.7},{"i":"exeggutor_shadow","n":"Exeggutor (Shadow)","f":"BULLET_SEED","c":"SOLAR_BEAM","cp":3014,"lv":40,"d":71.43,"d0":71.43,"d1":71.43,"dp":100,"m":0,"m0":0,"m1":0,"td":600,"td0":600,"td1":600,"e":0.05,"e0":0.05,"e1":0.05,"tw":8.4,"er":121.6,"bu":0,"bd":12.6},{"i":"exeggutor_shadow","n":"Exeggutor (Shadow)","f":"EXTRASENSORY","c":"SOLAR_BEAM","cp":3014,"lv":40,"d":63.49,"d0":63.49,"d1":63.49,"dp":100,"m":0,"m0":0,"m1":0,"td":600,"td0":600,"td1":600,"e":0.05,"e0":0.05,"e1":0.05,"tw":9.4,"er":111.32,"bu":0,"bd":12.6},{"i":"tapu_bulu","n":"Tapu Bulu","f":"BULLET_SEED","c":"SOLAR_BEAM","cp":3419,"lv":40,"d":71.43,"d0":71.43,"d1":71.43,"dp":100,"m":0,"m0":0,"m1":0,"td":600,"td0":600,"td1":600,"e":0.05,"e0":0.05,"e1":0.05,"tw":8.4,"er":121.6,"bu":0,"bd":9.5},{"i":"sceptile_shadow","n":"Sceptile (Shadow)","f":"FURY_CUTTER","c":"FRENZY_PLANT","cp":2757,"lv":40,"d":64.34,"d0":62.5,"d1":66.3,"dp":100,"m":0,"m0":0,"m1":0,"td":600,"td0":600,"td1":600,"e":0.05,"e0":0.05,"e1":0.05,"tw":9.3,"er":112.44,"bu":0.5,"bd":14.3},{"i":"electivire_shadow","n":"Electivire (Shadow)","f":"THUNDER_SHOCK","c":"WILD_CHARGE","cp":3079,"lv":40,"d":64.42,"d0":59.11,"d1":66.3,"dp":100,"m":0,"m0":0,"m1":0,"td":600,"td0":600,"td1":600,"e":0.05,"e0":0.05,"e1":0.06,"tw":9.3,"er":112.53,"bu":0.8,"bd":22.1},{"i":"raikou_shadow","n":"Raikou (Shadow)","f":"VOLT_SWITCH","c":"WILD_CHARGE","cp":3452,"lv":40,"d":62.28,"d0":55.81,"d1":65.22,"dp":100,"m":0,"m0":0,"m1":0,"td":600,"td0":600,"td1":600,"e":0.05,"e0":0.05,"e1":0.06,"tw":9.7,"er":109.72,"bu":0.8,"bd":16.6},{"i":"raikou_shadow","n":"Raikou (Shadow)","f":"THUNDER_SHOCK","c":"THUNDERBOLT","cp":3452,"lv":40,"d":61.83,"d0":59.11,"d1":62.5,"dp":100,"m":0,"m0":0,"m1":0,"td":600,"td0":600,"td1":600,"e":0.05,"e0":0.05,"e1":0.06,"tw":9.7,"er":109.13,"bu":0.8,"bd":16.6},{"i":"raikou_shadow","n":"Raikou (Shadow)","f":"THUNDER_SHOCK","c":"WILD_CHARGE","cp":3452,"lv":40,"d":61.69,"d0":59.11,"d1":62.5,"dp":100,"m":0,"m0":0,"m1":0,"td":600,"td0":600,"td1":600,"e":0.05,"e0":0.05,"e1":0.06,"tw":9.7,"er":108.94,"bu":0.8,"bd":16.6},{"i":"victreebel","n":"Victreebel","f":"MAGICAL_LEAF","c":"SOLAR_BEAM","cp":2431,"lv":40,"d":64.52,"d0":64.52,"d1":64.52,"dp":100,"m":0,"m0":0,"m1":0,"td":600,"td0":600,"td1":600,"e":0.05,"e0":0.05,"e1":0.05,"tw":9.3,"er":112.67,"bu":0,"bd":13},{"i":"victreebel_mega","n":"Victreebel (Mega)","f":"MAGICAL_LEAF","c":"SOLAR_BEAM","cp":3505,"lv":40,"d":64.52,"d0":64.52,"d1":64.52,"dp":100,"m":0,"m0":0,"m1":0,"td":600,"td0":600,"td1":600,"e":0.05,"e0":0.05,"e1":0.05,"tw":9.3,"er":112.67,"bu":0.4,"bd":9.9},{"i":"victreebel_shadow","n":"Victreebel (Shadow)","f":"MAGICAL_LEAF","c":"SOLAR_BEAM","cp":2431,"lv":40,"d":64.52,"d0":64.52,"d1":64.52,"dp":100,"m":0,"m0":0,"m1":0,"td":600,"td0":600,"td1":600,"e":0.05,"e0":0.05,"e1":0.05,"tw":9.3,"er":112.67,"bu":0.3,"bd":15.4},{"i":"meganium_shadow","n":"Meganium (Shadow)","f":"MAGICAL_LEAF","c":"SOLAR_BEAM","cp":2410,"lv":40,"d":64.52,"d0":64.52,"d1":64.52,"dp":100,"m":0,"m0":0,"m1":0,"td":600,"td0":600,"td1":600,"e":0.05,"e0":0.05,"e1":0.05,"tw":9.3,"er":112.67,"bu":0,"bd":11.1},{"i":"ho_oh_shadow","n":"Ho-Oh (Shadow)","f":"HIDDEN_POWER_ELECTRIC","c":"SOLAR_BEAM","cp":3863,"lv":40,"d":64.52,"d0":64.52,"d1":64.52,"dp":100,"m":0,"m0":0,"m1":0,"td":600,"td0":600,"td1":600,"e":0.05,"e0":0.05,"e1":0.05,"tw":9.3,"er":112.67,"bu":0,"bd":20.6},{"i":"ho_oh_shadow","n":"Ho-Oh (Shadow)","f":"HIDDEN_POWER_FLYING","c":"SOLAR_BEAM","cp":3863,"lv":40,"d":64.52,"d0":64.52,"d1":64.52,"dp":100,"m":0,"m0":0,"m1":0,"td":600,"td0":600,"td1":600,"e":0.05,"e0":0.05,"e1":0.05,"tw":9.3,"er":112.67,"bu":0,"bd":20.6},{"i":"ho_oh_shadow","n":"Ho-Oh (Shadow)","f":"HIDDEN_POWER_GRASS","c":"SOLAR_BEAM","cp":3863,"lv":40,"d":64.52,"d0":64.52,"d1":64.52,"dp":100,"m":0,"m0":0,"m1":0,"td":600,"td0":600,"td1":600,"e":0.05,"e0":0.05,"e1":0.05,"tw":9.3,"er":112.67,"bu":0,"bd":20.6},{"i":"manectric_mega","n":"Manectric (Mega)","f":"CHARGE_BEAM","c":"WILD_CHARGE","cp":3580,"lv":40,"d":62.71,"d0":57.97,"d1":64.52,"dp":100,"m":0,"m0":0,"m1":0,"td":600,"td0":600,"td1":600,"e":0.05,"e0":0.05,"e1":0.06,"tw":9.6,"er":110.29,"bu":0.7,"bd":17.7},{"i":"manectric_shadow","n":"Manectric (Shadow)","f":"THUNDER_FANG","c":"WILD_CHARGE","cp":2340,"lv":40,"d":61.2,"d0":57.97,"d1":64.52,"dp":100,"m":0,"m0":0,"m1":0,"td":600,"td0":600,"td1":600,"e":0.05,"e0":0.05,"e1":0.06,"tw":9.8,"er":108.29,"bu":0.5,"bd":28.6},{"i":"roserade","n":"Roserade","f":"MAGICAL_LEAF","c":"SOLAR_BEAM","cp":2971,"lv":40,"d":64.52,"d0":64.52,"d1":64.52,"dp":100,"m":0,"m0":0,"m1":0,"td":600,"td0":600,"td1":600,"e":0.05,"e0":0.05,"e1":0.05,"tw":9.3,"er":112.67,"bu":0.3,"bd":11.9},{"i":"shaymin_land","n":"Shaymin (Land)","f":"MAGICAL_LEAF","c":"SOLAR_BEAM","cp":3265,"lv":40,"d":64.52,"d0":64.52,"d1":64.52,"dp":100,"m":0,"m0":0,"m1":0,"td":600,"td0":600,"td1":600,"e":0.05,"e0":0.05,"e1":0.05,"tw":9.3,"er":112.67,"bu":0,"bd":7.4},{"i":"shaymin_sky","n":"Shaymin (Sky)","f":"MAGICAL_LEAF","c":"SOLAR_BEAM","cp":3592,"lv":40,"d":64.52,"d0":64.52,"d1":64.52,"dp":100,"m":0,"m0":0,"m1":0,"td":600,"td0":600,"td1":600,"e":0.05,"e0":0.05,"e1":0.05,"tw":9.3,"er":112.67,"bu":0.3,"bd":9.5},{"i":"lilligant","n":"Lilligant","f":"MAGICAL_LEAF","c":"SOLAR_BEAM","cp":2550,"lv":40,"d":64.52,"d0":64.52,"d1":64.52,"dp":100,"m":0,"m0":0,"m1":0,"td":600,"td0":600,"td1":600,"e":0.05,"e0":0.05,"e1":0.05,"tw":9.3,"er":112.67,"bu":0,"bd":12.9},{"i":"lilligant_hisuian","n":"Lilligant (Hisuian)","f":"MAGICAL_LEAF","c":"SOLAR_BEAM","cp":2512,"lv":40,"d":64.52,"d0":64.52,"d1":64.52,"dp":100,"m":0,"m0":0,"m1":0,"td":600,"td0":600,"td1":600,"e":0.05,"e0":0.05,"e1":0.05,"tw":9.3,"er":112.67,"bu":0,"bd":12.2},{"i":"tangela_shadow","n":"Tangela (Shadow)","f":"VINE_WHIP","c":"SOLAR_BEAM","cp":2238,"lv":40,"d":60.93,"d0":57.42,"d1":64.17,"dp":100,"m":0,"m0":0,"m1":0,"td":600,"td0":600,"td1":600,"e":0.05,"e0":0.05,"e1":0.06,"tw":9.9,"er":107.94,"bu":0.6,"bd":15},{"i":"deoxys_attack","n":"Deoxys (Attack)","f":"POISON_JAB","c":"ZAP_CANNON","cp":2580,"lv":40,"d":63.43,"d0":29.53,"d1":63.49,"dp":100,"m":0,"m0":0,"m1":1,"td":600,"td0":600,"td1":600,"e":0.05,"e0":0.05,"e1":0.11,"tw":9.5,"er":111.24,"bu":0.1,"bd":67.5},{"i":"deoxys_attack","n":"Deoxys (Attack)","f":"ZEN_HEADBUTT","c":"ZAP_CANNON","cp":2580,"lv":40,"d":63.43,"d0":29.46,"d1":63.49,"dp":100,"m":0,"m0":0,"m1":1,"td":600,"td0":600,"td1":600,"e":0.05,"e0":0.05,"e1":0.11,"tw":9.5,"er":111.24,"bu":0.1,"bd":67.5},{"i":"sceptile_mega","n":"Sceptile (Mega)","f":"FURY_CUTTER","c":"FRENZY_PLANT","cp":4056,"lv":40,"d":61.68,"d0":59.11,"d1":62.5,"dp":100,"m":0,"m0":0,"m1":0,"td":600,"td0":600,"td1":600,"e":0.05,"e0":0.05,"e1":0.06,"tw":9.7,"er":108.93,"bu":0.8,"bd":6.8},{"i":"xurkitree","n":"Xurkitree","f":"THUNDER_SHOCK","c":"POWER_WHIP","cp":3937,"lv":40,"d":61.67,"d0":59.11,"d1":62.5,"dp":100,"m":0,"m0":0,"m1":0,"td":600,"td0":600,"td1":600,"e":0.05,"e0":0.05,"e1":0.06,"tw":9.7,"er":108.91,"bu":0.8,"bd":19.4},{"i":"porygon_z_shadow","n":"Porygon-Z (Shadow)","f":"HIDDEN_POWER_ELECTRIC","c":"SOLAR_BEAM","cp":3266,"lv":40,"d":58.62,"d0":55.3,"d1":64.52,"dp":100,"m":0,"m0":0,"m1":0,"td":600,"td0":600,"td1":600,"e":0.06,"e0":0.05,"e1":0.06,"tw":10.3,"er":104.85,"bu":0.5,"bd":21.4},{"i":"porygon_z_shadow","n":"Porygon-Z (Shadow)","f":"HIDDEN_POWER_BUG","c":"SOLAR_BEAM","cp":3266,"lv":40,"d":55.32,"d0":55.3,"d1":64.52,"dp":100,"m":0,"m0":0,"m1":0,"td":600,"td0":600,"td1":600,"e":0.06,"e0":0.05,"e1":0.06,"tw":10.8,"er":100.39,"bu":0.2,"bd":21.4},{"i":"porygon_z_shadow","n":"Porygon-Z (Shadow)","f":"HIDDEN_POWER_ELECTRIC","c":"ZAP_CANNON","cp":3266,"lv":40,"d":58.5,"d0":55.3,"d1":64.52,"dp":100,"m":0,"m0":0,"m1":0,"td":600,"td0":600,"td1":600,"e":0.06,"e0":0.05,"e1":0.06,"tw":10.3,"er":104.69,"bu":0.5,"bd":21.4},{"i":"porygon_z_shadow","n":"Porygon-Z (Shadow)","f":"HIDDEN_POWER_GRASS","c":"SOLAR_BEAM","cp":3266,"lv":40,"d":58.43,"d0":55.3,"d1":64.52,"dp":100,"m":0,"m0":0,"m1":0,"td":600,"td0":600,"td1":600,"e":0.06,"e0":0.05,"e1":0.06,"tw":10.3,"er":104.6,"bu":0.5,"bd":21.4},{"i":"porygon_z_shadow","n":"Porygon-Z (Shadow)","f":"HIDDEN_POWER_GRASS","c":"ZAP_CANNON","cp":3266,"lv":40,"d":58.5,"d0":55.3,"d1":64.52,"dp":100,"m":0,"m0":0,"m1":0,"td":600,"td0":600,"td1":600,"e":0.06,"e0":0.05,"e1":0.06,"tw":10.3,"er":104.69,"bu":0.5,"bd":21.4},{"i":"magnezone_shadow","n":"Magnezone (Shadow)","f":"SPARK","c":"ZAP_CANNON","cp":3205,"lv":40,"d":61.02,"d0":48.98,"d1":68.18,"dp":100,"m":0,"m0":0,"m1":0,"td":600,"td0":600,"td1":600,"e":0.06,"e0":0.05,"e1":0.07,"tw":10.1,"er":108.06,"bu":0.5,"bd":18.4},{"i":"thundurus_therian","n":"Thundurus (Therian)","f":"VOLT_SWITCH","c":"THUNDERBOLT","cp":3659,"lv":40,"d":60.64,"d0":55.81,"d1":65.22,"dp":100,"m":0,"m0":0,"m1":0,"td":600,"td0":600,"td1":600,"e":0.06,"e0":0.05,"e1":0.06,"tw":10,"er":107.54,"bu":0.6,"bd":18.1},{"i":"raikou_shadow","n":"Raikou (Shadow)","f":"VOLT_SWITCH","c":"THUNDERBOLT","cp":3452,"lv":40,"d":60.58,"d0":55.81,"d1":65.22,"dp":100,"m":0,"m0":0,"m1":0,"td":600,"td0":600,"td1":600,"e":0.06,"e0":0.05,"e1":0.06,"tw":10,"er":107.47,"bu":0.6,"bd":16.6},{"i":"meganium_shadow","n":"Meganium (Shadow)","f":"VINE_WHIP","c":"SOLAR_BEAM","cp":2410,"lv":40,"d":59.07,"d0":57.42,"d1":60.61,"dp":100,"m":0,"m0":0,"m1":0,"td":600,"td0":600,"td1":600,"e":0.06,"e0":0.06,"e1":0.06,"tw":10.2,"er":105.46,"bu":0.6,"bd":11.1},{"i":"manectric_mega","n":"Manectric (Mega)","f":"SNARL","c":"WILD_CHARGE","cp":3580,"lv":40,"d":57.97,"d0":57.97,"d1":57.97,"dp":100,"m":0,"m0":0,"m1":0,"td":600,"td0":600,"td1":600,"e":0.06,"e0":0.06,"e1":0.06,"tw":10.4,"er":103.98,"bu":0.5,"bd":17.7},{"i":"shaymin_sky","n":"Shaymin (Sky)","f":"HIDDEN_POWER_GRASS","c":"SOLAR_BEAM","cp":3592,"lv":40,"d":58.53,"d0":55.3,"d1":64.52,"dp":100,"m":0,"m0":0,"m1":0,"td":600,"td0":600,"td1":600,"e":0.06,"e0":0.05,"e1":0.06,"tw":10.3,"er":104.74,"bu":0.5,"bd":9.5},{"i":"shaymin_sky","n":"Shaymin (Sky)","f":"HIDDEN_POWER_DARK","c":"SOLAR_BEAM","cp":3592,"lv":40,"d":55.3,"d0":55.3,"d1":55.3,"dp":100,"m":0,"m0":0,"m1":0,"td":600,"td0":600,"td1":600,"e":0.06,"e0":0.06,"e1":0.06,"tw":10.9,"er":100.36,"bu":0.2,"bd":9.5},{"i":"xurkitree","n":"Xurkitree","f":"SPARK","c":"POWER_WHIP","cp":3937,"lv":40,"d":57.76,"d0":50.85,"d1":59.11,"dp":100,"m":0,"m0":0,"m1":0,"td":600,"td0":600,"td1":600,"e":0.06,"e0":0.06,"e1":0.07,"tw":10.4,"er":103.69,"bu":0.9,"bd":19.4}]}